Workbook
Name \A: #REF!
Name \A: #REF!
Name \A: #REF!
Name \A: #REF!
Name \B: #REF!
Name \B: #REF!
Name \B: #REF!
Name \C: #REF!
Name \C: #REF!
Name \C: #REF!
Name \D: #REF!
Name \D: #REF!
Name \D: #REF!
Name \D: #REF!
Name \E: #REF!
Name \E: #REF!
Name \E: #REF!
Name \E: #REF!
Name \F: #REF!
Name \F: #REF!
Name \F: #REF!
Name \F: #REF!
Name \G: #REF!
Name \G: #REF!
Name \G: #REF!
Name \G: #REF!
Name \H: #REF!
Name \H: #REF!
Name \H: #REF!
Name \H: #REF!
Name \I: #REF!
Name \I: #REF!
Name \I: #REF!
Name \I: #REF!
Name \J: #REF!
Name \J: #REF!
Name \J: #REF!
Name \J: #REF!
Name \K: #REF!
Name \K: #REF!
Name \K: #REF!
Name \K: #REF!
Name \L: #REF!
Name \L: #REF!
Name \L: #REF!
Name \L: #REF!
Name \LX1: #REF!
Name \LX1: #REF!
Name \LX1: #REF!
Name \LX1: #REF!
Name \M: #REF!
Name \M: #REF!
Name \M: #REF!
Name \M: #REF!
Name \P: #REF!
Name \P: #REF!
Name \P: #REF!
Name \P: #REF!
Name \Q: #REF!
Name \Q: #REF!

Sheet REKAP MATERIAL
C1: PT. PLN ( PERSERO )
C2: =RAB!C2 -> UNIT INDUK DISTRIBUSI JAWA TENGAH & DI YOGYAKARTA
B4: REKAP KEBUTUHAN MATERIAL
B7: NO | C7: URAIAN | D7: GOL | E7: SAT | F7: VOL TOTAL | G7: HARGA SATUAN | H7: LOKASI | I7: NO PRK | J7: NAMA PROGRAM | K7: INISIATIF STRATEGIS
B11: + | C11: REKAP MATERIAL
A12: 1 | B12: =IF(C12="","",A12) -> 1 | C12: =IF(ISERROR(OFFSET($C$713,MATCH(A12,$F$714:$F$1320,0),0)),"",OFFSET($C$713,MATCH(A12,$F$714:$F$1320,0),0)) -> KWH Elektronik; 3P; 4W; 220/380V; 5(10); kls 1 (Pengukuran Tidak Langsung) | D12: =IF(ISERROR(OFFSET('HARGA SATUAN'!$D$6,MATCH(C12,'HARGA SATUAN'!$C$7:$C$1492,0),0)),"",OFFSET('HARGA SATUAN'!$D$6,MATCH(C12,'HARGA SATUAN'!$C$7:$C$1492,0),0)) -> MDU-KD | E12: =IF(B12="+","Unit",IF(ISERROR(OFFSET('HARGA SATUAN'!$E$6,MATCH(C12,'HARGA SATUAN'!$C$7:$C$1492,0),0)),"",OFFSET('HARGA SATUAN'!$E$6,MATCH(C12,'HARGA SATUAN'!$C$7:$C$1492,0),0))) -> Bh | F12: =IF(ISERROR(OFFSET($D$713,MATCH(A12,$F$714:$F$1320,0),0)),"",OFFSET($D$713,MATCH(A12,$F$714:$F$1320,0),0)) -> 1 | G12: =IF(ISERROR(OFFSET('HARGA SATUAN'!$I$6,MATCH(C12,'HARGA SATUAN'!$C$7:$C$1492,0),0)),"",OFFSET('HARGA SATUAN'!$I$6,MATCH(C12,'HARGA SATUAN'!$C$7:$C$1492,0),0)) -> 1504200 | H12: =IF(B12="","",#REF!) -> #REF! | I12: =IF(B12="","",#REF!) -> #REF! | J12: =IF(B12="","",#REF!) -> #REF! | K12: =IF(B12="","",#REF!) -> #REF! | L12: =IF(C12="","",#REF!) -> #REF!
A13: 2 | B13: =IF(C13="","",A13) -> 2 | C13: =IF(ISERROR(OFFSET($C$713,MATCH(A13,$F$714:$F$1320,0),0)),"",OFFSET($C$713,MATCH(A13,$F$714:$F$1320,0),0)) -> Smart Box Tidak Langsung Daya 105 kVA MCCB 160 A | D13: =IF(ISERROR(OFFSET('HARGA SATUAN'!$D$6,MATCH(C13,'HARGA SATUAN'!$C$7:$C$1492,0),0)),"",OFFSET('HARGA SATUAN'!$D$6,MATCH(C13,'HARGA SATUAN'!$C$7:$C$1492,0),0)) -> MDU-KD | E13: =IF(B13="+","Unit",IF(ISERROR(OFFSET('HARGA SATUAN'!$E$6,MATCH(C13,'HARGA SATUAN'!$C$7:$C$1492,0),0)),"",OFFSET('HARGA SATUAN'!$E$6,MATCH(C13,'HARGA SATUAN'!$C$7:$C$1492,0),0))) -> Unit | F13: =IF(ISERROR(OFFSET($D$713,MATCH(A13,$F$714:$F$1320,0),0)),"",OFFSET($D$713,MATCH(A13,$F$714:$F$1320,0),0)) -> 1 | G13: =IF(ISERROR(OFFSET('HARGA SATUAN'!$I$6,MATCH(C13,'HARGA SATUAN'!$C$7:$C$1492,0),0)),"",OFFSET('HARGA SATUAN'!$I$6,MATCH(C13,'HARGA SATUAN'!$C$7:$C$1492,0),0)) -> 14217900 | H13: =IF(B13="","",#REF!) -> #REF! | I13: =IF(B13="","",#REF!) -> #REF! | J13: =IF(B13="","",#REF!) -> #REF! | K13: =IF(B13="","",#REF!) -> #REF! | L13: =IF(C13="","",#REF!) -> #REF!
A14: 3 | B14: =IF(C14="","",A14) -> 3 | C14: =IF(ISERROR(OFFSET($C$713,MATCH(A14,$F$714:$F$1320,0),0)),"",OFFSET($C$713,MATCH(A14,$F$714:$F$1320,0),0)) -> Trafo 3 phasa 100 kVA YNyn0 | D14: =IF(ISERROR(OFFSET('HARGA SATUAN'!$D$6,MATCH(C14,'HARGA SATUAN'!$C$7:$C$1492,0),0)),"",OFFSET('HARGA SATUAN'!$D$6,MATCH(C14,'HARGA SATUAN'!$C$7:$C$1492,0),0)) -> MDU-KD | E14: =IF(B14="+","Unit",IF(ISERROR(OFFSET('HARGA SATUAN'!$E$6,MATCH(C14,'HARGA SATUAN'!$C$7:$C$1492,0),0)),"",OFFSET('HARGA SATUAN'!$E$6,MATCH(C14,'HARGA SATUAN'!$C$7:$C$1492,0),0))) -> Bh | F14: =IF(ISERROR(OFFSET($D$713,MATCH(A14,$F$714:$F$1320,0),0)),"",OFFSET($D$713,MATCH(A14,$F$714:$F$1320,0),0)) -> 1 | G14: =IF(ISERROR(OFFSET('HARGA SATUAN'!$I$6,MATCH(C14,'HARGA SATUAN'!$C$7:$C$1492,0),0)),"",OFFSET('HARGA SATUAN'!$I$6,MATCH(C14,'HARGA SATUAN'!$C$7:$C$1492,0),0)) -> 56838600 | H14: =IF(B14="","",#REF!) -> #REF! | I14: =IF(B14="","",#REF!) -> #REF! | J14: =IF(B14="","",#REF!) -> #REF! | K14: =IF(B14="","",#REF!) -> #REF! | L14: =IF(C14="","",#REF!) -> #REF!
A15: 4 | B15: =IF(C15="","",A15) -> 4 | C15: =IF(ISERROR(OFFSET($C$713,MATCH(A15,$F$714:$F$1320,0),0)),"",OFFSET($C$713,MATCH(A15,$F$714:$F$1320,0),0)) -> FCO Polymer | D15: =IF(ISERROR(OFFSET('HARGA SATUAN'!$D$6,MATCH(C15,'HARGA SATUAN'!$C$7:$C$1492,0),0)),"",OFFSET('HARGA SATUAN'!$D$6,MATCH(C15,'HARGA SATUAN'!$C$7:$C$1492,0),0)) -> MDU-KD | E15: =IF(B15="+","Unit",IF(ISERROR(OFFSET('HARGA SATUAN'!$E$6,MATCH(C15,'HARGA SATUAN'!$C$7:$C$1492,0),0)),"",OFFSET('HARGA SATUAN'!$E$6,MATCH(C15,'HARGA SATUAN'!$C$7:$C$1492,0),0))) -> Bh | F15: =IF(ISERROR(OFFSET($D$713,MATCH(A15,$F$714:$F$1320,0),0)),"",OFFSET($D$713,MATCH(A15,$F$714:$F$1320,0),0)) -> 3 | G15: =IF(ISERROR(OFFSET('HARGA SATUAN'!$I$6,MATCH(C15,'HARGA SATUAN'!$C$7:$C$1492,0),0)),"",OFFSET('HARGA SATUAN'!$I$6,MATCH(C15,'HARGA SATUAN'!$C$7:$C$1492,0),0)) -> 848250 | H15: =IF(B15="","",#REF!) -> #REF! | I15: =IF(B15="","",#REF!) -> #REF! | J15: =IF(B15="","",#REF!) -> #REF! | K15: =IF(B15="","",#REF!) -> #REF! | L15: =IF(C15="","",#REF!) -> #REF!
A16: 5 | B16: =IF(C16="","",A16) -> 5 | C16: =IF(ISERROR(OFFSET($C$713,MATCH(A16,$F$714:$F$1320,0),0)),"",OFFSET($C$713,MATCH(A16,$F$714:$F$1320,0),0)) -> Lightning Arester (Polymer) 21 KV, 10 KA | D16: =IF(ISERROR(OFFSET('HARGA SATUAN'!$D$6,MATCH(C16,'HARGA SATUAN'!$C$7:$C$1492,0),0)),"",OFFSET('HARGA SATUAN'!$D$6,MATCH(C16,'HARGA SATUAN'!$C$7:$C$1492,0),0)) -> MDU-KD | E16: =IF(B16="+","Unit",IF(ISERROR(OFFSET('HARGA SATUAN'!$E$6,MATCH(C16,'HARGA SATUAN'!$C$7:$C$1492,0),0)),"",OFFSET('HARGA SATUAN'!$E$6,MATCH(C16,'HARGA SATUAN'!$C$7:$C$1492,0),0))) -> Bh | F16: =IF(ISERROR(OFFSET($D$713,MATCH(A16,$F$714:$F$1320,0),0)),"",OFFSET($D$713,MATCH(A16,$F$714:$F$1320,0),0)) -> 3 | G16: =IF(ISERROR(OFFSET('HARGA SATUAN'!$I$6,MATCH(C16,'HARGA SATUAN'!$C$7:$C$1492,0),0)),"",OFFSET('HARGA SATUAN'!$I$6,MATCH(C16,'HARGA SATUAN'!$C$7:$C$1492,0),0)) -> 725900 | H16: =IF(B16="","",#REF!) -> #REF! | I16: =IF(B16="","",#REF!) -> #REF! | J16: =IF(B16="","",#REF!) -> #REF! | K16: =IF(B16="","",#REF!) -> #REF! | L16: =IF(C16="","",#REF!) -> #REF!
A17: 6 | B17: =IF(C17="","",A17) -> 6 | C17: =IF(ISERROR(OFFSET($C$713,MATCH(A17,$F$714:$F$1320,0),0)),"",OFFSET($C$713,MATCH(A17,$F$714:$F$1320,0),0)) -> Isolator Tumpu ( Pin Post ) 20 KV Porcelein | D17: =IF(ISERROR(OFFSET('HARGA SATUAN'!$D$6,MATCH(C17,'HARGA SATUAN'!$C$7:$C$1492,0),0)),"",OFFSET('HARGA SATUAN'!$D$6,MATCH(C17,'HARGA SATUAN'!$C$7:$C$1492,0),0)) -> MDU-KD | E17: =IF(B17="+","Unit",IF(ISERROR(OFFSET('HARGA SATUAN'!$E$6,MATCH(C17,'HARGA SATUAN'!$C$7:$C$1492,0),0)),"",OFFSET('HARGA SATUAN'!$E$6,MATCH(C17,'HARGA SATUAN'!$C$7:$C$1492,0),0))) -> Bh | F17: =IF(ISERROR(OFFSET($D$713,MATCH(A17,$F$714:$F$1320,0),0)),"",OFFSET($D$713,MATCH(A17,$F$714:$F$1320,0),0)) -> 3 | G17: =IF(ISERROR(OFFSET('HARGA SATUAN'!$I$6,MATCH(C17,'HARGA SATUAN'!$C$7:$C$1492,0),0)),"",OFFSET('HARGA SATUAN'!$I$6,MATCH(C17,'HARGA SATUAN'!$C$7:$C$1492,0),0)) -> 235900 | H17: =IF(B17="","",#REF!) -> #REF! | I17: =IF(B17="","",#REF!) -> #REF! | J17: =IF(B17="","",#REF!) -> #REF! | K17: =IF(B17="","",#REF!) -> #REF! | L17: =IF(C17="","",#REF!) -> #REF!
A18: 7 | B18: =IF(C18="","",A18) -> 7 | C18: =IF(ISERROR(OFFSET($C$713,MATCH(A18,$F$714:$F$1320,0),0)),"",OFFSET($C$713,MATCH(A18,$F$714:$F$1320,0),0)) -> Isolator Tarik ( Suspension Polymer ) 20 KV | D18: =IF(ISERROR(OFFSET('HARGA SATUAN'!$D$6,MATCH(C18,'HARGA SATUAN'!$C$7:$C$1492,0),0)),"",OFFSET('HARGA SATUAN'!$D$6,MATCH(C18,'HARGA SATUAN'!$C$7:$C$1492,0),0)) -> MDU-KD | E18: =IF(B18="+","Unit",IF(ISERROR(OFFSET('HARGA SATUAN'!$E$6,MATCH(C18,'HARGA SATUAN'!$C$7:$C$1492,0),0)),"",OFFSET('HARGA SATUAN'!$E$6,MATCH(C18,'HARGA SATUAN'!$C$7:$C$1492,0),0))) -> Set | F18: =IF(ISERROR(OFFSET($D$713,MATCH(A18,$F$714:$F$1320,0),0)),"",OFFSET($D$713,MATCH(A18,$F$714:$F$1320,0),0)) -> 6 | G18: =IF(ISERROR(OFFSET('HARGA SATUAN'!$I$6,MATCH(C18,'HARGA SATUAN'!$C$7:$C$1492,0),0)),"",OFFSET('HARGA SATUAN'!$I$6,MATCH(C18,'HARGA SATUAN'!$C$7:$C$1492,0),0)) -> 205700 | H18: =IF(B18="","",#REF!) -> #REF! | I18: =IF(B18="","",#REF!) -> #REF! | J18: =IF(B18="","",#REF!) -> #REF! | K18: =IF(B18="","",#REF!) -> #REF! | L18: =IF(C18="","",#REF!) -> #REF!
A19: 8 | B19: =IF(C19="","",A19) -> 8 | C19: =IF(ISERROR(OFFSET($C$713,MATCH(A19,$F$714:$F$1320,0),0)),"",OFFSET($C$713,MATCH(A19,$F$714:$F$1320,0),0)) -> AAAC 70 mm² | D19: =IF(ISERROR(OFFSET('HARGA SATUAN'!$D$6,MATCH(C19,'HARGA SATUAN'!$C$7:$C$1492,0),0)),"",OFFSET('HARGA SATUAN'!$D$6,MATCH(C19,'HARGA SATUAN'!$C$7:$C$1492,0),0)) -> MDU-KD | E19: =IF(B19="+","Unit",IF(ISERROR(OFFSET('HARGA SATUAN'!$E$6,MATCH(C19,'HARGA SATUAN'!$C$7:$C$1492,0),0)),"",OFFSET('HARGA SATUAN'!$E$6,MATCH(C19,'HARGA SATUAN'!$C$7:$C$1492,0),0))) -> Mtr | F19: =IF(ISERROR(OFFSET($D$713,MATCH(A19,$F$714:$F$1320,0),0)),"",OFFSET($D$713,MATCH(A19,$F$714:$F$1320,0),0)) -> 229 | G19: =IF(ISERROR(OFFSET('HARGA SATUAN'!$I$6,MATCH(C19,'HARGA SATUAN'!$C$7:$C$1492,0),0)),"",OFFSET('HARGA SATUAN'!$I$6,MATCH(C19,'HARGA SATUAN'!$C$7:$C$1492,0),0)) -> 14200 | H19: =IF(B19="","",#REF!) -> #REF! | I19: =IF(B19="","",#REF!) -> #REF! | J19: =IF(B19="","",#REF!) -> #REF! | K19: =IF(B19="","",#REF!) -> #REF! | L19: =IF(C19="","",#REF!) -> #REF!
A20: 9 | B20: =IF(C20="","",A20) -> 9 | C20: =IF(ISERROR(OFFSET($C$713,MATCH(A20,$F$714:$F$1320,0),0)),"",OFFSET($C$713,MATCH(A20,$F$714:$F$1320,0),0)) -> NFA2X-T 3x70+1x70 | D20: =IF(ISERROR(OFFSET('HARGA SATUAN'!$D$6,MATCH(C20,'HARGA SATUAN'!$C$7:$C$1492,0),0)),"",OFFSET('HARGA SATUAN'!$D$6,MATCH(C20,'HARGA SATUAN'!$C$7:$C$1492,0),0)) -> MDU-KD | E20: =IF(B20="+","Unit",IF(ISERROR(OFFSET('HARGA SATUAN'!$E$6,MATCH(C20,'HARGA SATUAN'!$C$7:$C$1492,0),0)),"",OFFSET('HARGA SATUAN'!$E$6,MATCH(C20,'HARGA SATUAN'!$C$7:$C$1492,0),0))) -> Mtr | F20: =IF(ISERROR(OFFSET($D$713,MATCH(A20,$F$714:$F$1320,0),0)),"",OFFSET($D$713,MATCH(A20,$F$714:$F$1320,0),0)) -> 12 | G20: =IF(ISERROR(OFFSET('HARGA SATUAN'!$I$6,MATCH(C20,'HARGA SATUAN'!$C$7:$C$1492,0),0)),"",OFFSET('HARGA SATUAN'!$I$6,MATCH(C20,'HARGA SATUAN'!$C$7:$C$1492,0),0)) -> 54500 | H20: =IF(B20="","",#REF!) -> #REF! | I20: =IF(B20="","",#REF!) -> #REF! | J20: =IF(B20="","",#REF!) -> #REF! | K20: =IF(B20="","",#REF!) -> #REF! | L20: =IF(C20="","",#REF!) -> #REF!
A21: 10 | B21: =IF(C21="","",A21) -> 10 | C21: =IF(ISERROR(OFFSET($C$713,MATCH(A21,$F$714:$F$1320,0),0)),"",OFFSET($C$713,MATCH(A21,$F$714:$F$1320,0),0)) -> Modem 3G/4G | D21: =IF(ISERROR(OFFSET('HARGA SATUAN'!$D$6,MATCH(C21,'HARGA SATUAN'!$C$7:$C$1492,0),0)),"",OFFSET('HARGA SATUAN'!$D$6,MATCH(C21,'HARGA SATUAN'!$C$7:$C$1492,0),0)) -> HDW | E21: =IF(B21="+","Unit",IF(ISERROR(OFFSET('HARGA SATUAN'!$E$6,MATCH(C21,'HARGA SATUAN'!$C$7:$C$1492,0),0)),"",OFFSET('HARGA SATUAN'!$E$6,MATCH(C21,'HARGA SATUAN'!$C$7:$C$1492,0),0))) -> Unit | F21: =IF(ISERROR(OFFSET($D$713,MATCH(A21,$F$714:$F$1320,0),0)),"",OFFSET($D$713,MATCH(A21,$F$714:$F$1320,0),0)) -> 1 | G21: =IF(ISERROR(OFFSET('HARGA SATUAN'!$I$6,MATCH(C21,'HARGA SATUAN'!$C$7:$C$1492,0),0)),"",OFFSET('HARGA SATUAN'!$I$6,MATCH(C21,'HARGA SATUAN'!$C$7:$C$1492,0),0)) -> 1113900 | H21: =IF(B21="","",#REF!) -> #REF! | I21: =IF(B21="","",#REF!) -> #REF! | J21: =IF(B21="","",#REF!) -> #REF! | K21: =IF(B21="","",#REF!) -> #REF! | L21: =IF(C21="","",#REF!) -> #REF!
A22: 11 | B22: =IF(C22="","",A22) | C22: =IF(ISERROR(OFFSET($C$713,MATCH(A22,$F$714:$F$1320,0),0)),"",OFFSET($C$713,MATCH(A22,$F$714:$F$1320,0),0)) | D22: =IF(ISERROR(OFFSET('HARGA SATUAN'!$D$6,MATCH(C22,'HARGA SATUAN'!$C$7:$C$1492,0),0)),"",OFFSET('HARGA SATUAN'!$D$6,MATCH(C22,'HARGA SATUAN'!$C$7:$C$1492,0),0)) | E22: =IF(B22="+","Unit",IF(ISERROR(OFFSET('HARGA SATUAN'!$E$6,MATCH(C22,'HARGA SATUAN'!$C$7:$C$1492,0),0)),"",OFFSET('HARGA SATUAN'!$E$6,MATCH(C22,'HARGA SATUAN'!$C$7:$C$1492,0),0))) -> 0 | F22: =IF(ISERROR(OFFSET($D$713,MATCH(A22,$F$714:$F$1320,0),0)),"",OFFSET($D$713,MATCH(A22,$F$714:$F$1320,0),0)) | G22: =IF(ISERROR(OFFSET('HARGA SATUAN'!$I$6,MATCH(C22,'HARGA SATUAN'!$C$7:$C$1492,0),0)),"",OFFSET('HARGA SATUAN'!$I$6,MATCH(C22,'HARGA SATUAN'!$C$7:$C$1492,0),0)) -> 0 | H22: =IF(B22="","",#REF!) | I22: =IF(B22="","",#REF!) | J22: =IF(B22="","",#REF!) | K22: =IF(B22="","",#REF!) | L22: =IF(C22="","",#REF!)
A23: 12 | B23: =IF(C23="","",A23) | C23: =IF(ISERROR(OFFSET($C$713,MATCH(A23,$F$714:$F$1320,0),0)),"",OFFSET($C$713,MATCH(A23,$F$714:$F$1320,0),0)) | D23: =IF(ISERROR(OFFSET('HARGA SATUAN'!$D$6,MATCH(C23,'HARGA SATUAN'!$C$7:$C$1492,0),0)),"",OFFSET('HARGA SATUAN'!$D$6,MATCH(C23,'HARGA SATUAN'!$C$7:$C$1492,0),0)) | E23: =IF(B23="+","Unit",IF(ISERROR(OFFSET('HARGA SATUAN'!$E$6,MATCH(C23,'HARGA SATUAN'!$C$7:$C$1492,0),0)),"",OFFSET('HARGA SATUAN'!$E$6,MATCH(C23,'HARGA SATUAN'!$C$7:$C$1492,0),0))) -> 0 | F23: =IF(ISERROR(OFFSET($D$713,MATCH(A23,$F$714:$F$1320,0),0)),"",OFFSET($D$713,MATCH(A23,$F$714:$F$1320,0),0)) | G23: =IF(ISERROR(OFFSET('HARGA SATUAN'!$I$6,MATCH(C23,'HARGA SATUAN'!$C$7:$C$1492,0),0)),"",OFFSET('HARGA SATUAN'!$I$6,MATCH(C23,'HARGA SATUAN'!$C$7:$C$1492,0),0)) -> 0 | H23: =IF(B23="","",#REF!) | I23: =IF(B23="","",#REF!) | J23: =IF(B23="","",#REF!) | K23: =IF(B23="","",#REF!) | L23: =IF(C23="","",#REF!)
... A710: 699 | B710: =IF(C710="","",A710) | C710: =IF(ISERROR(OFFSET($C$713,MATCH(A710,$F$714:$F$1320,0),0)),"",OFFSET($C$713,MATCH(A710,$F$714:$F$1320,0),0)) | D710: =IF(ISERROR(OFFSET('HARGA SATUAN'!$D$6,MATCH(C710,'HARGA SATUAN'!$C$7:$C$1492,0),0)),"",OFFSET('HARGA SATUAN'!$D$6,MATCH(C710,'HARGA SATUAN'!$C$7:$C$1492,0),0)) | E710: =IF(B710="+","Unit",IF(ISERROR(OFFSET('HARGA SATUAN'!$E$6,MATCH(C710,'HARGA SATUAN'!$C$7:$C$1492,0),0)),"",OFFSET('HARGA SATUAN'!$E$6,MATCH(C710,'HARGA SATUAN'!$C$7:$C$1492,0),0))) -> 0 | F710: =IF(ISERROR(OFFSET($D$713,MATCH(A710,$F$714:$F$1320,0),0)),"",OFFSET($D$713,MATCH(A710,$F$714:$F$1320,0),0)) | G710: =IF(ISERROR(OFFSET('HARGA SATUAN'!$I$6,MATCH(C710,'HARGA SATUAN'!$C$7:$C$1492,0),0)),"",OFFSET('HARGA SATUAN'!$I$6,MATCH(C710,'HARGA SATUAN'!$C$7:$C$1492,0),0)) -> 0 | H710: =IF(B710="","",#REF!) | I710: =IF(B710="","",#REF!) | J710: =IF(B710="","",#REF!) | K710: =IF(B710="","",#REF!) | L710: =IF(C710="","",#REF!)
A711: 700 | B711: =IF(C711="","",A711) | C711: =IF(ISERROR(OFFSET($C$713,MATCH(A711,$F$714:$F$1320,0),0)),"",OFFSET($C$713,MATCH(A711,$F$714:$F$1320,0),0)) | F711: =IF(ISERROR(OFFSET($D$713,MATCH(A711,$F$714:$F$1320,0),0)),"",OFFSET($D$713,MATCH(A711,$F$714:$F$1320,0),0)) | G711: =IF(ISERROR(OFFSET('HARGA SATUAN'!$I$6,MATCH(C711,'HARGA SATUAN'!$C$7:$C$1492,0),0)),"",OFFSET('HARGA SATUAN'!$I$6,MATCH(C711,'HARGA SATUAN'!$C$7:$C$1492,0),0)) -> 0 | H711: =IF(B711="","",#REF!) | I711: =IF(B711="","",#REF!) | J711: =IF(B711="","",#REF!) | K711: =IF(B711="","",#REF!) | L711: =IF(C711="","",#REF!)
B714: 1 | C714: =IF(ISERROR(OFFSET('HARGA SATUAN'!$C$6,MATCH(B714,'HARGA SATUAN'!$N$7:$N$1492,0),0)),"",OFFSET('HARGA SATUAN'!$C$6,MATCH(B714,'HARGA SATUAN'!$N$7:$N$1492,0),0)) -> KWH MPB; 1P;230V;5(60)A;1;2W | D714: =SUMIFS(RAB!$F$14:$F$160,RAB!$C$14:$C$160,C714) -> 0 | E714: =IF(D714=0,0,1) -> 0 | F714: =IF(D714=0,0,SUM($E$713:E714)) -> 0
B715: 2 | C715: =IF(ISERROR(OFFSET('HARGA SATUAN'!$C$6,MATCH(B715,'HARGA SATUAN'!$N$7:$N$1492,0),0)),"",OFFSET('HARGA SATUAN'!$C$6,MATCH(B715,'HARGA SATUAN'!$N$7:$N$1492,0),0)) -> KWH Elektronik; 1P; 2W; 230 V; 5(40) A; kls 1 (combo); register drum | D715: =SUMIFS(RAB!$F$14:$F$160,RAB!$C$14:$C$160,C715) -> 0 | E715: =IF(D715=0,0,1) -> 0 | F715: =IF(D715=0,0,SUM($E$713:E715)) -> 0
B716: 3 | C716: =IF(ISERROR(OFFSET('HARGA SATUAN'!$C$6,MATCH(B716,'HARGA SATUAN'!$N$7:$N$1492,0),0)),"",OFFSET('HARGA SATUAN'!$C$6,MATCH(B716,'HARGA SATUAN'!$N$7:$N$1492,0),0)) -> KWH Elektronik; 1P; 2W; 230 V; 5(100) A; kls 1 termasuk modem 3G/4G | D716: =SUMIFS(RAB!$F$14:$F$160,RAB!$C$14:$C$160,C716) -> 0 | E716: =IF(D716=0,0,1) -> 0 | F716: =IF(D716=0,0,SUM($E$713:E716)) -> 0
B717: 4 | C717: =IF(ISERROR(OFFSET('HARGA SATUAN'!$C$6,MATCH(B717,'HARGA SATUAN'!$N$7:$N$1492,0),0)),"",OFFSET('HARGA SATUAN'!$C$6,MATCH(B717,'HARGA SATUAN'!$N$7:$N$1492,0),0)) -> KWH Elektronik; 3P; 4W; 57.7-100V/220-400V; 5 A; kls 0.2 (meter pembanding) | D717: =SUMIFS(RAB!$F$14:$F$160,RAB!$C$14:$C$160,C717) -> 0 | E717: =IF(D717=0,0,1) -> 0 | F717: =IF(D717=0,0,SUM($E$713:E717)) -> 0
B718: 5 | C718: =IF(ISERROR(OFFSET('HARGA SATUAN'!$C$6,MATCH(B718,'HARGA SATUAN'!$N$7:$N$1492,0),0)),"",OFFSET('HARGA SATUAN'!$C$6,MATCH(B718,'HARGA SATUAN'!$N$7:$N$1492,0),0)) -> KWH Elektronik; 3P; 4W; 220/380V; 5(80) A; kls 1 (Pengukuran Langsung) | D718: =SUMIFS(RAB!$F$14:$F$160,RAB!$C$14:$C$160,C718) -> 0 | E718: =IF(D718=0,0,1) -> 0 | F718: =IF(D718=0,0,SUM($E$713:E718)) -> 0
B719: 6 | C719: =IF(ISERROR(OFFSET('HARGA SATUAN'!$C$6,MATCH(B719,'HARGA SATUAN'!$N$7:$N$1492,0),0)),"",OFFSET('HARGA SATUAN'!$C$6,MATCH(B719,'HARGA SATUAN'!$N$7:$N$1492,0),0)) -> KWH Elektronik; 3P; 4W; 57.7-100V/220-400V; 5(10) A; kls 0.5 (Pengukuran Tidak Langsung) | D719: =SUMIFS(RAB!$F$14:$F$160,RAB!$C$14:$C$160,C719) -> 0 | E719: =IF(D719=0,0,1) -> 0 | F719: =IF(D719=0,0,SUM($E$713:E719)) -> 0
B720: 7 | C720: =IF(ISERROR(OFFSET('HARGA SATUAN'!$C$6,MATCH(B720,'HARGA SATUAN'!$N$7:$N$1492,0),0)),"",OFFSET('HARGA SATUAN'!$C$6,MATCH(B720,'HARGA SATUAN'!$N$7:$N$1492,0),0)) -> KWH Elektronik; 3P; 4W; 220/380V; 5(10); kls 1 (Pengukuran Tidak Langsung) | D720: =SUMIFS(RAB!$F$14:$F$160,RAB!$C$14:$C$160,C720) -> 1 | E720: =IF(D720=0,0,1) -> 1 | F720: =IF(D720=0,0,SUM($E$713:E720)) -> 1
B721: 8 | C721: =IF(ISERROR(OFFSET('HARGA SATUAN'!$C$6,MATCH(B721,'HARGA SATUAN'!$N$7:$N$1492,0),0)),"",OFFSET('HARGA SATUAN'!$C$6,MATCH(B721,'HARGA SATUAN'!$N$7:$N$1492,0),0)) -> MCB 1 Fasa 2 A | D721: =SUMIFS(RAB!$F$14:$F$160,RAB!$C$14:$C$160,C721) -> 0 | E721: =IF(D721=0,0,1) -> 0 | F721: =IF(D721=0,0,SUM($E$713:E721)) -> 0
B722: 9 | C722: =IF(ISERROR(OFFSET('HARGA SATUAN'!$C$6,MATCH(B722,'HARGA SATUAN'!$N$7:$N$1492,0),0)),"",OFFSET('HARGA SATUAN'!$C$6,MATCH(B722,'HARGA SATUAN'!$N$7:$N$1492,0),0)) -> MCB 1 Fasa 4 A | D722: =SUMIFS(RAB!$F$14:$F$160,RAB!$C$14:$C$160,C722) -> 0 | E722: =IF(D722=0,0,1) -> 0 | F722: =IF(D722=0,0,SUM($E$713:E722)) -> 0
B723: 10 | C723: =IF(ISERROR(OFFSET('HARGA SATUAN'!$C$6,MATCH(B723,'HARGA SATUAN'!$N$7:$N$1492,0),0)),"",OFFSET('HARGA SATUAN'!$C$6,MATCH(B723,'HARGA SATUAN'!$N$7:$N$1492,0),0)) -> MCB 1 Fasa 6 A | D723: =SUMIFS(RAB!$F$14:$F$160,RAB!$C$14:$C$160,C723) -> 0 | E723: =IF(D723=0,0,1) -> 0 | F723: =IF(D723=0,0,SUM($E$713:E723)) -> 0
B724: 11 | C724: =IF(ISERROR(OFFSET('HARGA SATUAN'!$C$6,MATCH(B724,'HARGA SATUAN'!$N$7:$N$1492,0),0)),"",OFFSET('HARGA SATUAN'!$C$6,MATCH(B724,'HARGA SATUAN'!$N$7:$N$1492,0),0)) -> MCB 1 Fasa 10 A | D724: =SUMIFS(RAB!$F$14:$F$160,RAB!$C$14:$C$160,C724) -> 0 | E724: =IF(D724=0,0,1) -> 0 | F724: =IF(D724=0,0,SUM($E$713:E724)) -> 0
B725: 12 | C725: =IF(ISERROR(OFFSET('HARGA SATUAN'!$C$6,MATCH(B725,'HARGA SATUAN'!$N$7:$N$1492,0),0)),"",OFFSET('HARGA SATUAN'!$C$6,MATCH(B725,'HARGA SATUAN'!$N$7:$N$1492,0),0)) -> MCB 1 Fasa 16 A | D725: =SUMIFS(RAB!$F$14:$F$160,RAB!$C$14:$C$160,C725) -> 0 | E725: =IF(D725=0,0,1) -> 0 | F725: =IF(D725=0,0,SUM($E$713:E725)) -> 0
... B1320: 607 | C1320: =IF(ISERROR(OFFSET('HARGA SATUAN'!$C$6,MATCH(B1320,'HARGA SATUAN'!$N$7:$N$1492,0),0)),"",OFFSET('HARGA SATUAN'!$C$6,MATCH(B1320,'HARGA SATUAN'!$N$7:$N$1492,0),0)) | D1320: =SUMIFS(RAB!$F$14:$F$160,RAB!$C$14:$C$160,C1320) -> 0 | E1320: =IF(D1320=0,0,1) -> 0 | F1320: =IF(D1320=0,0,SUM($E$713:E1320)) -> 0

Sheet REKAP TIANG
C1: =RAB!C1 -> PT. PLN ( PERSERO )
C2: =RAB!C2 -> UNIT INDUK DISTRIBUSI JAWA TENGAH & DI YOGYAKARTA
C3: =RAB!C3 -> UP3 DEMAK
B4: REKAP KEBUTUHAN TIANG
E6: Pekerjaan | F6: : | G6: =RAB!G6 -> AGR UD NURA JAYA
E7: Lokasi | F7: : | G7: =RAB!G7 -> DS SIDOMULYO 07/04 WONOSALAM
E8: Pelaksana | F8: : | G8: =RAB!G8 -> 0
E9: Anggaran | F9: : | G9: =RAB!G9 -> SAR 2023
B11: NO | C11: URAIAN | D11: GOL | E11: SAT | F11: VOL | G11: HARGA SATUAN | H11: BIAYA YANG DIPERLUKAN ( Rp )
H12: MDU | I12: HARDWARE | J12: JASA | K12: JUMLAH
G14: =IF(ISERROR(OFFSET('HARGA SATUAN'!$I$6,MATCH(C14,'HARGA SATUAN'!$C$7:$C$1492,0),0)),"",OFFSET('HARGA SATUAN'!$I$6,MATCH(C14,'HARGA SATUAN'!$C$7:$C$1492,0),0)) | H14: =IF(OR(D14="MDU",D14="MDU-KD"),G14*F14,0) -> 0 | I14: =IF(D14="HDW",G14*F14,0) -> 0 | J14: =IF(D14="JASA",G14*F14,0) -> 0 | K14: =SUM(H14:J14) -> 0
B15: + | C15: REKAP TIANG | G15: =IF(ISERROR(OFFSET('HARGA SATUAN'!$I$6,MATCH(C15,'HARGA SATUAN'!$C$7:$C$1492,0),0)),"",OFFSET('HARGA SATUAN'!$I$6,MATCH(C15,'HARGA SATUAN'!$C$7:$C$1492,0),0)) | H15: =IF(OR(D15="MDU",D15="MDU-KD"),G15*F15,0) -> 0 | I15: =IF(D15="HDW",G15*F15,0) -> 0 | J15: =IF(D15="JASA",G15*F15,0) -> 0 | K15: =SUM(H15:J15) -> 0
A16: 1 | B16: =IF(C16="","",A16) -> 1 | C16: =IF(ISERROR(OFFSET($C$56,MATCH(A16,$F$57:$F$76,0),0)),"",OFFSET($C$56,MATCH(A16,$F$57:$F$76,0),0)) -> Tiang Beton 12M-350 daN+E | D16: =IF(ISERROR(OFFSET('HARGA SATUAN'!$D$6,MATCH(C16,'HARGA SATUAN'!$C$7:$C$1492,0),0)),"",OFFSET('HARGA SATUAN'!$D$6,MATCH(C16,'HARGA SATUAN'!$C$7:$C$1492,0),0)) -> HDW | E16: =IF(B16="+","Unit",IF(ISERROR(OFFSET('HARGA SATUAN'!$E$6,MATCH(C16,'HARGA SATUAN'!$C$7:$C$1492,0),0)),"",OFFSET('HARGA SATUAN'!$E$6,MATCH(C16,'HARGA SATUAN'!$C$7:$C$1492,0),0))) -> Btg | F16: =IF(ISERROR(OFFSET($D$56,MATCH(A16,$F$57:$F$76,0),0)),"",OFFSET($D$56,MATCH(A16,$F$57:$F$76,0),0)) -> 1 | G16: =IF(ISERROR(OFFSET('HARGA SATUAN'!$I$6,MATCH(C16,'HARGA SATUAN'!$C$7:$C$1492,0),0)),"",OFFSET('HARGA SATUAN'!$I$6,MATCH(C16,'HARGA SATUAN'!$C$7:$C$1492,0),0)) -> 6074400 | H16: =IF(OR(D16="MDU",D16="MDU-KD"),G16*F16,0) -> 0 | I16: =IF(D16="HDW",G16*F16,0) -> 6074400 | J16: =IF(D16="JASA",G16*F16,0) -> 0 | K16: =SUM(H16:J16) -> 6074400
A17: 2 | B17: =IF(C17="","",A17) | C17: =IF(ISERROR(OFFSET($C$56,MATCH(A17,$F$57:$F$76,0),0)),"",OFFSET($C$56,MATCH(A17,$F$57:$F$76,0),0)) | D17: =IF(ISERROR(OFFSET('HARGA SATUAN'!$D$6,MATCH(C17,'HARGA SATUAN'!$C$7:$C$1492,0),0)),"",OFFSET('HARGA SATUAN'!$D$6,MATCH(C17,'HARGA SATUAN'!$C$7:$C$1492,0),0)) | E17: =IF(B17="+","Unit",IF(ISERROR(OFFSET('HARGA SATUAN'!$E$6,MATCH(C17,'HARGA SATUAN'!$C$7:$C$1492,0),0)),"",OFFSET('HARGA SATUAN'!$E$6,MATCH(C17,'HARGA SATUAN'!$C$7:$C$1492,0),0))) -> 0 | F17: =IF(ISERROR(OFFSET($D$56,MATCH(A17,$F$57:$F$76,0),0)),"",OFFSET($D$56,MATCH(A17,$F$57:$F$76,0),0)) | G17: =IF(ISERROR(OFFSET('HARGA SATUAN'!$I$6,MATCH(C17,'HARGA SATUAN'!$C$7:$C$1492,0),0)),"",OFFSET('HARGA SATUAN'!$I$6,MATCH(C17,'HARGA SATUAN'!$C$7:$C$1492,0),0)) -> 0 | H17: =IF(OR(D17="MDU",D17="MDU-KD"),G17*F17,0) -> 0 | I17: =IF(D17="HDW",G17*F17,0) -> 0 | J17: =IF(D17="JASA",G17*F17,0) -> 0 | K17: =SUM(H17:J17) -> 0
A18: 3 | B18: =IF(C18="","",A18) | C18: =IF(ISERROR(OFFSET($C$56,MATCH(A18,$F$57:$F$76,0),0)),"",OFFSET($C$56,MATCH(A18,$F$57:$F$76,0),0)) | D18: =IF(ISERROR(OFFSET('HARGA SATUAN'!$D$6,MATCH(C18,'HARGA SATUAN'!$C$7:$C$1492,0),0)),"",OFFSET('HARGA SATUAN'!$D$6,MATCH(C18,'HARGA SATUAN'!$C$7:$C$1492,0),0)) | E18: =IF(B18="+","Unit",IF(ISERROR(OFFSET('HARGA SATUAN'!$E$6,MATCH(C18,'HARGA SATUAN'!$C$7:$C$1492,0),0)),"",OFFSET('HARGA SATUAN'!$E$6,MATCH(C18,'HARGA SATUAN'!$C$7:$C$1492,0),0))) -> 0 | F18: =IF(ISERROR(OFFSET($D$56,MATCH(A18,$F$57:$F$76,0),0)),"",OFFSET($D$56,MATCH(A18,$F$57:$F$76,0),0)) | G18: =IF(ISERROR(OFFSET('HARGA SATUAN'!$I$6,MATCH(C18,'HARGA SATUAN'!$C$7:$C$1492,0),0)),"",OFFSET('HARGA SATUAN'!$I$6,MATCH(C18,'HARGA SATUAN'!$C$7:$C$1492,0),0)) -> 0 | H18: =IF(OR(D18="MDU",D18="MDU-KD"),G18*F18,0) -> 0 | I18: =IF(D18="HDW",G18*F18,0) -> 0 | J18: =IF(D18="JASA",G18*F18,0) -> 0 | K18: =SUM(H18:J18) -> 0
A19: 4 | B19: =IF(C19="","",A19) | C19: =IF(ISERROR(OFFSET($C$56,MATCH(A19,$F$57:$F$76,0),0)),"",OFFSET($C$56,MATCH(A19,$F$57:$F$76,0),0)) | D19: =IF(ISERROR(OFFSET('HARGA SATUAN'!$D$6,MATCH(C19,'HARGA SATUAN'!$C$7:$C$1492,0),0)),"",OFFSET('HARGA SATUAN'!$D$6,MATCH(C19,'HARGA SATUAN'!$C$7:$C$1492,0),0)) | E19: =IF(B19="+","Unit",IF(ISERROR(OFFSET('HARGA SATUAN'!$E$6,MATCH(C19,'HARGA SATUAN'!$C$7:$C$1492,0),0)),"",OFFSET('HARGA SATUAN'!$E$6,MATCH(C19,'HARGA SATUAN'!$C$7:$C$1492,0),0))) -> 0 | F19: =IF(ISERROR(OFFSET($D$56,MATCH(A19,$F$57:$F$76,0),0)),"",OFFSET($D$56,MATCH(A19,$F$57:$F$76,0),0)) | G19: =IF(ISERROR(OFFSET('HARGA SATUAN'!$I$6,MATCH(C19,'HARGA SATUAN'!$C$7:$C$1492,0),0)),"",OFFSET('HARGA SATUAN'!$I$6,MATCH(C19,'HARGA SATUAN'!$C$7:$C$1492,0),0)) -> 0 | H19: =IF(OR(D19="MDU",D19="MDU-KD"),G19*F19,0) -> 0 | I19: =IF(D19="HDW",G19*F19,0) -> 0 | J19: =IF(D19="JASA",G19*F19,0) -> 0 | K19: =SUM(H19:J19) -> 0
A20: 5 | B20: =IF(C20="","",A20) | C20: =IF(ISERROR(OFFSET($C$56,MATCH(A20,$F$57:$F$76,0),0)),"",OFFSET($C$56,MATCH(A20,$F$57:$F$76,0),0)) | D20: =IF(ISERROR(OFFSET('HARGA SATUAN'!$D$6,MATCH(C20,'HARGA SATUAN'!$C$7:$C$1492,0),0)),"",OFFSET('HARGA SATUAN'!$D$6,MATCH(C20,'HARGA SATUAN'!$C$7:$C$1492,0),0)) | E20: =IF(B20="+","Unit",IF(ISERROR(OFFSET('HARGA SATUAN'!$E$6,MATCH(C20,'HARGA SATUAN'!$C$7:$C$1492,0),0)),"",OFFSET('HARGA SATUAN'!$E$6,MATCH(C20,'HARGA SATUAN'!$C$7:$C$1492,0),0))) -> 0 | F20: =IF(ISERROR(OFFSET($D$56,MATCH(A20,$F$57:$F$76,0),0)),"",OFFSET($D$56,MATCH(A20,$F$57:$F$76,0),0)) | G20: =IF(ISERROR(OFFSET('HARGA SATUAN'!$I$6,MATCH(C20,'HARGA SATUAN'!$C$7:$C$1492,0),0)),"",OFFSET('HARGA SATUAN'!$I$6,MATCH(C20,'HARGA SATUAN'!$C$7:$C$1492,0),0)) -> 0 | H20: =IF(OR(D20="MDU",D20="MDU-KD"),G20*F20,0) -> 0 | I20: =IF(D20="HDW",G20*F20,0) -> 0 | J20: =IF(D20="JASA",G20*F20,0) -> 0 | K20: =SUM(H20:J20) -> 0
A21: 6 | B21: =IF(C21="","",A21) | C21: =IF(ISERROR(OFFSET($C$56,MATCH(A21,$F$57:$F$76,0),0)),"",OFFSET($C$56,MATCH(A21,$F$57:$F$76,0),0)) | D21: =IF(ISERROR(OFFSET('HARGA SATUAN'!$D$6,MATCH(C21,'HARGA SATUAN'!$C$7:$C$1492,0),0)),"",OFFSET('HARGA SATUAN'!$D$6,MATCH(C21,'HARGA SATUAN'!$C$7:$C$1492,0),0)) | E21: =IF(B21="+","Unit",IF(ISERROR(OFFSET('HARGA SATUAN'!$E$6,MATCH(C21,'HARGA SATUAN'!$C$7:$C$1492,0),0)),"",OFFSET('HARGA SATUAN'!$E$6,MATCH(C21,'HARGA SATUAN'!$C$7:$C$1492,0),0))) -> 0 | F21: =IF(ISERROR(OFFSET($D$56,MATCH(A21,$F$57:$F$76,0),0)),"",OFFSET($D$56,MATCH(A21,$F$57:$F$76,0),0)) | G21: =IF(ISERROR(OFFSET('HARGA SATUAN'!$I$6,MATCH(C21,'HARGA SATUAN'!$C$7:$C$1492,0),0)),"",OFFSET('HARGA SATUAN'!$I$6,MATCH(C21,'HARGA SATUAN'!$C$7:$C$1492,0),0)) -> 0 | H21: =IF(OR(D21="MDU",D21="MDU-KD"),G21*F21,0) -> 0 | I21: =IF(D21="HDW",G21*F21,0) -> 0 | J21: =IF(D21="JASA",G21*F21,0) -> 0 | K21: =SUM(H21:J21) -> 0
A22: 7 | B22: =IF(C22="","",A22) | C22: =IF(ISERROR(OFFSET($C$56,MATCH(A22,$F$57:$F$76,0),0)),"",OFFSET($C$56,MATCH(A22,$F$57:$F$76,0),0)) | D22: =IF(ISERROR(OFFSET('HARGA SATUAN'!$D$6,MATCH(C22,'HARGA SATUAN'!$C$7:$C$1492,0),0)),"",OFFSET('HARGA SATUAN'!$D$6,MATCH(C22,'HARGA SATUAN'!$C$7:$C$1492,0),0)) | E22: =IF(B22="+","Unit",IF(ISERROR(OFFSET('HARGA SATUAN'!$E$6,MATCH(C22,'HARGA SATUAN'!$C$7:$C$1492,0),0)),"",OFFSET('HARGA SATUAN'!$E$6,MATCH(C22,'HARGA SATUAN'!$C$7:$C$1492,0),0))) -> 0 | F22: =IF(ISERROR(OFFSET($D$56,MATCH(A22,$F$57:$F$76,0),0)),"",OFFSET($D$56,MATCH(A22,$F$57:$F$76,0),0)) | G22: =IF(ISERROR(OFFSET('HARGA SATUAN'!$I$6,MATCH(C22,'HARGA SATUAN'!$C$7:$C$1492,0),0)),"",OFFSET('HARGA SATUAN'!$I$6,MATCH(C22,'HARGA SATUAN'!$C$7:$C$1492,0),0)) -> 0 | H22: =IF(OR(D22="MDU",D22="MDU-KD"),G22*F22,0) -> 0 | I22: =IF(D22="HDW",G22*F22,0) -> 0 | J22: =IF(D22="JASA",G22*F22,0) -> 0 | K22: =SUM(H22:J22) -> 0
A23: 8 | B23: =IF(C23="","",A23) | C23: =IF(ISERROR(OFFSET($C$56,MATCH(A23,$F$57:$F$76,0),0)),"",OFFSET($C$56,MATCH(A23,$F$57:$F$76,0),0)) | D23: =IF(ISERROR(OFFSET('HARGA SATUAN'!$D$6,MATCH(C23,'HARGA SATUAN'!$C$7:$C$1492,0),0)),"",OFFSET('HARGA SATUAN'!$D$6,MATCH(C23,'HARGA SATUAN'!$C$7:$C$1492,0),0)) | E23: =IF(B23="+","Unit",IF(ISERROR(OFFSET('HARGA SATUAN'!$E$6,MATCH(C23,'HARGA SATUAN'!$C$7:$C$1492,0),0)),"",OFFSET('HARGA SATUAN'!$E$6,MATCH(C23,'HARGA SATUAN'!$C$7:$C$1492,0),0))) -> 0 | F23: =IF(ISERROR(OFFSET($D$56,MATCH(A23,$F$57:$F$76,0),0)),"",OFFSET($D$56,MATCH(A23,$F$57:$F$76,0),0)) | G23: =IF(ISERROR(OFFSET('HARGA SATUAN'!$I$6,MATCH(C23,'HARGA SATUAN'!$C$7:$C$1492,0),0)),"",OFFSET('HARGA SATUAN'!$I$6,MATCH(C23,'HARGA SATUAN'!$C$7:$C$1492,0),0)) -> 0 | H23: =IF(OR(D23="MDU",D23="MDU-KD"),G23*F23,0) -> 0 | I23: =IF(D23="HDW",G23*F23,0) -> 0 | J23: =IF(D23="JASA",G23*F23,0) -> 0 | K23: =SUM(H23:J23) -> 0
A24: 9 | B24: =IF(C24="","",A24) | C24: =IF(ISERROR(OFFSET($C$56,MATCH(A24,$F$57:$F$76,0),0)),"",OFFSET($C$56,MATCH(A24,$F$57:$F$76,0),0)) | D24: =IF(ISERROR(OFFSET('HARGA SATUAN'!$D$6,MATCH(C24,'HARGA SATUAN'!$C$7:$C$1492,0),0)),"",OFFSET('HARGA SATUAN'!$D$6,MATCH(C24,'HARGA SATUAN'!$C$7:$C$1492,0),0)) | E24: =IF(B24="+","Unit",IF(ISERROR(OFFSET('HARGA SATUAN'!$E$6,MATCH(C24,'HARGA SATUAN'!$C$7:$C$1492,0),0)),"",OFFSET('HARGA SATUAN'!$E$6,MATCH(C24,'HARGA SATUAN'!$C$7:$C$1492,0),0))) -> 0 | F24: =IF(ISERROR(OFFSET($D$56,MATCH(A24,$F$57:$F$76,0),0)),"",OFFSET($D$56,MATCH(A24,$F$57:$F$76,0),0)) | G24: =IF(ISERROR(OFFSET('HARGA SATUAN'!$I$6,MATCH(C24,'HARGA SATUAN'!$C$7:$C$1492,0),0)),"",OFFSET('HARGA SATUAN'!$I$6,MATCH(C24,'HARGA SATUAN'!$C$7:$C$1492,0),0)) -> 0 | H24: =IF(OR(D24="MDU",D24="MDU-KD"),G24*F24,0) -> 0 | I24: =IF(D24="HDW",G24*F24,0) -> 0 | J24: =IF(D24="JASA",G24*F24,0) -> 0 | K24: =SUM(H24:J24) -> 0
A25: 10 | B25: =IF(C25="","",A25) | C25: =IF(ISERROR(OFFSET($C$56,MATCH(A25,$F$57:$F$76,0),0)),"",OFFSET($C$56,MATCH(A25,$F$57:$F$76,0),0)) | D25: =IF(ISERROR(OFFSET('HARGA SATUAN'!$D$6,MATCH(C25,'HARGA SATUAN'!$C$7:$C$1492,0),0)),"",OFFSET('HARGA SATUAN'!$D$6,MATCH(C25,'HARGA SATUAN'!$C$7:$C$1492,0),0)) | E25: =IF(B25="+","Unit",IF(ISERROR(OFFSET('HARGA SATUAN'!$E$6,MATCH(C25,'HARGA SATUAN'!$C$7:$C$1492,0),0)),"",OFFSET('HARGA SATUAN'!$E$6,MATCH(C25,'HARGA SATUAN'!$C$7:$C$1492,0),0))) -> 0 | F25: =IF(ISERROR(OFFSET($D$56,MATCH(A25,$F$57:$F$76,0),0)),"",OFFSET($D$56,MATCH(A25,$F$57:$F$76,0),0)) | G25: =IF(ISERROR(OFFSET('HARGA SATUAN'!$I$6,MATCH(C25,'HARGA SATUAN'!$C$7:$C$1492,0),0)),"",OFFSET('HARGA SATUAN'!$I$6,MATCH(C25,'HARGA SATUAN'!$C$7:$C$1492,0),0)) -> 0 | H25: =IF(OR(D25="MDU",D25="MDU-KD"),G25*F25,0) -> 0 | I25: =IF(D25="HDW",G25*F25,0) -> 0 | J25: =IF(D25="JASA",G25*F25,0) -> 0 | K25: =SUM(H25:J25) -> 0
A26: 11 | B26: =IF(C26="","",A26) | C26: =IF(ISERROR(OFFSET($C$56,MATCH(A26,$F$57:$F$76,0),0)),"",OFFSET($C$56,MATCH(A26,$F$57:$F$76,0),0)) | D26: =IF(ISERROR(OFFSET('HARGA SATUAN'!$D$6,MATCH(C26,'HARGA SATUAN'!$C$7:$C$1492,0),0)),"",OFFSET('HARGA SATUAN'!$D$6,MATCH(C26,'HARGA SATUAN'!$C$7:$C$1492,0),0)) | E26: =IF(B26="+","Unit",IF(ISERROR(OFFSET('HARGA SATUAN'!$E$6,MATCH(C26,'HARGA SATUAN'!$C$7:$C$1492,0),0)),"",OFFSET('HARGA SATUAN'!$E$6,MATCH(C26,'HARGA SATUAN'!$C$7:$C$1492,0),0))) -> 0 | F26: =IF(ISERROR(OFFSET($D$56,MATCH(A26,$F$57:$F$76,0),0)),"",OFFSET($D$56,MATCH(A26,$F$57:$F$76,0),0)) | G26: =IF(ISERROR(OFFSET('HARGA SATUAN'!$I$6,MATCH(C26,'HARGA SATUAN'!$C$7:$C$1492,0),0)),"",OFFSET('HARGA SATUAN'!$I$6,MATCH(C26,'HARGA SATUAN'!$C$7:$C$1492,0),0)) -> 0 | H26: =IF(OR(D26="MDU",D26="MDU-KD"),G26*F26,0) -> 0 | I26: =IF(D26="HDW",G26*F26,0) -> 0 | J26: =IF(D26="JASA",G26*F26,0) -> 0 | K26: =SUM(H26:J26) -> 0
A27: 12 | B27: =IF(C27="","",A27) | C27: =IF(ISERROR(OFFSET($C$56,MATCH(A27,$F$57:$F$76,0),0)),"",OFFSET($C$56,MATCH(A27,$F$57:$F$76,0),0)) | D27: =IF(ISERROR(OFFSET('HARGA SATUAN'!$D$6,MATCH(C27,'HARGA SATUAN'!$C$7:$C$1492,0),0)),"",OFFSET('HARGA SATUAN'!$D$6,MATCH(C27,'HARGA SATUAN'!$C$7:$C$1492,0),0)) | E27: =IF(B27="+","Unit",IF(ISERROR(OFFSET('HARGA SATUAN'!$E$6,MATCH(C27,'HARGA SATUAN'!$C$7:$C$1492,0),0)),"",OFFSET('HARGA SATUAN'!$E$6,MATCH(C27,'HARGA SATUAN'!$C$7:$C$1492,0),0))) -> 0 | F27: =IF(ISERROR(OFFSET($D$56,MATCH(A27,$F$57:$F$76,0),0)),"",OFFSET($D$56,MATCH(A27,$F$57:$F$76,0),0)) | G27: =IF(ISERROR(OFFSET('HARGA SATUAN'!$I$6,MATCH(C27,'HARGA SATUAN'!$C$7:$C$1492,0),0)),"",OFFSET('HARGA SATUAN'!$I$6,MATCH(C27,'HARGA SATUAN'!$C$7:$C$1492,0),0)) -> 0 | H27: =IF(OR(D27="MDU",D27="MDU-KD"),G27*F27,0) -> 0 | I27: =IF(D27="HDW",G27*F27,0) -> 0 | J27: =IF(D27="JASA",G27*F27,0) -> 0 | K27: =SUM(H27:J27) -> 0
... A35: 20 | B35: =IF(C35="","",A35) | C35: =IF(ISERROR(OFFSET($C$56,MATCH(A35,$F$57:$F$76,0),0)),"",OFFSET($C$56,MATCH(A35,$F$57:$F$76,0),0)) | D35: =IF(ISERROR(OFFSET('HARGA SATUAN'!$D$6,MATCH(C35,'HARGA SATUAN'!$C$7:$C$1492,0),0)),"",OFFSET('HARGA SATUAN'!$D$6,MATCH(C35,'HARGA SATUAN'!$C$7:$C$1492,0),0)) | E35: =IF(B35="+","Unit",IF(ISERROR(OFFSET('HARGA SATUAN'!$E$6,MATCH(C35,'HARGA SATUAN'!$C$7:$C$1492,0),0)),"",OFFSET('HARGA SATUAN'!$E$6,MATCH(C35,'HARGA SATUAN'!$C$7:$C$1492,0),0))) -> 0 | F35: =IF(ISERROR(OFFSET($D$56,MATCH(A35,$F$57:$F$76,0),0)),"",OFFSET($D$56,MATCH(A35,$F$57:$F$76,0),0)) | G35: =IF(ISERROR(OFFSET('HARGA SATUAN'!$I$6,MATCH(C35,'HARGA SATUAN'!$C$7:$C$1492,0),0)),"",OFFSET('HARGA SATUAN'!$I$6,MATCH(C35,'HARGA SATUAN'!$C$7:$C$1492,0),0)) -> 0 | H35: =IF(OR(D35="MDU",D35="MDU-KD"),G35*F35,0) -> 0 | I35: =IF(D35="HDW",G35*F35,0) -> 0 | J35: =IF(D35="JASA",G35*F35,0) -> 0 | K35: =SUM(H35:J35) -> 0
D36: =IF(ISERROR(OFFSET('HARGA SATUAN'!$D$6,MATCH(C36,'HARGA SATUAN'!$C$7:$C$1492,0),0)),"",OFFSET('HARGA SATUAN'!$D$6,MATCH(C36,'HARGA SATUAN'!$C$7:$C$1492,0),0)) | E36: =IF(B36="+","Unit",IF(ISERROR(OFFSET('HARGA SATUAN'!$E$6,MATCH(C36,'HARGA SATUAN'!$C$7:$C$1492,0),0)),"",OFFSET('HARGA SATUAN'!$E$6,MATCH(C36,'HARGA SATUAN'!$C$7:$C$1492,0),0))) | F36: =IF(ISERROR(OFFSET($D$56,MATCH(A36,$F$57:$F$76,0),0)),"",OFFSET($D$56,MATCH(A36,$F$57:$F$76,0),0)) -> 0 | G36: =IF(ISERROR(OFFSET('HARGA SATUAN'!$I$6,MATCH(C36,'HARGA SATUAN'!$C$7:$C$1492,0),0)),"",OFFSET('HARGA SATUAN'!$I$6,MATCH(C36,'HARGA SATUAN'!$C$7:$C$1492,0),0)) | H36: =IF(OR(D36="MDU",D36="MDU-KD"),G36*F36,0) -> 0 | I36: =IF(D36="HDW",G36*F36,0) -> 0 | J36: =IF(D36="JASA",G36*F36,0) -> 0 | K36: =SUM(H36:J36) -> 0
C38: Jumlah MDU - Hardware - Jasa | G38: : | H38: =SUM(H14:H37) -> 0 | I38: =SUM(I14:I37) -> 6074400 | J38: =SUM(J14:J37) -> 0 | K38: =SUM(K14:K37) -> 6074400
C39: PPN 10% | G39: : | H39: =H38*0.1 -> 0 | I39: =I38*0.1 -> 607440 | J39: =J38*0.1 -> 0 | K39: =K38*0.1 -> 607440
C40: Jumlah Total | G40: : | H40: =SUM(H38:H39) -> 0 | I40: =SUM(I38:I39) -> 6681840 | J40: =SUM(J38:J39) -> 0 | K40: =SUM(K38:K39) -> 6681840
B41: ="Terbilang : ( "&L42&" Rupiah )" -> #NAME?
L42: =PROPER([91]!terbilang(K40)) -> #NAME?
B43: ="Harga yang dipakai adalah "&'HARGA SATUAN'!I5&"" -> Harga yang dipakai adalah RAB HSS 2023
B56: NO | C56: JENIS TIANG
B57: 1 | C57: =IF(ISERROR(OFFSET('HARGA SATUAN'!$C$6,MATCH('REKAP TIANG'!B57,'HARGA SATUAN'!$P$7:$P$1455,0),0)),"",OFFSET('HARGA SATUAN'!$C$6,MATCH('REKAP TIANG'!B57,'HARGA SATUAN'!$P$7:$P$1455,0),0)) -> Tiang Beton 9M-200 daN+E | D57: =SUMIFS(RAB!$F$14:$F$160,RAB!$C$14:$C$160,'REKAP TIANG'!C57) -> 0 | E57: =IF(D57=0,0,1) -> 0 | F57: =IF(D57=0,0,SUM($E$56:E57)) -> 0
B58: 2 | C58: =IF(ISERROR(OFFSET('HARGA SATUAN'!$C$6,MATCH('REKAP TIANG'!B58,'HARGA SATUAN'!$P$7:$P$1455,0),0)),"",OFFSET('HARGA SATUAN'!$C$6,MATCH('REKAP TIANG'!B58,'HARGA SATUAN'!$P$7:$P$1455,0),0)) -> Tiang Beton 11M-200 daN+E | D58: =SUMIFS(RAB!$F$14:$F$160,RAB!$C$14:$C$160,'REKAP TIANG'!C58) -> 0 | E58: =IF(D58=0,0,1) -> 0 | F58: =IF(D58=0,0,SUM($E$56:E58)) -> 0
B59: 3 | C59: =IF(ISERROR(OFFSET('HARGA SATUAN'!$C$6,MATCH('REKAP TIANG'!B59,'HARGA SATUAN'!$P$7:$P$1455,0),0)),"",OFFSET('HARGA SATUAN'!$C$6,MATCH('REKAP TIANG'!B59,'HARGA SATUAN'!$P$7:$P$1455,0),0)) -> Tiang Beton 12M-200 daN+E | D59: =SUMIFS(RAB!$F$14:$F$160,RAB!$C$14:$C$160,'REKAP TIANG'!C59) -> 0 | E59: =IF(D59=0,0,1) -> 0 | F59: =IF(D59=0,0,SUM($E$56:E59)) -> 0
B60: 4 | C60: =IF(ISERROR(OFFSET('HARGA SATUAN'!$C$6,MATCH('REKAP TIANG'!B60,'HARGA SATUAN'!$P$7:$P$1455,0),0)),"",OFFSET('HARGA SATUAN'!$C$6,MATCH('REKAP TIANG'!B60,'HARGA SATUAN'!$P$7:$P$1455,0),0)) -> Tiang Beton 12M-350 daN+E | D60: =SUMIFS(RAB!$F$14:$F$160,RAB!$C$14:$C$160,'REKAP TIANG'!C60) -> 1 | E60: =IF(D60=0,0,1) -> 1 | F60: =IF(D60=0,0,SUM($E$56:E60)) -> 1
B61: 5 | C61: =IF(ISERROR(OFFSET('HARGA SATUAN'!$C$6,MATCH('REKAP TIANG'!B61,'HARGA SATUAN'!$P$7:$P$1455,0),0)),"",OFFSET('HARGA SATUAN'!$C$6,MATCH('REKAP TIANG'!B61,'HARGA SATUAN'!$P$7:$P$1455,0),0)) -> Tiang Beton 13M-350 daN+E | D61: =SUMIFS(RAB!$F$14:$F$160,RAB!$C$14:$C$160,'REKAP TIANG'!C61) -> 0 | E61: =IF(D61=0,0,1) -> 0 | F61: =IF(D61=0,0,SUM($E$56:E61)) -> 0
B62: 6 | C62: =IF(ISERROR(OFFSET('HARGA SATUAN'!$C$6,MATCH('REKAP TIANG'!B62,'HARGA SATUAN'!$P$7:$P$1455,0),0)),"",OFFSET('HARGA SATUAN'!$C$6,MATCH('REKAP TIANG'!B62,'HARGA SATUAN'!$P$7:$P$1455,0),0)) -> Tiang Beton 14M-350 daN+E | D62: =SUMIFS(RAB!$F$14:$F$160,RAB!$C$14:$C$160,'REKAP TIANG'!C62) -> 0 | E62: =IF(D62=0,0,1) -> 0 | F62: =IF(D62=0,0,SUM($E$56:E62)) -> 0
B63: 7 | C63: =IF(ISERROR(OFFSET('HARGA SATUAN'!$C$6,MATCH('REKAP TIANG'!B63,'HARGA SATUAN'!$P$7:$P$1455,0),0)),"",OFFSET('HARGA SATUAN'!$C$6,MATCH('REKAP TIANG'!B63,'HARGA SATUAN'!$P$7:$P$1455,0),0)) | D63: =SUMIFS(RAB!$F$14:$F$160,RAB!$C$14:$C$160,'REKAP TIANG'!C63) -> 0 | E63: =IF(D63=0,0,1) -> 0 | F63: =IF(D63=0,0,SUM($E$56:E63)) -> 0
B64: 8 | C64: =IF(ISERROR(OFFSET('HARGA SATUAN'!$C$6,MATCH('REKAP TIANG'!B64,'HARGA SATUAN'!$P$7:$P$1455,0),0)),"",OFFSET('HARGA SATUAN'!$C$6,MATCH('REKAP TIANG'!B64,'HARGA SATUAN'!$P$7:$P$1455,0),0)) | D64: =SUMIFS(RAB!$F$14:$F$160,RAB!$C$14:$C$160,'REKAP TIANG'!C64) -> 0 | E64: =IF(D64=0,0,1) -> 0 | F64: =IF(D64=0,0,SUM($E$56:E64)) -> 0
B65: 9 | C65: =IF(ISERROR(OFFSET('HARGA SATUAN'!$C$6,MATCH('REKAP TIANG'!B65,'HARGA SATUAN'!$P$7:$P$1455,0),0)),"",OFFSET('HARGA SATUAN'!$C$6,MATCH('REKAP TIANG'!B65,'HARGA SATUAN'!$P$7:$P$1455,0),0)) | D65: =SUMIFS(RAB!$F$14:$F$160,RAB!$C$14:$C$160,'REKAP TIANG'!C65) -> 0 | E65: =IF(D65=0,0,1) -> 0 | F65: =IF(D65=0,0,SUM($E$56:E65)) -> 0
B66: 10 | C66: =IF(ISERROR(OFFSET('HARGA SATUAN'!$C$6,MATCH('REKAP TIANG'!B66,'HARGA SATUAN'!$P$7:$P$1455,0),0)),"",OFFSET('HARGA SATUAN'!$C$6,MATCH('REKAP TIANG'!B66,'HARGA SATUAN'!$P$7:$P$1455,0),0)) | D66: =SUMIFS(RAB!$F$14:$F$160,RAB!$C$14:$C$160,'REKAP TIANG'!C66) -> 0 | E66: =IF(D66=0,0,1) -> 0 | F66: =IF(D66=0,0,SUM($E$56:E66)) -> 0
B67: 11 | C67: =IF(ISERROR(OFFSET('HARGA SATUAN'!$C$6,MATCH('REKAP TIANG'!B67,'HARGA SATUAN'!$P$7:$P$1455,0),0)),"",OFFSET('HARGA SATUAN'!$C$6,MATCH('REKAP TIANG'!B67,'HARGA SATUAN'!$P$7:$P$1455,0),0)) | D67: =SUMIFS(RAB!$F$14:$F$160,RAB!$C$14:$C$160,'REKAP TIANG'!C67) -> 0 | E67: =IF(D67=0,0,1) -> 0 | F67: =IF(D67=0,0,SUM($E$56:E67)) -> 0
B68: 12 | C68: =IF(ISERROR(OFFSET('HARGA SATUAN'!$C$6,MATCH('REKAP TIANG'!B68,'HARGA SATUAN'!$P$7:$P$1455,0),0)),"",OFFSET('HARGA SATUAN'!$C$6,MATCH('REKAP TIANG'!B68,'HARGA SATUAN'!$P$7:$P$1455,0),0)) | D68: =SUMIFS(RAB!$F$14:$F$160,RAB!$C$14:$C$160,'REKAP TIANG'!C68) -> 0 | E68: =IF(D68=0,0,1) -> 0 | F68: =IF(D68=0,0,SUM($E$56:E68)) -> 0
... B76: 20 | C76: =IF(ISERROR(OFFSET('HARGA SATUAN'!$C$6,MATCH('REKAP TIANG'!B76,'HARGA SATUAN'!$P$7:$P$1455,0),0)),"",OFFSET('HARGA SATUAN'!$C$6,MATCH('REKAP TIANG'!B76,'HARGA SATUAN'!$P$7:$P$1455,0),0)) | D76: =SUMIFS(RAB!$F$14:$F$160,RAB!$C$14:$C$160,'REKAP TIANG'!C76) -> 0 | E76: =IF(D76=0,0,1) -> 0 | F76: =IF(D76=0,0,SUM($E$56:E76)) -> 0

Sheet REKAP MDU
C1: =RAB!C1 -> PT. PLN ( PERSERO )
C2: =RAB!C2 -> UNIT INDUK DISTRIBUSI JAWA TENGAH & DI YOGYAKARTA
C3: =RAB!C3 -> UP3 DEMAK
B4: REKAP MDU
E6: Pekerjaan | F6: : | G6: =RAB!G6 -> AGR UD NURA JAYA
E7: Lokasi | F7: : | G7: =RAB!G7 -> DS SIDOMULYO 07/04 WONOSALAM
E8: Pelaksana | F8: : | G8: =RAB!G8 -> 0
E9: Anggaran | F9: : | G9: =RAB!G9 -> SAR 2023
B11: NO | C11: URAIAN | D11: GOL | E11: SAT | F11: VOL | G11: HARGA SATUAN | H11: BIAYA YANG DIPERLUKAN ( Rp )
H12: MDU | I12: HARDWARE | J12: JASA | K12: JUMLAH
G14: =IF(ISERROR(OFFSET('HARGA SATUAN'!$I$6,MATCH(C14,'HARGA SATUAN'!$C$7:$C$1492,0),0)),"",OFFSET('HARGA SATUAN'!$I$6,MATCH(C14,'HARGA SATUAN'!$C$7:$C$1492,0),0)) | H14: =IF(OR(D14="MDU",D14="MDU-KD"),G14*F14,0) -> 0 | I14: =IF(D14="HDW",G14*F14,0) -> 0 | J14: =IF(D14="JASA",G14*F14,0) -> 0 | K14: =SUM(H14:J14) -> 0
B15: + | C15: REKAP MDU | G15: =IF(ISERROR(OFFSET('HARGA SATUAN'!$I$6,MATCH(C15,'HARGA SATUAN'!$C$7:$C$1492,0),0)),"",OFFSET('HARGA SATUAN'!$I$6,MATCH(C15,'HARGA SATUAN'!$C$7:$C$1492,0),0)) | H15: =IF(OR(D15="MDU",D15="MDU-KD"),G15*F15,0) -> 0 | I15: =IF(D15="HDW",G15*F15,0) -> 0 | J15: =IF(D15="JASA",G15*F15,0) -> 0 | K15: =SUM(H15:J15) -> 0
A16: 1 | B16: =IF(C16="","",A16) -> 1 | C16: =IF(ISERROR(OFFSET($C$223,MATCH(A16,$F$224:$F$373,0),0)),"",OFFSET($C$223,MATCH(A16,$F$224:$F$373,0),0)) -> KWH Elektronik; 3P; 4W; 220/380V; 5(10); kls 1 (Pengukuran Tidak Langsung) | D16: =IF(ISERROR(OFFSET('HARGA SATUAN'!$D$6,MATCH(C16,'HARGA SATUAN'!$C$7:$C$1492,0),0)),"",OFFSET('HARGA SATUAN'!$D$6,MATCH(C16,'HARGA SATUAN'!$C$7:$C$1492,0),0)) -> MDU-KD | E16: =IF(B16="+","Unit",IF(ISERROR(OFFSET('HARGA SATUAN'!$E$6,MATCH(C16,'HARGA SATUAN'!$C$7:$C$1492,0),0)),"",OFFSET('HARGA SATUAN'!$E$6,MATCH(C16,'HARGA SATUAN'!$C$7:$C$1492,0),0))) -> Bh | F16: =IF(ISERROR(OFFSET($D$223,MATCH(A16,$F$224:$F$373,0),0)),"",OFFSET($D$223,MATCH(A16,$F$224:$F$373,0),0)) -> 1 | G16: =IF(ISERROR(OFFSET('HARGA SATUAN'!$I$6,MATCH(C16,'HARGA SATUAN'!$C$7:$C$1492,0),0)),"",OFFSET('HARGA SATUAN'!$I$6,MATCH(C16,'HARGA SATUAN'!$C$7:$C$1492,0),0)) -> 1504200 | H16: =IF(OR(D16="MDU",D16="MDU-KD"),G16*F16,0) -> 1504200 | I16: =IF(D16="HDW",G16*F16,0) -> 0 | J16: =IF(D16="JASA",G16*F16,0) -> 0 | K16: =SUM(H16:J16) -> 1504200
A17: 2 | B17: =IF(C17="","",A17) -> 2 | C17: =IF(ISERROR(OFFSET($C$223,MATCH(A17,$F$224:$F$373,0),0)),"",OFFSET($C$223,MATCH(A17,$F$224:$F$373,0),0)) -> Smart Box Tidak Langsung Daya 105 kVA MCCB 160 A | D17: =IF(ISERROR(OFFSET('HARGA SATUAN'!$D$6,MATCH(C17,'HARGA SATUAN'!$C$7:$C$1492,0),0)),"",OFFSET('HARGA SATUAN'!$D$6,MATCH(C17,'HARGA SATUAN'!$C$7:$C$1492,0),0)) -> MDU-KD | E17: =IF(B17="+","Unit",IF(ISERROR(OFFSET('HARGA SATUAN'!$E$6,MATCH(C17,'HARGA SATUAN'!$C$7:$C$1492,0),0)),"",OFFSET('HARGA SATUAN'!$E$6,MATCH(C17,'HARGA SATUAN'!$C$7:$C$1492,0),0))) -> Unit | F17: =IF(ISERROR(OFFSET($D$223,MATCH(A17,$F$224:$F$373,0),0)),"",OFFSET($D$223,MATCH(A17,$F$224:$F$373,0),0)) -> 1 | G17: =IF(ISERROR(OFFSET('HARGA SATUAN'!$I$6,MATCH(C17,'HARGA SATUAN'!$C$7:$C$1492,0),0)),"",OFFSET('HARGA SATUAN'!$I$6,MATCH(C17,'HARGA SATUAN'!$C$7:$C$1492,0),0)) -> 14217900 | H17: =IF(OR(D17="MDU",D17="MDU-KD"),G17*F17,0) -> 14217900 | I17: =IF(D17="HDW",G17*F17,0) -> 0 | J17: =IF(D17="JASA",G17*F17,0) -> 0 | K17: =SUM(H17:J17) -> 14217900
A18: 3 | B18: =IF(C18="","",A18) -> 3 | C18: =IF(ISERROR(OFFSET($C$223,MATCH(A18,$F$224:$F$373,0),0)),"",OFFSET($C$223,MATCH(A18,$F$224:$F$373,0),0)) -> Trafo 3 phasa 100 kVA YNyn0 | D18: =IF(ISERROR(OFFSET('HARGA SATUAN'!$D$6,MATCH(C18,'HARGA SATUAN'!$C$7:$C$1492,0),0)),"",OFFSET('HARGA SATUAN'!$D$6,MATCH(C18,'HARGA SATUAN'!$C$7:$C$1492,0),0)) -> MDU-KD | E18: =IF(B18="+","Unit",IF(ISERROR(OFFSET('HARGA SATUAN'!$E$6,MATCH(C18,'HARGA SATUAN'!$C$7:$C$1492,0),0)),"",OFFSET('HARGA SATUAN'!$E$6,MATCH(C18,'HARGA SATUAN'!$C$7:$C$1492,0),0))) -> Bh | F18: =IF(ISERROR(OFFSET($D$223,MATCH(A18,$F$224:$F$373,0),0)),"",OFFSET($D$223,MATCH(A18,$F$224:$F$373,0),0)) -> 1 | G18: =IF(ISERROR(OFFSET('HARGA SATUAN'!$I$6,MATCH(C18,'HARGA SATUAN'!$C$7:$C$1492,0),0)),"",OFFSET('HARGA SATUAN'!$I$6,MATCH(C18,'HARGA SATUAN'!$C$7:$C$1492,0),0)) -> 56838600 | H18: =IF(OR(D18="MDU",D18="MDU-KD"),G18*F18,0) -> 56838600 | I18: =IF(D18="HDW",G18*F18,0) -> 0 | J18: =IF(D18="JASA",G18*F18,0) -> 0 | K18: =SUM(H18:J18) -> 56838600
A19: 4 | B19: =IF(C19="","",A19) -> 4 | C19: =IF(ISERROR(OFFSET($C$223,MATCH(A19,$F$224:$F$373,0),0)),"",OFFSET($C$223,MATCH(A19,$F$224:$F$373,0),0)) -> FCO Polymer | D19: =IF(ISERROR(OFFSET('HARGA SATUAN'!$D$6,MATCH(C19,'HARGA SATUAN'!$C$7:$C$1492,0),0)),"",OFFSET('HARGA SATUAN'!$D$6,MATCH(C19,'HARGA SATUAN'!$C$7:$C$1492,0),0)) -> MDU-KD | E19: =IF(B19="+","Unit",IF(ISERROR(OFFSET('HARGA SATUAN'!$E$6,MATCH(C19,'HARGA SATUAN'!$C$7:$C$1492,0),0)),"",OFFSET('HARGA SATUAN'!$E$6,MATCH(C19,'HARGA SATUAN'!$C$7:$C$1492,0),0))) -> Bh | F19: =IF(ISERROR(OFFSET($D$223,MATCH(A19,$F$224:$F$373,0),0)),"",OFFSET($D$223,MATCH(A19,$F$224:$F$373,0),0)) -> 3 | G19: =IF(ISERROR(OFFSET('HARGA SATUAN'!$I$6,MATCH(C19,'HARGA SATUAN'!$C$7:$C$1492,0),0)),"",OFFSET('HARGA SATUAN'!$I$6,MATCH(C19,'HARGA SATUAN'!$C$7:$C$1492,0),0)) -> 848250 | H19: =IF(OR(D19="MDU",D19="MDU-KD"),G19*F19,0) -> 2544750 | I19: =IF(D19="HDW",G19*F19,0) -> 0 | J19: =IF(D19="JASA",G19*F19,0) -> 0 | K19: =SUM(H19:J19) -> 2544750
A20: 5 | B20: =IF(C20="","",A20) -> 5 | C20: =IF(ISERROR(OFFSET($C$223,MATCH(A20,$F$224:$F$373,0),0)),"",OFFSET($C$223,MATCH(A20,$F$224:$F$373,0),0)) -> Lightning Arester (Polymer) 21 KV, 10 KA | D20: =IF(ISERROR(OFFSET('HARGA SATUAN'!$D$6,MATCH(C20,'HARGA SATUAN'!$C$7:$C$1492,0),0)),"",OFFSET('HARGA SATUAN'!$D$6,MATCH(C20,'HARGA SATUAN'!$C$7:$C$1492,0),0)) -> MDU-KD | E20: =IF(B20="+","Unit",IF(ISERROR(OFFSET('HARGA SATUAN'!$E$6,MATCH(C20,'HARGA SATUAN'!$C$7:$C$1492,0),0)),"",OFFSET('HARGA SATUAN'!$E$6,MATCH(C20,'HARGA SATUAN'!$C$7:$C$1492,0),0))) -> Bh | F20: =IF(ISERROR(OFFSET($D$223,MATCH(A20,$F$224:$F$373,0),0)),"",OFFSET($D$223,MATCH(A20,$F$224:$F$373,0),0)) -> 3 | G20: =IF(ISERROR(OFFSET('HARGA SATUAN'!$I$6,MATCH(C20,'HARGA SATUAN'!$C$7:$C$1492,0),0)),"",OFFSET('HARGA SATUAN'!$I$6,MATCH(C20,'HARGA SATUAN'!$C$7:$C$1492,0),0)) -> 725900 | H20: =IF(OR(D20="MDU",D20="MDU-KD"),G20*F20,0) -> 2177700 | I20: =IF(D20="HDW",G20*F20,0) -> 0 | J20: =IF(D20="JASA",G20*F20,0) -> 0 | K20: =SUM(H20:J20) -> 2177700
A21: 6 | B21: =IF(C21="","",A21) -> 6 | C21: =IF(ISERROR(OFFSET($C$223,MATCH(A21,$F$224:$F$373,0),0)),"",OFFSET($C$223,MATCH(A21,$F$224:$F$373,0),0)) -> Isolator Tumpu ( Pin Post ) 20 KV Porcelein | D21: =IF(ISERROR(OFFSET('HARGA SATUAN'!$D$6,MATCH(C21,'HARGA SATUAN'!$C$7:$C$1492,0),0)),"",OFFSET('HARGA SATUAN'!$D$6,MATCH(C21,'HARGA SATUAN'!$C$7:$C$1492,0),0)) -> MDU-KD | E21: =IF(B21="+","Unit",IF(ISERROR(OFFSET('HARGA SATUAN'!$E$6,MATCH(C21,'HARGA SATUAN'!$C$7:$C$1492,0),0)),"",OFFSET('HARGA SATUAN'!$E$6,MATCH(C21,'HARGA SATUAN'!$C$7:$C$1492,0),0))) -> Bh | F21: =IF(ISERROR(OFFSET($D$223,MATCH(A21,$F$224:$F$373,0),0)),"",OFFSET($D$223,MATCH(A21,$F$224:$F$373,0),0)) -> 3 | G21: =IF(ISERROR(OFFSET('HARGA SATUAN'!$I$6,MATCH(C21,'HARGA SATUAN'!$C$7:$C$1492,0),0)),"",OFFSET('HARGA SATUAN'!$I$6,MATCH(C21,'HARGA SATUAN'!$C$7:$C$1492,0),0)) -> 235900 | H21: =IF(OR(D21="MDU",D21="MDU-KD"),G21*F21,0) -> 707700 | I21: =IF(D21="HDW",G21*F21,0) -> 0 | J21: =IF(D21="JASA",G21*F21,0) -> 0 | K21: =SUM(H21:J21) -> 707700
A22: 7 | B22: =IF(C22="","",A22) -> 7 | C22: =IF(ISERROR(OFFSET($C$223,MATCH(A22,$F$224:$F$373,0),0)),"",OFFSET($C$223,MATCH(A22,$F$224:$F$373,0),0)) -> Isolator Tarik ( Suspension Polymer ) 20 KV | D22: =IF(ISERROR(OFFSET('HARGA SATUAN'!$D$6,MATCH(C22,'HARGA SATUAN'!$C$7:$C$1492,0),0)),"",OFFSET('HARGA SATUAN'!$D$6,MATCH(C22,'HARGA SATUAN'!$C$7:$C$1492,0),0)) -> MDU-KD | E22: =IF(B22="+","Unit",IF(ISERROR(OFFSET('HARGA SATUAN'!$E$6,MATCH(C22,'HARGA SATUAN'!$C$7:$C$1492,0),0)),"",OFFSET('HARGA SATUAN'!$E$6,MATCH(C22,'HARGA SATUAN'!$C$7:$C$1492,0),0))) -> Set | F22: =IF(ISERROR(OFFSET($D$223,MATCH(A22,$F$224:$F$373,0),0)),"",OFFSET($D$223,MATCH(A22,$F$224:$F$373,0),0)) -> 6 | G22: =IF(ISERROR(OFFSET('HARGA SATUAN'!$I$6,MATCH(C22,'HARGA SATUAN'!$C$7:$C$1492,0),0)),"",OFFSET('HARGA SATUAN'!$I$6,MATCH(C22,'HARGA SATUAN'!$C$7:$C$1492,0),0)) -> 205700 | H22: =IF(OR(D22="MDU",D22="MDU-KD"),G22*F22,0) -> 1234200 | I22: =IF(D22="HDW",G22*F22,0) -> 0 | J22: =IF(D22="JASA",G22*F22,0) -> 0 | K22: =SUM(H22:J22) -> 1234200
A23: 8 | B23: =IF(C23="","",A23) -> 8 | C23: =IF(ISERROR(OFFSET($C$223,MATCH(A23,$F$224:$F$373,0),0)),"",OFFSET($C$223,MATCH(A23,$F$224:$F$373,0),0)) -> AAAC 70 mm² | D23: =IF(ISERROR(OFFSET('HARGA SATUAN'!$D$6,MATCH(C23,'HARGA SATUAN'!$C$7:$C$1492,0),0)),"",OFFSET('HARGA SATUAN'!$D$6,MATCH(C23,'HARGA SATUAN'!$C$7:$C$1492,0),0)) -> MDU-KD | E23: =IF(B23="+","Unit",IF(ISERROR(OFFSET('HARGA SATUAN'!$E$6,MATCH(C23,'HARGA SATUAN'!$C$7:$C$1492,0),0)),"",OFFSET('HARGA SATUAN'!$E$6,MATCH(C23,'HARGA SATUAN'!$C$7:$C$1492,0),0))) -> Mtr | F23: =IF(ISERROR(OFFSET($D$223,MATCH(A23,$F$224:$F$373,0),0)),"",OFFSET($D$223,MATCH(A23,$F$224:$F$373,0),0)) -> 229 | G23: =IF(ISERROR(OFFSET('HARGA SATUAN'!$I$6,MATCH(C23,'HARGA SATUAN'!$C$7:$C$1492,0),0)),"",OFFSET('HARGA SATUAN'!$I$6,MATCH(C23,'HARGA SATUAN'!$C$7:$C$1492,0),0)) -> 14200 | H23: =IF(OR(D23="MDU",D23="MDU-KD"),G23*F23,0) -> 3251800 | I23: =IF(D23="HDW",G23*F23,0) -> 0 | J23: =IF(D23="JASA",G23*F23,0) -> 0 | K23: =SUM(H23:J23) -> 3251800
A24: 9 | B24: =IF(C24="","",A24) -> 9 | C24: =IF(ISERROR(OFFSET($C$223,MATCH(A24,$F$224:$F$373,0),0)),"",OFFSET($C$223,MATCH(A24,$F$224:$F$373,0),0)) -> NFA2X-T 3x70+1x70 | D24: =IF(ISERROR(OFFSET('HARGA SATUAN'!$D$6,MATCH(C24,'HARGA SATUAN'!$C$7:$C$1492,0),0)),"",OFFSET('HARGA SATUAN'!$D$6,MATCH(C24,'HARGA SATUAN'!$C$7:$C$1492,0),0)) -> MDU-KD | E24: =IF(B24="+","Unit",IF(ISERROR(OFFSET('HARGA SATUAN'!$E$6,MATCH(C24,'HARGA SATUAN'!$C$7:$C$1492,0),0)),"",OFFSET('HARGA SATUAN'!$E$6,MATCH(C24,'HARGA SATUAN'!$C$7:$C$1492,0),0))) -> Mtr | F24: =IF(ISERROR(OFFSET($D$223,MATCH(A24,$F$224:$F$373,0),0)),"",OFFSET($D$223,MATCH(A24,$F$224:$F$373,0),0)) -> 12 | G24: =IF(ISERROR(OFFSET('HARGA SATUAN'!$I$6,MATCH(C24,'HARGA SATUAN'!$C$7:$C$1492,0),0)),"",OFFSET('HARGA SATUAN'!$I$6,MATCH(C24,'HARGA SATUAN'!$C$7:$C$1492,0),0)) -> 54500 | H24: =IF(OR(D24="MDU",D24="MDU-KD"),G24*F24,0) -> 654000 | I24: =IF(D24="HDW",G24*F24,0) -> 0 | J24: =IF(D24="JASA",G24*F24,0) -> 0 | K24: =SUM(H24:J24) -> 654000
A25: 10 | B25: =IF(C25="","",A25) | C25: =IF(ISERROR(OFFSET($C$223,MATCH(A25,$F$224:$F$373,0),0)),"",OFFSET($C$223,MATCH(A25,$F$224:$F$373,0),0)) | D25: =IF(ISERROR(OFFSET('HARGA SATUAN'!$D$6,MATCH(C25,'HARGA SATUAN'!$C$7:$C$1492,0),0)),"",OFFSET('HARGA SATUAN'!$D$6,MATCH(C25,'HARGA SATUAN'!$C$7:$C$1492,0),0)) | E25: =IF(B25="+","Unit",IF(ISERROR(OFFSET('HARGA SATUAN'!$E$6,MATCH(C25,'HARGA SATUAN'!$C$7:$C$1492,0),0)),"",OFFSET('HARGA SATUAN'!$E$6,MATCH(C25,'HARGA SATUAN'!$C$7:$C$1492,0),0))) -> 0 | F25: =IF(ISERROR(OFFSET($D$223,MATCH(A25,$F$224:$F$373,0),0)),"",OFFSET($D$223,MATCH(A25,$F$224:$F$373,0),0)) | G25: =IF(ISERROR(OFFSET('HARGA SATUAN'!$I$6,MATCH(C25,'HARGA SATUAN'!$C$7:$C$1492,0),0)),"",OFFSET('HARGA SATUAN'!$I$6,MATCH(C25,'HARGA SATUAN'!$C$7:$C$1492,0),0)) -> 0 | H25: =IF(OR(D25="MDU",D25="MDU-KD"),G25*F25,0) -> 0 | I25: =IF(D25="HDW",G25*F25,0) -> 0 | J25: =IF(D25="JASA",G25*F25,0) -> 0 | K25: =SUM(H25:J25) -> 0
A26: 11 | B26: =IF(C26="","",A26) | C26: =IF(ISERROR(OFFSET($C$223,MATCH(A26,$F$224:$F$373,0),0)),"",OFFSET($C$223,MATCH(A26,$F$224:$F$373,0),0)) | D26: =IF(ISERROR(OFFSET('HARGA SATUAN'!$D$6,MATCH(C26,'HARGA SATUAN'!$C$7:$C$1492,0),0)),"",OFFSET('HARGA SATUAN'!$D$6,MATCH(C26,'HARGA SATUAN'!$C$7:$C$1492,0),0)) | E26: =IF(B26="+","Unit",IF(ISERROR(OFFSET('HARGA SATUAN'!$E$6,MATCH(C26,'HARGA SATUAN'!$C$7:$C$1492,0),0)),"",OFFSET('HARGA SATUAN'!$E$6,MATCH(C26,'HARGA SATUAN'!$C$7:$C$1492,0),0))) -> 0 | F26: =IF(ISERROR(OFFSET($D$223,MATCH(A26,$F$224:$F$373,0),0)),"",OFFSET($D$223,MATCH(A26,$F$224:$F$373,0),0)) | G26: =IF(ISERROR(OFFSET('HARGA SATUAN'!$I$6,MATCH(C26,'HARGA SATUAN'!$C$7:$C$1492,0),0)),"",OFFSET('HARGA SATUAN'!$I$6,MATCH(C26,'HARGA SATUAN'!$C$7:$C$1492,0),0)) -> 0 | H26: =IF(OR(D26="MDU",D26="MDU-KD"),G26*F26,0) -> 0 | I26: =IF(D26="HDW",G26*F26,0) -> 0 | J26: =IF(D26="JASA",G26*F26,0) -> 0 | K26: =SUM(H26:J26) -> 0
A27: 12 | B27: =IF(C27="","",A27) | C27: =IF(ISERROR(OFFSET($C$223,MATCH(A27,$F$224:$F$373,0),0)),"",OFFSET($C$223,MATCH(A27,$F$224:$F$373,0),0)) | D27: =IF(ISERROR(OFFSET('HARGA SATUAN'!$D$6,MATCH(C27,'HARGA SATUAN'!$C$7:$C$1492,0),0)),"",OFFSET('HARGA SATUAN'!$D$6,MATCH(C27,'HARGA SATUAN'!$C$7:$C$1492,0),0)) | E27: =IF(B27="+","Unit",IF(ISERROR(OFFSET('HARGA SATUAN'!$E$6,MATCH(C27,'HARGA SATUAN'!$C$7:$C$1492,0),0)),"",OFFSET('HARGA SATUAN'!$E$6,MATCH(C27,'HARGA SATUAN'!$C$7:$C$1492,0),0))) -> 0 | F27: =IF(ISERROR(OFFSET($D$223,MATCH(A27,$F$224:$F$373,0),0)),"",OFFSET($D$223,MATCH(A27,$F$224:$F$373,0),0)) | G27: =IF(ISERROR(OFFSET('HARGA SATUAN'!$I$6,MATCH(C27,'HARGA SATUAN'!$C$7:$C$1492,0),0)),"",OFFSET('HARGA SATUAN'!$I$6,MATCH(C27,'HARGA SATUAN'!$C$7:$C$1492,0),0)) -> 0 | H27: =IF(OR(D27="MDU",D27="MDU-KD"),G27*F27,0) -> 0 | I27: =IF(D27="HDW",G27*F27,0) -> 0 | J27: =IF(D27="JASA",G27*F27,0) -> 0 | K27: =SUM(H27:J27) -> 0
... A165: 150 | B165: =IF(C165="","",A165) | C165: =IF(ISERROR(OFFSET($C$223,MATCH(A165,$F$224:$F$373,0),0)),"",OFFSET($C$223,MATCH(A165,$F$224:$F$373,0),0)) | D165: =IF(ISERROR(OFFSET('HARGA SATUAN'!$D$6,MATCH(C165,'HARGA SATUAN'!$C$7:$C$1492,0),0)),"",OFFSET('HARGA SATUAN'!$D$6,MATCH(C165,'HARGA SATUAN'!$C$7:$C$1492,0),0)) | E165: =IF(B165="+","Unit",IF(ISERROR(OFFSET('HARGA SATUAN'!$E$6,MATCH(C165,'HARGA SATUAN'!$C$7:$C$1492,0),0)),"",OFFSET('HARGA SATUAN'!$E$6,MATCH(C165,'HARGA SATUAN'!$C$7:$C$1492,0),0))) -> 0 | F165: =IF(ISERROR(OFFSET($D$223,MATCH(A165,$F$224:$F$373,0),0)),"",OFFSET($D$223,MATCH(A165,$F$224:$F$373,0),0)) | G165: =IF(ISERROR(OFFSET('HARGA SATUAN'!$I$6,MATCH(C165,'HARGA SATUAN'!$C$7:$C$1492,0),0)),"",OFFSET('HARGA SATUAN'!$I$6,MATCH(C165,'HARGA SATUAN'!$C$7:$C$1492,0),0)) -> 0 | H165: =IF(OR(D165="MDU",D165="MDU-KD"),G165*F165,0) -> 0 | I165: =IF(D165="HDW",G165*F165,0) -> 0 | J165: =IF(D165="JASA",G165*F165,0) -> 0 | K165: =SUM(H165:J165) -> 0
C168: Jumlah MDU - Hardware - Jasa | G168: : | H168: =SUM(H14:H167) -> 83130850 | I168: =SUM(I14:I167) -> 0 | J168: =SUM(J14:J167) -> 0 | K168: =SUM(K14:K167) -> 83130850
C169: PPN 10% | G169: : | H169: =H168*0.1 -> 8313085 | I169: =I168*0.1 -> 0 | J169: =J168*0.1 -> 0 | K169: =K168*0.1 -> 8313085
C170: Jumlah Total | G170: : | H170: =SUM(H168:H169) -> 91443935 | I170: =SUM(I168:I169) -> 0 | J170: =SUM(J168:J169) -> 0 | K170: =SUM(K168:K169) -> 91443935
B171: ="Terbilang : ( "&L172&" Rupiah )" -> #NAME?
L172: =PROPER([91]!terbilang(K170)) -> #NAME?
B173: ="Harga yang dipakai adalah "&'HARGA SATUAN'!I5&"" -> Harga yang dipakai adalah RAB HSS 2023
B223: NO | C223: JENIS MDU
B224: 1 | C224: =IF(ISERROR(OFFSET('HARGA SATUAN'!$C$6,MATCH('REKAP MDU'!B224,'HARGA SATUAN'!$L$7:$L$1455,0),0)),"",OFFSET('HARGA SATUAN'!$C$6,MATCH('REKAP MDU'!B224,'HARGA SATUAN'!$L$7:$L$1455,0),0)) -> KWH MPB; 1P;230V;5(60)A;1;2W | D224: =SUMIFS(RAB!$F$14:$F$160,RAB!$C$14:$C$160,C224) -> 0 | E224: =IF(D224=0,0,1) -> 0 | F224: =IF(D224=0,0,SUM($E$223:E224)) -> 0
B225: 2 | C225: =IF(ISERROR(OFFSET('HARGA SATUAN'!$C$6,MATCH('REKAP MDU'!B225,'HARGA SATUAN'!$L$7:$L$1455,0),0)),"",OFFSET('HARGA SATUAN'!$C$6,MATCH('REKAP MDU'!B225,'HARGA SATUAN'!$L$7:$L$1455,0),0)) -> KWH Elektronik; 1P; 2W; 230 V; 5(40) A; kls 1 (combo); register drum | D225: =SUMIFS(RAB!$F$14:$F$160,RAB!$C$14:$C$160,C225) -> 0 | E225: =IF(D225=0,0,1) -> 0 | F225: =IF(D225=0,0,SUM($E$223:E225)) -> 0
B226: 3 | C226: =IF(ISERROR(OFFSET('HARGA SATUAN'!$C$6,MATCH('REKAP MDU'!B226,'HARGA SATUAN'!$L$7:$L$1455,0),0)),"",OFFSET('HARGA SATUAN'!$C$6,MATCH('REKAP MDU'!B226,'HARGA SATUAN'!$L$7:$L$1455,0),0)) -> KWH Elektronik; 1P; 2W; 230 V; 5(100) A; kls 1 termasuk modem 3G/4G | D226: =SUMIFS(RAB!$F$14:$F$160,RAB!$C$14:$C$160,C226) -> 0 | E226: =IF(D226=0,0,1) -> 0 | F226: =IF(D226=0,0,SUM($E$223:E226)) -> 0
B227: 4 | C227: =IF(ISERROR(OFFSET('HARGA SATUAN'!$C$6,MATCH('REKAP MDU'!B227,'HARGA SATUAN'!$L$7:$L$1455,0),0)),"",OFFSET('HARGA SATUAN'!$C$6,MATCH('REKAP MDU'!B227,'HARGA SATUAN'!$L$7:$L$1455,0),0)) -> KWH Elektronik; 3P; 4W; 57.7-100V/220-400V; 5 A; kls 0.2 (meter pembanding) | D227: =SUMIFS(RAB!$F$14:$F$160,RAB!$C$14:$C$160,C227) -> 0 | E227: =IF(D227=0,0,1) -> 0 | F227: =IF(D227=0,0,SUM($E$223:E227)) -> 0
B228: 5 | C228: =IF(ISERROR(OFFSET('HARGA SATUAN'!$C$6,MATCH('REKAP MDU'!B228,'HARGA SATUAN'!$L$7:$L$1455,0),0)),"",OFFSET('HARGA SATUAN'!$C$6,MATCH('REKAP MDU'!B228,'HARGA SATUAN'!$L$7:$L$1455,0),0)) -> KWH Elektronik; 3P; 4W; 220/380V; 5(80) A; kls 1 (Pengukuran Langsung) | D228: =SUMIFS(RAB!$F$14:$F$160,RAB!$C$14:$C$160,C228) -> 0 | E228: =IF(D228=0,0,1) -> 0 | F228: =IF(D228=0,0,SUM($E$223:E228)) -> 0
B229: 6 | C229: =IF(ISERROR(OFFSET('HARGA SATUAN'!$C$6,MATCH('REKAP MDU'!B229,'HARGA SATUAN'!$L$7:$L$1455,0),0)),"",OFFSET('HARGA SATUAN'!$C$6,MATCH('REKAP MDU'!B229,'HARGA SATUAN'!$L$7:$L$1455,0),0)) -> KWH Elektronik; 3P; 4W; 57.7-100V/220-400V; 5(10) A; kls 0.5 (Pengukuran Tidak Langsung) | D229: =SUMIFS(RAB!$F$14:$F$160,RAB!$C$14:$C$160,C229) -> 0 | E229: =IF(D229=0,0,1) -> 0 | F229: =IF(D229=0,0,SUM($E$223:E229)) -> 0
B230: 7 | C230: =IF(ISERROR(OFFSET('HARGA SATUAN'!$C$6,MATCH('REKAP MDU'!B230,'HARGA SATUAN'!$L$7:$L$1455,0),0)),"",OFFSET('HARGA SATUAN'!$C$6,MATCH('REKAP MDU'!B230,'HARGA SATUAN'!$L$7:$L$1455,0),0)) -> KWH Elektronik; 3P; 4W; 220/380V; 5(10); kls 1 (Pengukuran Tidak Langsung) | D230: =SUMIFS(RAB!$F$14:$F$160,RAB!$C$14:$C$160,C230) -> 1 | E230: =IF(D230=0,0,1) -> 1 | F230: =IF(D230=0,0,SUM($E$223:E230)) -> 1
B231: 8 | C231: =IF(ISERROR(OFFSET('HARGA SATUAN'!$C$6,MATCH('REKAP MDU'!B231,'HARGA SATUAN'!$L$7:$L$1455,0),0)),"",OFFSET('HARGA SATUAN'!$C$6,MATCH('REKAP MDU'!B231,'HARGA SATUAN'!$L$7:$L$1455,0),0)) -> MCB 1 Fasa 2 A | D231: =SUMIFS(RAB!$F$14:$F$160,RAB!$C$14:$C$160,C231) -> 0 | E231: =IF(D231=0,0,1) -> 0 | F231: =IF(D231=0,0,SUM($E$223:E231)) -> 0
B232: 9 | C232: =IF(ISERROR(OFFSET('HARGA SATUAN'!$C$6,MATCH('REKAP MDU'!B232,'HARGA SATUAN'!$L$7:$L$1455,0),0)),"",OFFSET('HARGA SATUAN'!$C$6,MATCH('REKAP MDU'!B232,'HARGA SATUAN'!$L$7:$L$1455,0),0)) -> MCB 1 Fasa 4 A | D232: =SUMIFS(RAB!$F$14:$F$160,RAB!$C$14:$C$160,C232) -> 0 | E232: =IF(D232=0,0,1) -> 0 | F232: =IF(D232=0,0,SUM($E$223:E232)) -> 0
B233: 10 | C233: =IF(ISERROR(OFFSET('HARGA SATUAN'!$C$6,MATCH('REKAP MDU'!B233,'HARGA SATUAN'!$L$7:$L$1455,0),0)),"",OFFSET('HARGA SATUAN'!$C$6,MATCH('REKAP MDU'!B233,'HARGA SATUAN'!$L$7:$L$1455,0),0)) -> MCB 1 Fasa 6 A | D233: =SUMIFS(RAB!$F$14:$F$160,RAB!$C$14:$C$160,C233) -> 0 | E233: =IF(D233=0,0,1) -> 0 | F233: =IF(D233=0,0,SUM($E$223:E233)) -> 0
B234: 11 | C234: =IF(ISERROR(OFFSET('HARGA SATUAN'!$C$6,MATCH('REKAP MDU'!B234,'HARGA SATUAN'!$L$7:$L$1455,0),0)),"",OFFSET('HARGA SATUAN'!$C$6,MATCH('REKAP MDU'!B234,'HARGA SATUAN'!$L$7:$L$1455,0),0)) -> MCB 1 Fasa 10 A | D234: =SUMIFS(RAB!$F$14:$F$160,RAB!$C$14:$C$160,C234) -> 0 | E234: =IF(D234=0,0,1) -> 0 | F234: =IF(D234=0,0,SUM($E$223:E234)) -> 0
B235: 12 | C235: =IF(ISERROR(OFFSET('HARGA SATUAN'!$C$6,MATCH('REKAP MDU'!B235,'HARGA SATUAN'!$L$7:$L$1455,0),0)),"",OFFSET('HARGA SATUAN'!$C$6,MATCH('REKAP MDU'!B235,'HARGA SATUAN'!$L$7:$L$1455,0),0)) -> MCB 1 Fasa 16 A | D235: =SUMIFS(RAB!$F$14:$F$160,RAB!$C$14:$C$160,C235) -> 0 | E235: =IF(D235=0,0,1) -> 0 | F235: =IF(D235=0,0,SUM($E$223:E235)) -> 0
... B373: 150 | C373: =IF(ISERROR(OFFSET('HARGA SATUAN'!$C$6,MATCH('REKAP MDU'!B373,'HARGA SATUAN'!$L$7:$L$1455,0),0)),"",OFFSET('HARGA SATUAN'!$C$6,MATCH('REKAP MDU'!B373,'HARGA SATUAN'!$L$7:$L$1455,0),0)) | D373: =SUMIFS(RAB!$F$14:$F$160,RAB!$C$14:$C$160,C373) -> 0 | E373: =IF(D373=0,0,1) -> 0 | F373: =IF(D373=0,0,SUM($E$223:E373)) -> 0

Sheet Sheet1
D4: 3
D5: 1

Sheet HARGA SATUAN
B2: HARGA SATUAN
B4: NO. | C4: MATERIAL + SIZE | D4: GOL | E4: SAT | F4: RAB SKK 2022 | G4: RAB HSS 2023 | H4: KETERANGAN | I4: HARGA YANG DIPAKAI DI RAB
I5: RAB HSS 2023
K6: =MAX(L7:L1455) -> 137 | M6: =MAX(M7:M1455) -> 2.012275e+08
F7: =(IF(D7="JASA",G7*#REF!,0))+(IF(D7="HDW",G7*#REF!,0))+(IF(D7="MDU",G7*#REF!,0))+(IF(D7="MDU-KD",G7*#REF!,0)) -> 0 | G7: 0 | I7: =IF($I$5=$G$4,G7,(IF($I$5=$F$4,(IF(F7=0,G7,F7)),0))) -> 0 | J7: =IF(D7="MDU-KD",1,0) -> 0 | K7: =IF(D7="HDW",1,0) -> 0 | L7: =IF(J7=1,SUM($J$6:J7),0) -> 0 | M7: =IF(K7=1,SUM($K$6:K7),0) -> 0 | N7: =IF(L7=0,M7,L7) -> 0 | O7: =IF(E7=0,0,IF(LEFT(C7,11)="Tiang Beton",1,0)) -> 0 | P7: =IF(O7=1,SUM($O$6:O7),0) -> 0
B8: A | C8: ALAT PENGUKUR DAN PEMBATAS | F8: =(IF(D8="JASA",G8*'[92]DETAIL USULAN'!$K$58,0))+(IF(D8="HDW",G8*'[92]DETAIL USULAN'!$J$58,0))+(IF(D8="MDU",G8*'[92]DETAIL USULAN'!$I$58,0))+(IF(D8="MDU-KD",G8*'[92]DETAIL USULAN'!$I$58,0)) -> 0 | G8: 0 | I8: =IF($I$5=$G$4,G8,(IF($I$5=$F$4,(IF(F8=0,G8,F8)),0))) -> 0 | J8: =IF(D8="MDU-KD",1,0) -> 0 | K8: =IF(D8="HDW",1,0) -> 0 | L8: =IF(J8=1,SUM($J$6:J8),0) -> 0 | M8: =IF(K8=1,SUM($K$6:K8),0) -> 0 | N8: =IF(L8=0,M8,L8) -> 0 | O8: =IF(E8=0,0,IF(LEFT(C8,11)="Tiang Beton",1,0)) -> 0 | P8: =IF(O8=1,SUM($O$6:O8),0) -> 0
B9: 1 | C9: KWH MPB; 1P;230V;5(60)A;1;2W | D9: MDU-KD | E9: Bh | F9: 294100 | G9: 327600 | I9: =IF($I$5=$G$4,G9,(IF($I$5=$F$4,F9,0))) -> 327600 | J9: =IF(D9="MDU-KD",1,0) -> 1 | K9: =IF(D9="HDW",1,0) -> 0 | L9: =IF(J9=1,SUM($J$6:J9),0) -> 1 | M9: =IF(K9=1,SUM($K$6:K9),0) -> 0 | N9: =IF(L9=0,M9,L9) -> 1 | O9: =IF(E9=0,0,IF(LEFT(C9,11)="Tiang Beton",1,0)) -> 0 | P9: =IF(O9=1,SUM($O$6:O9),0) -> 0
B10: 2 | C10: KWH MPB; 3P; 4W; 230/400 V; 5(80) A; Class 1 | D10: HDW | E10: Bh | F10: 1719200 | G10: 1719200 | I10: =IF($I$5=$G$4,G10,(IF($I$5=$F$4,F10,0))) -> 1719200 | J10: =IF(D10="MDU-KD",1,0) -> 0 | K10: =IF(D10="HDW",1,0) -> 1 | L10: =IF(J10=1,SUM($J$6:J10),0) -> 0 | M10: =IF(K10=1,SUM($K$6:K10),0) -> 138 | N10: =IF(L10=0,M10,L10) -> 138 | O10: =IF(E10=0,0,IF(LEFT(C10,11)="Tiang Beton",1,0)) -> 0 | P10: =IF(O10=1,SUM($O$6:O10),0) -> 0
B11: 3 | C11: KWH Elektronik; 1P; 2W; 230 V; 5(40) A; kls 1 (combo); register drum | D11: MDU-KD | E11: Bh | F11: 151000 | G11: 168200 | I11: =IF($I$5=$G$4,G11,(IF($I$5=$F$4,F11,0))) -> 168200 | J11: =IF(D11="MDU-KD",1,0) -> 1 | K11: =IF(D11="HDW",1,0) -> 0 | L11: =IF(J11=1,SUM($J$6:J11),0) -> 2 | M11: =IF(K11=1,SUM($K$6:K11),0) -> 0 | N11: =IF(L11=0,M11,L11) -> 2 | O11: =IF(E11=0,0,IF(LEFT(C11,11)="Tiang Beton",1,0)) -> 0 | P11: =IF(O11=1,SUM($O$6:O11),0) -> 0
B12: 4 | C12: KWH Elektronik; 1P; 2W; 230 V; 5(100) A; kls 1 termasuk modem 3G/4G | D12: MDU-KD | E12: Bh | F12: 1430000 | G12: 1740750 | I12: =IF($I$5=$G$4,G12,(IF($I$5=$F$4,F12,0))) -> 1740750 | J12: =IF(D12="MDU-KD",1,0) -> 1 | K12: =IF(D12="HDW",1,0) -> 0 | L12: =IF(J12=1,SUM($J$6:J12),0) -> 3 | M12: =IF(K12=1,SUM($K$6:K12),0) -> 0 | N12: =IF(L12=0,M12,L12) -> 3 | O12: =IF(E12=0,0,IF(LEFT(C12,11)="Tiang Beton",1,0)) -> 0 | P12: =IF(O12=1,SUM($O$6:O12),0) -> 0
B13: 5 | C13: KWH Elektronik; 3P; 4W; 57.7-100V/220-400V; 5 A; kls 0.2 (meter pembanding) | D13: MDU-KD | E13: Bh | F13: 16495000 | G13: 18373800 | I13: =IF($I$5=$G$4,G13,(IF($I$5=$F$4,F13,0))) -> 18373800 | J13: =IF(D13="MDU-KD",1,0) -> 1 | K13: =IF(D13="HDW",1,0) -> 0 | L13: =IF(J13=1,SUM($J$6:J13),0) -> 4 | M13: =IF(K13=1,SUM($K$6:K13),0) -> 0 | N13: =IF(L13=0,M13,L13) -> 4 | O13: =IF(E13=0,0,IF(LEFT(C13,11)="Tiang Beton",1,0)) -> 0 | P13: =IF(O13=1,SUM($O$6:O13),0) -> 0
B14: 6 | C14: KWH Elektronik; 3P; 4W; 220/380V; 5(80) A; kls 1 (Pengukuran Langsung) | D14: MDU-KD | E14: Bh | F14: 1281430 | G14: 1427400 | I14: =IF($I$5=$G$4,G14,(IF($I$5=$F$4,F14,0))) -> 1427400 | J14: =IF(D14="MDU-KD",1,0) -> 1 | K14: =IF(D14="HDW",1,0) -> 0 | L14: =IF(J14=1,SUM($J$6:J14),0) -> 5 | M14: =IF(K14=1,SUM($K$6:K14),0) -> 0 | N14: =IF(L14=0,M14,L14) -> 5 | O14: =IF(E14=0,0,IF(LEFT(C14,11)="Tiang Beton",1,0)) -> 0 | P14: =IF(O14=1,SUM($O$6:O14),0) -> 0
B15: 7 | C15: KWH Elektronik; 3P; 4W; 57.7-100V/220-400V; 5(10) A; kls 0.5 (Pengukuran Tidak Langsung) | D15: MDU-KD | E15: Bh | F15: 1344430 | G15: 1497600 | I15: =IF($I$5=$G$4,G15,(IF($I$5=$F$4,F15,0))) -> 1497600 | J15: =IF(D15="MDU-KD",1,0) -> 1 | K15: =IF(D15="HDW",1,0) -> 0 | L15: =IF(J15=1,SUM($J$6:J15),0) -> 6 | M15: =IF(K15=1,SUM($K$6:K15),0) -> 0 | N15: =IF(L15=0,M15,L15) -> 6 | O15: =IF(E15=0,0,IF(LEFT(C15,11)="Tiang Beton",1,0)) -> 0 | P15: =IF(O15=1,SUM($O$6:O15),0) -> 0
B16: 8 | C16: KWH Elektronik; 3P; 4W; 220/380V; 5(10); kls 1 (Pengukuran Tidak Langsung) | D16: MDU-KD | E16: Bh | F16: 1350430 | G16: 1504200 | I16: =IF($I$5=$G$4,G16,(IF($I$5=$F$4,F16,0))) -> 1504200 | J16: =IF(D16="MDU-KD",1,0) -> 1 | K16: =IF(D16="HDW",1,0) -> 0 | L16: =IF(J16=1,SUM($J$6:J16),0) -> 7 | M16: =IF(K16=1,SUM($K$6:K16),0) -> 0 | N16: =IF(L16=0,M16,L16) -> 7 | O16: =IF(E16=0,0,IF(LEFT(C16,11)="Tiang Beton",1,0)) -> 0 | P16: =IF(O16=1,SUM($O$6:O16),0) -> 0
B17: 9 | C17: Modem 3G/4G | D17: HDW | E17: Unit | F17: 1000000 | G17: 1113900 | I17: =IF($I$5=$G$4,G17,(IF($I$5=$F$4,F17,0))) -> 1113900 | J17: =IF(D17="MDU-KD",1,0) -> 0 | K17: =IF(D17="HDW",1,0) -> 1 | L17: =IF(J17=1,SUM($J$6:J17),0) -> 0 | M17: =IF(K17=1,SUM($K$6:K17),0) -> 139 | N17: =IF(L17=0,M17,L17) -> 139 | O17: =IF(E17=0,0,IF(LEFT(C17,11)="Tiang Beton",1,0)) -> 0 | P17: =IF(O17=1,SUM($O$6:O17),0) -> 0
B18: 10 | C18: MCB 1 Fasa 2 A | D18: MDU-KD | E18: Bh | F18: 35000 | G18: 39000 | I18: =IF($I$5=$G$4,G18,(IF($I$5=$F$4,F18,0))) -> 39000 | J18: =IF(D18="MDU-KD",1,0) -> 1 | K18: =IF(D18="HDW",1,0) -> 0 | L18: =IF(J18=1,SUM($J$6:J18),0) -> 8 | M18: =IF(K18=1,SUM($K$6:K18),0) -> 0 | N18: =IF(L18=0,M18,L18) -> 8 | O18: =IF(E18=0,0,IF(LEFT(C18,11)="Tiang Beton",1,0)) -> 0 | P18: =IF(O18=1,SUM($O$6:O18),0) -> 0
B19: 11 | C19: MCB 1 Fasa 4 A | D19: MDU-KD | E19: Bh | F19: 35000 | G19: 39000 | I19: =IF($I$5=$G$4,G19,(IF($I$5=$F$4,F19,0))) -> 39000 | J19: =IF(D19="MDU-KD",1,0) -> 1 | K19: =IF(D19="HDW",1,0) -> 0 | L19: =IF(J19=1,SUM($J$6:J19),0) -> 9 | M19: =IF(K19=1,SUM($K$6:K19),0) -> 0 | N19: =IF(L19=0,M19,L19) -> 9 | O19: =IF(E19=0,0,IF(LEFT(C19,11)="Tiang Beton",1,0)) -> 0 | P19: =IF(O19=1,SUM($O$6:O19),0) -> 0
B20: 12 | C20: MCB 1 Fasa 6 A | D20: MDU-KD | E20: Bh | F20: 35000 | G20: 39000 | I20: =IF($I$5=$G$4,G20,(IF($I$5=$F$4,F20,0))) -> 39000 | J20: =IF(D20="MDU-KD",1,0) -> 1 | K20: =IF(D20="HDW",1,0) -> 0 | L20: =IF(J20=1,SUM($J$6:J20),0) -> 10 | M20: =IF(K20=1,SUM($K$6:K20),0) -> 0 | N20: =IF(L20=0,M20,L20) -> 10 | O20: =IF(E20=0,0,IF(LEFT(C20,11)="Tiang Beton",1,0)) -> 0 | P20: =IF(O20=1,SUM($O$6:O20),0) -> 0
... B79: 71 | C79: CT TM Outdoor 150/5 | D79: MDU-KD | E79: Bh | F79: 3826640 | G79: 7842800 | I79: =IF($I$5=$G$4,G79,(IF($I$5=$F$4,F79,0))) -> 7842800 | J79: =IF(D79="MDU-KD",1,0) -> 1 | K79: =IF(D79="HDW",1,0) -> 0 | L79: =IF(J79=1,SUM($J$6:J79),0) -> 55 | M79: =IF(K79=1,SUM($K$6:K79),0) -> 0 | N79: =IF(L79=0,M79,L79) -> 55 | O79: =IF(E79=0,0,IF(LEFT(C79,11)="Tiang Beton",1,0)) -> 0 | P79: =IF(O79=1,SUM($O$6:O79),0) -> 0
B80: 72 | C80: CT TM Outdoor 200/5 | D80: MDU-KD | E80: Bh | F80: 3826640 | G80: 7842800 | I80: =IF($I$5=$G$4,G80,(IF($I$5=$F$4,F80,0))) -> 7842800 | J80: =IF(D80="MDU-KD",1,0) -> 1 | K80: 2980000 | L80: =IF(J80=1,SUM($J$6:J80),0) -> 56 | M80: =IF(K80=1,SUM($K$6:K80),0) -> 0 | N80: =IF(L80=0,M80,L80) -> 56 | O80: =IF(E80=0,0,IF(LEFT(C80,11)="Tiang Beton",1,0)) -> 0 | P80: =IF(O80=1,SUM($O$6:O80),0) -> 0
B81: 73 | C81: CT TM Outdoor 250/5 | D81: MDU-KD | E81: Bh | F81: 3826640 | G81: 7842800 | I81: =IF($I$5=$G$4,G81,(IF($I$5=$F$4,F81,0))) -> 7842800 | J81: =IF(D81="MDU-KD",1,0) -> 1 | K81: 2980000 | L81: =IF(J81=1,SUM($J$6:J81),0) -> 57 | M81: =IF(K81=1,SUM($K$6:K81),0) -> 0 | N81: =IF(L81=0,M81,L81) -> 57 | O81: =IF(E81=0,0,IF(LEFT(C81,11)="Tiang Beton",1,0)) -> 0 | P81: =IF(O81=1,SUM($O$6:O81),0) -> 0
B82: 74 | C82: CT TM Outdoor 300/5 | D82: MDU-KD | E82: Bh | F82: 3826640 | G82: 7842800 | I82: =IF($I$5=$G$4,G82,(IF($I$5=$F$4,F82,0))) -> 7842800 | J82: =IF(D82="MDU-KD",1,0) -> 1 | K82: 2980000 | L82: =IF(J82=1,SUM($J$6:J82),0) -> 58 | M82: =IF(K82=1,SUM($K$6:K82),0) -> 0 | N82: =IF(L82=0,M82,L82) -> 58 | O82: =IF(E82=0,0,IF(LEFT(C82,11)="Tiang Beton",1,0)) -> 0 | P82: =IF(O82=1,SUM($O$6:O82),0) -> 0
B83: 75 | C83: CT TM Outdoor 400/5 | D83: MDU-KD | E83: Bh | F83: 3826640 | G83: 7842800 | I83: =IF($I$5=$G$4,G83,(IF($I$5=$F$4,F83,0))) -> 7842800 | J83: =IF(D83="MDU-KD",1,0) -> 1 | K83: 2980000 | L83: =IF(J83=1,SUM($J$6:J83),0) -> 59 | M83: =IF(K83=1,SUM($K$6:K83),0) -> 0 | N83: =IF(L83=0,M83,L83) -> 59 | O83: =IF(E83=0,0,IF(LEFT(C83,11)="Tiang Beton",1,0)) -> 0 | P83: =IF(O83=1,SUM($O$6:O83),0) -> 0
B84: 76 | C84: PT Indoor (ratio 20.000/v3 : 100/v3) Class 0.2s | D84: MDU-KD | E84: Bh | F84: 3551000 | G84: 5811500 | I84: =IF($I$5=$G$4,G84,(IF($I$5=$F$4,F84,0))) -> 5811500 | J84: =IF(D84="MDU-KD",1,0) -> 1 | K84: 2980000 | L84: =IF(J84=1,SUM($J$6:J84),0) -> 60 | M84: =IF(K84=1,SUM($K$6:K84),0) -> 0 | N84: =IF(L84=0,M84,L84) -> 60 | O84: =IF(E84=0,0,IF(LEFT(C84,11)="Tiang Beton",1,0)) -> 0 | P84: =IF(O84=1,SUM($O$6:O84),0) -> 0
B85: 77 | C85: PT Outdoor (ratio 20.000/v3 : 100/v3) Class 0.2s | D85: MDU-KD | E85: Bh | F85: 4585000 | G85: 7805600 | I85: =IF($I$5=$G$4,G85,(IF($I$5=$F$4,F85,0))) -> 7805600 | J85: =IF(D85="MDU-KD",1,0) -> 1 | K85: 2980000 | L85: =IF(J85=1,SUM($J$6:J85),0) -> 61 | M85: =IF(K85=1,SUM($K$6:K85),0) -> 0 | N85: =IF(L85=0,M85,L85) -> 61 | O85: =IF(E85=0,0,IF(LEFT(C85,11)="Tiang Beton",1,0)) -> 0 | P85: =IF(O85=1,SUM($O$6:O85),0) -> 0
I86: =IF($I$5=$G$4,G86,(IF($I$5=$F$4,F86,0))) -> 0 | J86: =IF(D86="MDU-KD",1,0) -> 0 | K86: 2980000 | L86: =IF(J86=1,SUM($J$6:J86),0) -> 0 | M86: =IF(K86=1,SUM($K$6:K86),0) -> 0 | N86: =IF(L86=0,M86,L86) -> 0 | O86: =IF(E86=0,0,IF(LEFT(C86,11)="Tiang Beton",1,0)) -> 0 | P86: =IF(O86=1,SUM($O$6:O86),0) -> 0
B87: B | C87: KOTAK APP | I87: =IF($I$5=$G$4,G87,(IF($I$5=$F$4,F87,0))) -> 0 | J87: =IF(D87="MDU-KD",1,0) -> 0 | K87: 2980000 | L87: =IF(J87=1,SUM($J$6:J87),0) -> 0 | M87: =IF(K87=1,SUM($K$6:K87),0) -> 0 | N87: =IF(L87=0,M87,L87) -> 0 | O87: =IF(E87=0,0,IF(LEFT(C87,11)="Tiang Beton",1,0)) -> 0 | P87: =IF(O87=1,SUM($O$6:O87),0) -> 0
B88: 1 | C88: Smart Box Langsung Daya 3.9 kVA MCCB 6 A | D88: MDU-KD | E88: Unit | F88: 2980000 | G88: 3564900 | I88: =IF($I$5=$G$4,G88,(IF($I$5=$F$4,F88,0))) -> 3564900 | J88: =IF(D88="MDU-KD",1,0) -> 1 | K88: 11955000 | L88: =IF(J88=1,SUM($J$6:J88),0) -> 62 | M88: =IF(K88=1,SUM($K$6:K88),0) -> 0 | N88: =IF(L88=0,M88,L88) -> 62 | O88: =IF(E88=0,0,IF(LEFT(C88,11)="Tiang Beton",1,0)) -> 0 | P88: =IF(O88=1,SUM($O$6:O88),0) -> 0
B89: 2 | C89: Smart Box Langsung Daya 6.6 kVA MCCB 10 A | D89: MDU-KD | E89: Unit | F89: 2980000 | G89: 3564900 | I89: =IF($I$5=$G$4,G89,(IF($I$5=$F$4,F89,0))) -> 3564900 | J89: =IF(D89="MDU-KD",1,0) -> 1 | K89: 11955000 | L89: =IF(J89=1,SUM($J$6:J89),0) -> 63 | M89: =IF(K89=1,SUM($K$6:K89),0) -> 0 | N89: =IF(L89=0,M89,L89) -> 63 | O89: =IF(E89=0,0,IF(LEFT(C89,11)="Tiang Beton",1,0)) -> 0 | P89: =IF(O89=1,SUM($O$6:O89),0) -> 0
B90: 3 | C90: Smart Box Langsung Daya 10.6 kVA MCCB 16 A | D90: MDU-KD | E90: Unit | F90: 2980000 | G90: 3564900 | I90: =IF($I$5=$G$4,G90,(IF($I$5=$F$4,F90,0))) -> 3564900 | J90: =IF(D90="MDU-KD",1,0) -> 1 | K90: 12470000 | L90: =IF(J90=1,SUM($J$6:J90),0) -> 64 | M90: =IF(K90=1,SUM($K$6:K90),0) -> 0 | N90: =IF(L90=0,M90,L90) -> 64 | O90: =IF(E90=0,0,IF(LEFT(C90,11)="Tiang Beton",1,0)) -> 0 | P90: =IF(O90=1,SUM($O$6:O90),0) -> 0
B91: 4 | C91: Smart Box Langsung Daya 13.2 kVA MCCB 20 A | D91: MDU-KD | E91: Unit | F91: 2980000 | G91: 3564900 | I91: =IF($I$5=$G$4,G91,(IF($I$5=$F$4,F91,0))) -> 3564900 | J91: =IF(D91="MDU-KD",1,0) -> 1 | K91: 12470000 | L91: =IF(J91=1,SUM($J$6:J91),0) -> 65 | M91: =IF(K91=1,SUM($K$6:K91),0) -> 0 | N91: =IF(L91=0,M91,L91) -> 65 | O91: =IF(E91=0,0,IF(LEFT(C91,11)="Tiang Beton",1,0)) -> 0 | P91: =IF(O91=1,SUM($O$6:O91),0) -> 0
B92: 5 | C92: Smart Box Langsung Daya 16.5 kVA MCCB 25 A | D92: MDU-KD | E92: Unit | F92: 2980000 | G92: 3564900 | I92: =IF($I$5=$G$4,G92,(IF($I$5=$F$4,F92,0))) -> 3564900 | J92: =IF(D92="MDU-KD",1,0) -> 1 | K92: 13150000 | L92: =IF(J92=1,SUM($J$6:J92),0) -> 66 | M92: =IF(K92=1,SUM($K$6:K92),0) -> 0 | N92: =IF(L92=0,M92,L92) -> 66 | O92: =IF(E92=0,0,IF(LEFT(C92,11)="Tiang Beton",1,0)) -> 0 | P92: =IF(O92=1,SUM($O$6:O92),0) -> 0
B93: 6 | C93: Smart Box Langsung Daya 23 kVA MCCB 35 A | D93: MDU-KD | E93: Unit | F93: 2980000 | G93: 3564900 | I93: =IF($I$5=$G$4,G93,(IF($I$5=$F$4,F93,0))) -> 3564900 | J93: =IF(D93="MDU-KD",1,0) -> 1 | K93: 13150000 | L93: =IF(J93=1,SUM($J$6:J93),0) -> 67 | M93: =IF(K93=1,SUM($K$6:K93),0) -> 0 | N93: =IF(L93=0,M93,L93) -> 67 | O93: =IF(E93=0,0,IF(LEFT(C93,11)="Tiang Beton",1,0)) -> 0 | P93: =IF(O93=1,SUM($O$6:O93),0) -> 0
B94: 7 | C94: Smart Box Langsung Daya 33 kVA MCCB 50 A | D94: MDU-KD | E94: Unit | F94: 2980000 | G94: 3564900 | I94: =IF($I$5=$G$4,G94,(IF($I$5=$F$4,F94,0))) -> 3564900 | J94: =IF(D94="MDU-KD",1,0) -> 1 | K94: 13150000 | L94: =IF(J94=1,SUM($J$6:J94),0) -> 68 | M94: =IF(K94=1,SUM($K$6:K94),0) -> 0 | N94: =IF(L94=0,M94,L94) -> 68 | O94: =IF(E94=0,0,IF(LEFT(C94,11)="Tiang Beton",1,0)) -> 0 | P94: =IF(O94=1,SUM($O$6:O94),0) -> 0
B95: 8 | C95: Smart Box Langsung Daya 41.5 kVA MCCB 63 A | D95: MDU-KD | E95: Unit | F95: 2980000 | G95: 3564900 | I95: =IF($I$5=$G$4,G95,(IF($I$5=$F$4,F95,0))) -> 3564900 | J95: =IF(D95="MDU-KD",1,0) -> 1 | K95: 13825000 | L95: =IF(J95=1,SUM($J$6:J95),0) -> 69 | M95: =IF(K95=1,SUM($K$6:K95),0) -> 0 | N95: =IF(L95=0,M95,L95) -> 69 | O95: =IF(E95=0,0,IF(LEFT(C95,11)="Tiang Beton",1,0)) -> 0 | P95: =IF(O95=1,SUM($O$6:O95),0) -> 0
B96: 9 | C96: Smart Box Tidak Langsung Daya 53 kVA MCCB 80 A | D96: MDU-KD | E96: Unit | F96: 12249100 | G96: 13644300 | I96: =IF($I$5=$G$4,G96,(IF($I$5=$F$4,F96,0))) -> 13644300 | J96: =IF(D96="MDU-KD",1,0) -> 1 | K96: 3050000 | L96: =IF(J96=1,SUM($J$6:J96),0) -> 70 | M96: =IF(K96=1,SUM($K$6:K96),0) -> 0 | N96: =IF(L96=0,M96,L96) -> 70 | O96: =IF(E96=0,0,IF(LEFT(C96,11)="Tiang Beton",1,0)) -> 0 | P96: =IF(O96=1,SUM($O$6:O96),0) -> 0
B97: 10 | C97: Smart Box Tidak Langsung Daya 66 kVA MCCB 100 A | D97: MDU-KD | E97: Unit | F97: 12249100 | G97: 13644300 | I97: =IF($I$5=$G$4,G97,(IF($I$5=$F$4,F97,0))) -> 13644300 | J97: =IF(D97="MDU-KD",1,0) -> 1 | K97: 61350.369 | L97: =IF(J97=1,SUM($J$6:J97),0) -> 71 | M97: =IF(K97=1,SUM($K$6:K97),0) -> 0 | N97: =IF(L97=0,M97,L97) -> 71 | O97: =IF(E97=0,0,IF(LEFT(C97,11)="Tiang Beton",1,0)) -> 0 | P97: =IF(O97=1,SUM($O$6:O97),0) -> 0
B98: 11 | C98: Smart Box Tidak Langsung Daya 82.5 kVA MCCB 125 A | D98: MDU-KD | E98: Unit | F98: 12764100 | G98: 14217900 | I98: =IF($I$5=$G$4,G98,(IF($I$5=$F$4,F98,0))) -> 14217900 | J98: =IF(D98="MDU-KD",1,0) -> 1 | K98: 297606.45 | L98: =IF(J98=1,SUM($J$6:J98),0) -> 72 | M98: =IF(K98=1,SUM($K$6:K98),0) -> 0 | N98: =IF(L98=0,M98,L98) -> 72 | O98: =IF(E98=0,0,IF(LEFT(C98,11)="Tiang Beton",1,0)) -> 0 | P98: =IF(O98=1,SUM($O$6:O98),0) -> 0
B99: 12 | C99: Smart Box Tidak Langsung Daya 105 kVA MCCB 160 A | D99: MDU-KD | E99: Unit | F99: 12764100 | G99: 14217900 | I99: =IF($I$5=$G$4,G99,(IF($I$5=$F$4,F99,0))) -> 14217900 | J99: =IF(D99="MDU-KD",1,0) -> 1 | K99: 63410.287 | L99: =IF(J99=1,SUM($J$6:J99),0) -> 73 | M99: =IF(K99=1,SUM($K$6:K99),0) -> 0 | N99: =IF(L99=0,M99,L99) -> 73 | O99: =IF(E99=0,0,IF(LEFT(C99,11)="Tiang Beton",1,0)) -> 0 | P99: =IF(O99=1,SUM($O$6:O99),0) -> 0
... B108: 21 | C108: Kotak APP Type III Lipat,lengkap | D108: HDW | E108: Bh | F108: 259574.27 | G108: 259574.27 | I108: =IF($I$5=$G$4,G108,(IF($I$5=$F$4,F108,0))) -> 259574.27 | J108: =IF(D108="MDU-KD",1,0) -> 0 | K108: 12875140 | L108: =IF(J108=1,SUM($J$6:J108),0) -> 0 | M108: =IF(K108=1,SUM($K$6:K108),0) -> 0 | N108: =IF(L108=0,M108,L108) -> 0 | O108: =IF(E108=0,0,IF(LEFT(C108,11)="Tiang Beton",1,0)) -> 0 | P108: =IF(O108=1,SUM($O$6:O108),0) -> 0
B109: 22 | C109: Kotak APP TR Type IV Tanpa Topi,lengkap | D109: HDW | E109: Bh | F109: 5918293.4 | G109: 5918293.4 | I109: =IF($I$5=$G$4,G109,(IF($I$5=$F$4,F109,0))) -> 5918293.4 | J109: =IF(D109="MDU-KD",1,0) -> 0 | K109: =IF(D109="HDW",1,0) -> 1 | L109: =IF(J109=1,SUM($J$6:J109),0) -> 0 | M109: =IF(K109=1,SUM($K$6:K109),0) -> 2.0122706e+08 | N109: =IF(L109=0,M109,L109) -> 2.0122706e+08 | O109: =IF(E109=0,0,IF(LEFT(C109,11)="Tiang Beton",1,0)) -> 0 | P109: =IF(O109=1,SUM($O$6:O109),0) -> 0
B110: 23 | C110: Kotak APP TR Type I A Single Tarif, lengkap | D110: HDW | E110: Bh | F110: 7304865 | G110: 7304865 | I110: =IF($I$5=$G$4,G110,(IF($I$5=$F$4,F110,0))) -> 7304865 | J110: =IF(D110="MDU-KD",1,0) -> 0 | K110: =IF(D110="HDW",1,0) -> 1 | L110: =IF(J110=1,SUM($J$6:J110),0) -> 0 | M110: =IF(K110=1,SUM($K$6:K110),0) -> 2.0122706e+08 | N110: =IF(L110=0,M110,L110) -> 2.0122706e+08 | O110: =IF(E110=0,0,IF(LEFT(C110,11)="Tiang Beton",1,0)) -> 0 | P110: =IF(O110=1,SUM($O$6:O110),0) -> 0
B111: 24 | C111: Kotak APP TR Double Tarif, lengkap | D111: HDW | E111: Bh | F111: 7575415.6 | G111: 7575415.6 | I111: =IF($I$5=$G$4,G111,(IF($I$5=$F$4,F111,0))) -> 7575415.6 | J111: =IF(D111="MDU-KD",1,0) -> 0 | K111: =IF(D111="HDW",1,0) -> 1 | L111: =IF(J111=1,SUM($J$6:J111),0) -> 0 | M111: =IF(K111=1,SUM($K$6:K111),0) -> 2.0122707e+08 | N111: =IF(L111=0,M111,L111) -> 2.0122707e+08 | O111: =IF(E111=0,0,IF(LEFT(C111,11)="Tiang Beton",1,0)) -> 0 | P111: =IF(O111=1,SUM($O$6:O111),0) -> 0
B112: 25 | C112: Kotak APP TM , lengkap | D112: HDW | E112: Bh | F112: 7034314.4 | G112: 7034314.4 | I112: =IF($I$5=$G$4,G112,(IF($I$5=$F$4,F112,0))) -> 7034314.4 | J112: =IF(D112="MDU-KD",1,0) -> 0 | K112: =IF(D112="HDW",1,0) -> 1 | L112: =IF(J112=1,SUM($J$6:J112),0) -> 0 | M112: =IF(K112=1,SUM($K$6:K112),0) -> 2.0122707e+08 | N112: =IF(L112=0,M112,L112) -> 2.0122707e+08 | O112: =IF(E112=0,0,IF(LEFT(C112,11)="Tiang Beton",1,0)) -> 0 | P112: =IF(O112=1,SUM($O$6:O112),0) -> 0
I113: =IF($I$5=$G$4,G113,(IF($I$5=$F$4,F113,0))) -> 0 | J113: =IF(D113="MDU-KD",1,0) -> 0 | K113: =IF(D113="HDW",1,0) -> 0 | L113: =IF(J113=1,SUM($J$6:J113),0) -> 0 | M113: =IF(K113=1,SUM($K$6:K113),0) -> 0 | N113: =IF(L113=0,M113,L113) -> 0 | O113: =IF(E113=0,0,IF(LEFT(C113,11)="Tiang Beton",1,0)) -> 0 | P113: =IF(O113=1,SUM($O$6:O113),0) -> 0
B114: C | C114: LBS & KUBIKEL PELANGGAN | I114: =IF($I$5=$G$4,G114,(IF($I$5=$F$4,F114,0))) -> 0 | J114: =IF(D114="MDU-KD",1,0) -> 0 | K114: =IF(D114="HDW",1,0) -> 0 | L114: =IF(J114=1,SUM($J$6:J114),0) -> 0 | M114: =IF(K114=1,SUM($K$6:K114),0) -> 0 | N114: =IF(L114=0,M114,L114) -> 0 | O114: =IF(E114=0,0,IF(LEFT(C114,11)="Tiang Beton",1,0)) -> 0 | P114: =IF(O114=1,SUM($O$6:O114),0) -> 0
B115: 1 | C115: LBS Pelanggan TM | D115: HDW | E115: Unit | I115: =IF($I$5=$G$4,G115,(IF($I$5=$F$4,F115,0))) -> 0 | J115: =IF(D115="MDU-KD",1,0) -> 0 | K115: =IF(D115="HDW",1,0) -> 1 | L115: =IF(J115=1,SUM($J$6:J115),0) -> 0 | M115: =IF(K115=1,SUM($K$6:K115),0) -> 2.0122707e+08 | N115: =IF(L115=0,M115,L115) -> 2.0122707e+08 | O115: =IF(E115=0,0,IF(LEFT(C115,11)="Tiang Beton",1,0)) -> 0 | P115: =IF(O115=1,SUM($O$6:O115),0) -> 0
B116: 2 | C116: Air Insulated LBS Manual;24KV;630A;Min-16KA | D116: MDU-KD | E116: Cell | F116: 16002920 | G116: 30518900 | I116: =IF($I$5=$G$4,G116,(IF($I$5=$F$4,F116,0))) -> 30518900 | J116: =IF(D116="MDU-KD",1,0) -> 1 | K116: =IF(D116="HDW",1,0) -> 0 | L116: =IF(J116=1,SUM($J$6:J116),0) -> 79 | M116: =IF(K116=1,SUM($K$6:K116),0) -> 0 | N116: =IF(L116=0,M116,L116) -> 79 | O116: =IF(E116=0,0,IF(LEFT(C116,11)="Tiang Beton",1,0)) -> 0 | P116: =IF(O116=1,SUM($O$6:O116),0) -> 0
B117: 3 | C117: Air Insulated LBS Motorized;24KV;630A;Min-16KA | D117: MDU-KD | E117: Cell | F117: 18311920 | G117: 34969900 | I117: =IF($I$5=$G$4,G117,(IF($I$5=$F$4,F117,0))) -> 34969900 | J117: =IF(D117="MDU-KD",1,0) -> 1 | K117: =IF(D117="HDW",1,0) -> 0 | L117: =IF(J117=1,SUM($J$6:J117),0) -> 80 | M117: =IF(K117=1,SUM($K$6:K117),0) -> 0 | N117: =IF(L117=0,M117,L117) -> 80 | O117: =IF(E117=0,0,IF(LEFT(C117,11)="Tiang Beton",1,0)) -> 0 | P117: =IF(O117=1,SUM($O$6:O117),0) -> 0
B118: 4 | C118: Air Insulated CBOG Motorized+Metering;20KV;630A;Min-16KA | D118: MDU-KD | E118: Cell | F118: 79514150 | G118: 145312800 | I118: =IF($I$5=$G$4,G118,(IF($I$5=$F$4,F118,0))) -> 145312800 | J118: =IF(D118="MDU-KD",1,0) -> 1 | K118: =IF(D118="HDW",1,0) -> 0 | L118: =IF(J118=1,SUM($J$6:J118),0) -> 81 | M118: =IF(K118=1,SUM($K$6:K118),0) -> 0 | N118: =IF(L118=0,M118,L118) -> 81 | O118: =IF(E118=0,0,IF(LEFT(C118,11)="Tiang Beton",1,0)) -> 0 | P118: =IF(O118=1,SUM($O$6:O118),0) -> 0
B119: 5 | C119: Fully Gas Insulated LBS Motorized;24KV;630A;Min-16KA | D119: MDU-KD | E119: Cell | F119: 46492920 | G119: 46492920 | I119: =IF($I$5=$G$4,G119,(IF($I$5=$F$4,F119,0))) -> 46492920 | J119: =IF(D119="MDU-KD",1,0) -> 1 | K119: =IF(D119="HDW",1,0) -> 0 | L119: =IF(J119=1,SUM($J$6:J119),0) -> 82 | M119: =IF(K119=1,SUM($K$6:K119),0) -> 0 | N119: =IF(L119=0,M119,L119) -> 82 | O119: =IF(E119=0,0,IF(LEFT(C119,11)="Tiang Beton",1,0)) -> 0 | P119: =IF(O119=1,SUM($O$6:O119),0) -> 0
B120: 6 | C120: Fully Gas Insulated CBOG Motorized+Metering;20KV;630A;Min-16KA | D120: MDU-KD | E120: Cell | F120: 229416150 | G120: 229416150 | I120: =IF($I$5=$G$4,G120,(IF($I$5=$F$4,F120,0))) -> 229416150 | J120: =IF(D120="MDU-KD",1,0) -> 1 | K120: =IF(D120="HDW",1,0) -> 0 | L120: =IF(J120=1,SUM($J$6:J120),0) -> 83 | M120: =IF(K120=1,SUM($K$6:K120),0) -> 0 | N120: =IF(L120=0,M120,L120) -> 83 | O120: =IF(E120=0,0,IF(LEFT(C120,11)="Tiang Beton",1,0)) -> 0 | P120: =IF(O120=1,SUM($O$6:O120),0) -> 0
B121: 7 | C121: Fully Gas Insulated LBS Manual;24KV;630A;Min-16KA | D121: MDU-KD | E121: Cell | F121: 46425420 | G121: 46425420 | I121: =IF($I$5=$G$4,G121,(IF($I$5=$F$4,F121,0))) -> 46425420 | J121: =IF(D121="MDU-KD",1,0) -> 1 | K121: =IF(D121="HDW",1,0) -> 0 | L121: =IF(J121=1,SUM($J$6:J121),0) -> 84 | M121: =IF(K121=1,SUM($K$6:K121),0) -> 0 | N121: =IF(L121=0,M121,L121) -> 84 | O121: =IF(E121=0,0,IF(LEFT(C121,11)="Tiang Beton",1,0)) -> 0 | P121: =IF(O121=1,SUM($O$6:O121),0) -> 0
C122: Kubikel Pelayanan Prioritas | I122: =IF($I$5=$G$4,G122,(IF($I$5=$F$4,F122,0))) -> 0 | J122: =IF(D122="MDU-KD",1,0) -> 0 | K122: =IF(D122="HDW",1,0) -> 0 | L122: =IF(J122=1,SUM($J$6:J122),0) -> 0 | M122: =IF(K122=1,SUM($K$6:K122),0) -> 0 | N122: =IF(L122=0,M122,L122) -> 0 | O122: =IF(E122=0,0,IF(LEFT(C122,11)="Tiang Beton",1,0)) -> 0 | P122: =IF(O122=1,SUM($O$6:O122),0) -> 0
B123: 8 | C123: Automatic Change Over (ACO) TM | D123: MDU-KD | E123: Cell | F123: 241300000 | G123: 286907300 | I123: =IF($I$5=$G$4,G123,(IF($I$5=$F$4,F123,0))) -> 286907300 | J123: =IF(D123="MDU-KD",1,0) -> 1 | K123: =IF(D123="HDW",1,0) -> 0 | L123: =IF(J123=1,SUM($J$6:J123),0) -> 85 | M123: =IF(K123=1,SUM($K$6:K123),0) -> 0 | N123: =IF(L123=0,M123,L123) -> 85 | O123: =IF(E123=0,0,IF(LEFT(C123,11)="Tiang Beton",1,0)) -> 0 | P123: =IF(O123=1,SUM($O$6:O123),0) -> 0
B124: 9 | C124: Automatic Change Over (ACO) TR | D124: MDU-KD | E124: Unit | F124: 42499000 | G124: 47390600 | I124: =IF($I$5=$G$4,G124,(IF($I$5=$F$4,F124,0))) -> 47390600 | J124: =IF(D124="MDU-KD",1,0) -> 1 | K124: =IF(D124="HDW",1,0) -> 0 | L124: =IF(J124=1,SUM($J$6:J124),0) -> 86 | M124: =IF(K124=1,SUM($K$6:K124),0) -> 0 | N124: =IF(L124=0,M124,L124) -> 86 | O124: =IF(E124=0,0,IF(LEFT(C124,11)="Tiang Beton",1,0)) -> 0 | P124: =IF(O124=1,SUM($O$6:O124),0) -> 0
I125: =IF($I$5=$G$4,G125,(IF($I$5=$F$4,F125,0))) -> 0 | J125: =IF(D125="MDU-KD",1,0) -> 0 | K125: =IF(D125="HDW",1,0) -> 0 | L125: =IF(J125=1,SUM($J$6:J125),0) -> 0 | M125: =IF(K125=1,SUM($K$6:K125),0) -> 0 | N125: =IF(L125=0,M125,L125) -> 0 | O125: =IF(E125=0,0,IF(LEFT(C125,11)="Tiang Beton",1,0)) -> 0 | P125: =IF(O125=1,SUM($O$6:O125),0) -> 0
B126: D | C126: KUBIKEL GARDU INDUK | I126: =IF($I$5=$G$4,G126,(IF($I$5=$F$4,F126,0))) -> 0 | J126: =IF(D126="MDU-KD",1,0) -> 0 | K126: =IF(D126="HDW",1,0) -> 0 | L126: =IF(J126=1,SUM($J$6:J126),0) -> 0 | M126: =IF(K126=1,SUM($K$6:K126),0) -> 0 | N126: =IF(L126=0,M126,L126) -> 0 | O126: =IF(E126=0,0,IF(LEFT(C126,11)="Tiang Beton",1,0)) -> 0 | P126: =IF(O126=1,SUM($O$6:O126),0) -> 0
B127: 1 | C127: Metaclad;Outgoing;20kV;630A;25kA - GI | D127: MDU-KD | E127: Cell | F127: 126104830 | G127: 181123500 | I127: =IF($I$5=$G$4,G127,(IF($I$5=$F$4,F127,0))) -> 181123500 | J127: =IF(D127="MDU-KD",1,0) -> 1 | K127: =IF(D127="HDW",1,0) -> 0 | L127: =IF(J127=1,SUM($J$6:J127),0) -> 87 | M127: =IF(K127=1,SUM($K$6:K127),0) -> 0 | N127: =IF(L127=0,M127,L127) -> 87 | O127: =IF(E127=0,0,IF(LEFT(C127,11)="Tiang Beton",1,0)) -> 0 | P127: =IF(O127=1,SUM($O$6:O127),0) -> 0
B128: 2 | C128: Metaclad;Couple;20kV;2000A;25kA - GI | D128: MDU-KD | E128: Cell | F128: 191704830 | G128: 265523500 | I128: =IF($I$5=$G$4,G128,(IF($I$5=$F$4,F128,0))) -> 265523500 | J128: =IF(D128="MDU-KD",1,0) -> 1 | K128: =IF(D128="HDW",1,0) -> 0 | L128: =IF(J128=1,SUM($J$6:J128),0) -> 88 | M128: =IF(K128=1,SUM($K$6:K128),0) -> 0 | N128: =IF(L128=0,M128,L128) -> 88 | O128: =IF(E128=0,0,IF(LEFT(C128,11)="Tiang Beton",1,0)) -> 0 | P128: =IF(O128=1,SUM($O$6:O128),0) -> 0
B129: 3 | C129: Kubikel Interface 20 kV | D129: HDW | E129: Cell | F129: 79200000 | G129: 79200000 | I129: =IF($I$5=$G$4,G129,(IF($I$5=$F$4,F129,0))) -> 79200000 | J129: =IF(D129="MDU-KD",1,0) -> 0 | K129: =IF(D129="HDW",1,0) -> 1 | L129: =IF(J129=1,SUM($J$6:J129),0) -> 0 | M129: =IF(K129=1,SUM($K$6:K129),0) -> 2.0122707e+08 | N129: =IF(L129=0,M129,L129) -> 2.0122707e+08 | O129: =IF(E129=0,0,IF(LEFT(C129,11)="Tiang Beton",1,0)) -> 0 | P129: =IF(O129=1,SUM($O$6:O129),0) -> 0
B130: 4 | C130: Power Meter Digital | D130: HDW | E130: Unit | F130: 5975000 | G130: 5975000 | I130: =IF($I$5=$G$4,G130,(IF($I$5=$F$4,F130,0))) -> 5975000 | J130: =IF(D130="MDU-KD",1,0) -> 0 | K130: =IF(D130="HDW",1,0) -> 1 | L130: =IF(J130=1,SUM($J$6:J130),0) -> 0 | M130: =IF(K130=1,SUM($K$6:K130),0) -> 2.0122707e+08 | N130: =IF(L130=0,M130,L130) -> 2.0122707e+08 | O130: =IF(E130=0,0,IF(LEFT(C130,11)="Tiang Beton",1,0)) -> 0 | P130: =IF(O130=1,SUM($O$6:O130),0) -> 0
B131: 5 | C131: Rele Proteksi OC/EF | D131: HDW | E131: Set | F131: 12500000 | G131: 12500000 | I131: =IF($I$5=$G$4,G131,(IF($I$5=$F$4,F131,0))) -> 12500000 | J131: =IF(D131="MDU-KD",1,0) -> 0 | K131: =IF(D131="HDW",1,0) -> 1 | L131: =IF(J131=1,SUM($J$6:J131),0) -> 0 | M131: =IF(K131=1,SUM($K$6:K131),0) -> 2.0122707e+08 | N131: =IF(L131=0,M131,L131) -> 2.0122707e+08 | O131: =IF(E131=0,0,IF(LEFT(C131,11)="Tiang Beton",1,0)) -> 0 | P131: =IF(O131=1,SUM($O$6:O131),0) -> 0
I132: =IF($I$5=$G$4,G132,(IF($I$5=$F$4,F132,0))) -> 0 | J132: =IF(D132="MDU-KD",1,0) -> 0 | K132: =IF(D132="HDW",1,0) -> 0 | L132: =IF(J132=1,SUM($J$6:J132),0) -> 0 | M132: =IF(K132=1,SUM($K$6:K132),0) -> 0 | N132: =IF(L132=0,M132,L132) -> 0 | O132: =IF(E132=0,0,IF(LEFT(C132,11)="Tiang Beton",1,0)) -> 0 | P132: =IF(O132=1,SUM($O$6:O132),0) -> 0
B133: E | C133: TRAFO DISTRIBUSI | I133: =IF($I$5=$G$4,G133,(IF($I$5=$F$4,F133,0))) -> 0 | J133: =IF(D133="MDU-KD",1,0) -> 0 | K133: =IF(D133="HDW",1,0) -> 0 | L133: =IF(J133=1,SUM($J$6:J133),0) -> 0 | M133: =IF(K133=1,SUM($K$6:K133),0) -> 0 | N133: =IF(L133=0,M133,L133) -> 0 | O133: =IF(E133=0,0,IF(LEFT(C133,11)="Tiang Beton",1,0)) -> 0 | P133: =IF(O133=1,SUM($O$6:O133),0) -> 0
B134: 1 | C134: Trafo 1 Fasa CSP 50 kVA | D134: MDU-KD | E134: Bh | F134: 24998100 | G134: 27845400 | I134: =IF($I$5=$G$4,G134,(IF($I$5=$F$4,F134,0))) -> 27845400 | J134: =IF(D134="MDU-KD",1,0) -> 1 | K134: =IF(D134="HDW",1,0) -> 0 | L134: =IF(J134=1,SUM($J$6:J134),0) -> 89 | M134: =IF(K134=1,SUM($K$6:K134),0) -> 0 | N134: =IF(L134=0,M134,L134) -> 89 | O134: =IF(E134=0,0,IF(LEFT(C134,11)="Tiang Beton",1,0)) -> 0 | P134: =IF(O134=1,SUM($O$6:O134),0) -> 0
B135: 2 | C135: Trafo 3 phasa 50 kVA YNyn0 | D135: MDU-KD | E135: Bh | F135: 26746100 | G135: 42757200 | I135: =IF($I$5=$G$4,G135,(IF($I$5=$F$4,F135,0))) -> 42757200 | J135: =IF(D135="MDU-KD",1,0) -> 1 | K135: =IF(D135="HDW",1,0) -> 0 | L135: =IF(J135=1,SUM($J$6:J135),0) -> 90 | M135: =IF(K135=1,SUM($K$6:K135),0) -> 0 | N135: =IF(L135=0,M135,L135) -> 90 | O135: =IF(E135=0,0,IF(LEFT(C135,11)="Tiang Beton",1,0)) -> 0 | P135: =IF(O135=1,SUM($O$6:O135),0) -> 0
B136: 3 | C136: Trafo 3 phasa 100 kVA YNyn0 | D136: MDU-KD | E136: Bh | F136: 38097500 | G136: 56838600 | I136: =IF($I$5=$G$4,G136,(IF($I$5=$F$4,F136,0))) -> 56838600 | J136: =IF(D136="MDU-KD",1,0) -> 1 | K136: =IF(D136="HDW",1,0) -> 0 | L136: =IF(J136=1,SUM($J$6:J136),0) -> 91 | M136: =IF(K136=1,SUM($K$6:K136),0) -> 0 | N136: =IF(L136=0,M136,L136) -> 91 | O136: =IF(E136=0,0,IF(LEFT(C136,11)="Tiang Beton",1,0)) -> 0 | P136: =IF(O136=1,SUM($O$6:O136),0) -> 0
B137: 4 | C137: Trafo 3 phasa 160 kVA YNyn0 | D137: MDU-KD | E137: Bh | F137: 46697500 | G137: 77674900 | I137: =IF($I$5=$G$4,G137,(IF($I$5=$F$4,F137,0))) -> 77674900 | J137: =IF(D137="MDU-KD",1,0) -> 1 | K137: =IF(D137="HDW",1,0) -> 0 | L137: =IF(J137=1,SUM($J$6:J137),0) -> 92 | M137: =IF(K137=1,SUM($K$6:K137),0) -> 0 | N137: =IF(L137=0,M137,L137) -> 92 | O137: =IF(E137=0,0,IF(LEFT(C137,11)="Tiang Beton",1,0)) -> 0 | P137: =IF(O137=1,SUM($O$6:O137),0) -> 0
B138: 5 | C138: Trafo 3 phasa 50 kVA Yzn5 | D138: MDU-KD | E138: Bh | F138: 21530100 | G138: 21530100 | I138: =IF($I$5=$G$4,G138,(IF($I$5=$F$4,F138,0))) -> 21530100 | J138: =IF(D138="MDU-KD",1,0) -> 1 | K138: =IF(D138="HDW",1,0) -> 0 | L138: =IF(J138=1,SUM($J$6:J138),0) -> 93 | M138: =IF(K138=1,SUM($K$6:K138),0) -> 0 | N138: =IF(L138=0,M138,L138) -> 93 | O138: =IF(E138=0,0,IF(LEFT(C138,11)="Tiang Beton",1,0)) -> 0 | P138: =IF(O138=1,SUM($O$6:O138),0) -> 0
B139: 6 | C139: Trafo 3 phasa 100 kVA Yzn5 | D139: MDU-KD | E139: Bh | F139: 31630800 | G139: 31630800 | I139: =IF($I$5=$G$4,G139,(IF($I$5=$F$4,F139,0))) -> 31630800 | J139: =IF(D139="MDU-KD",1,0) -> 1 | K139: =IF(D139="HDW",1,0) -> 0 | L139: =IF(J139=1,SUM($J$6:J139),0) -> 94 | M139: =IF(K139=1,SUM($K$6:K139),0) -> 0 | N139: =IF(L139=0,M139,L139) -> 94 | O139: =IF(E139=0,0,IF(LEFT(C139,11)="Tiang Beton",1,0)) -> 0 | P139: =IF(O139=1,SUM($O$6:O139),0) -> 0
B140: 7 | C140: Trafo 3 phasa 160 kVA Yzn5 | D140: MDU-KD | E140: Bh | F140: 32680800 | G140: 32680800 | I140: =IF($I$5=$G$4,G140,(IF($I$5=$F$4,F140,0))) -> 32680800 | J140: =IF(D140="MDU-KD",1,0) -> 1 | K140: =IF(D140="HDW",1,0) -> 0 | L140: =IF(J140=1,SUM($J$6:J140),0) -> 95 | M140: =IF(K140=1,SUM($K$6:K140),0) -> 0 | N140: =IF(L140=0,M140,L140) -> 95 | O140: =IF(E140=0,0,IF(LEFT(C140,11)="Tiang Beton",1,0)) -> 0 | P140: =IF(O140=1,SUM($O$6:O140),0) -> 0
B141: 8 | C141: Trafo 3 phasa 200 kVA Dyn5 | D141: MDU-KD | E141: Bh | F141: 37313100 | G141: 37313100 | I141: =IF($I$5=$G$4,G141,(IF($I$5=$F$4,F141,0))) -> 37313100 | J141: =IF(D141="MDU-KD",1,0) -> 1 | K141: =IF(D141="HDW",1,0) -> 0 | L141: =IF(J141=1,SUM($J$6:J141),0) -> 96 | M141: =IF(K141=1,SUM($K$6:K141),0) -> 0 | N141: =IF(L141=0,M141,L141) -> 96 | O141: =IF(E141=0,0,IF(LEFT(C141,11)="Tiang Beton",1,0)) -> 0 | P141: =IF(O141=1,SUM($O$6:O141),0) -> 0
B142: 9 | C142: Trafo 3 phasa 250 kVA DYn5 | D142: MDU-KD | E142: Bh | F142: 63057400 | G142: 63057400 | I142: =IF($I$5=$G$4,G142,(IF($I$5=$F$4,F142,0))) -> 63057400 | J142: =IF(D142="MDU-KD",1,0) -> 1 | K142: =IF(D142="HDW",1,0) -> 0 | L142: =IF(J142=1,SUM($J$6:J142),0) -> 97 | M142: =IF(K142=1,SUM($K$6:K142),0) -> 0 | N142: =IF(L142=0,M142,L142) -> 97 | O142: =IF(E142=0,0,IF(LEFT(C142,11)="Tiang Beton",1,0)) -> 0 | P142: =IF(O142=1,SUM($O$6:O142),0) -> 0
B143: 10 | C143: Trafo 3 phasa 400 kVA DYn5 OD | D143: MDU-KD | E143: Bh | F143: 87094400 | G143: 97014452 | I143: =IF($I$5=$G$4,G143,(IF($I$5=$F$4,F143,0))) -> 97014452 | J143: =IF(D143="MDU-KD",1,0) -> 1 | K143: =IF(D143="HDW",1,0) -> 0 | L143: =IF(J143=1,SUM($J$6:J143),0) -> 98 | M143: =IF(K143=1,SUM($K$6:K143),0) -> 0 | N143: =IF(L143=0,M143,L143) -> 98 | O143: =IF(E143=0,0,IF(LEFT(C143,11)="Tiang Beton",1,0)) -> 0 | P143: =IF(O143=1,SUM($O$6:O143),0) -> 0
B144: 11 | C144: LVCB 2 Jurusan 250 A MCCB | D144: MDU-KD | E144: Bh | F144: 10270090 | G144: 11439900 | I144: =IF($I$5=$G$4,G144,(IF($I$5=$F$4,F144,0))) -> 11439900 | J144: =IF(D144="MDU-KD",1,0) -> 1 | K144: =IF(D144="HDW",1,0) -> 0 | L144: =IF(J144=1,SUM($J$6:J144),0) -> 99 | M144: =IF(K144=1,SUM($K$6:K144),0) -> 0 | N144: =IF(L144=0,M144,L144) -> 99 | O144: =IF(E144=0,0,IF(LEFT(C144,11)="Tiang Beton",1,0)) -> 0 | P144: =IF(O144=1,SUM($O$6:O144),0) -> 0
B145: 12 | C145: LVCB 2 Jurusan 250 A LBS | D145: MDU-KD | E145: Bh | F145: 8972560 | G145: 9994500 | I145: =IF($I$5=$G$4,G145,(IF($I$5=$F$4,F145,0))) -> 9994500 | J145: =IF(D145="MDU-KD",1,0) -> 1 | K145: =IF(D145="HDW",1,0) -> 0 | L145: =IF(J145=1,SUM($J$6:J145),0) -> 100 | M145: =IF(K145=1,SUM($K$6:K145),0) -> 0 | N145: =IF(L145=0,M145,L145) -> 100 | O145: =IF(E145=0,0,IF(LEFT(C145,11)="Tiang Beton",1,0)) -> 0 | P145: =IF(O145=1,SUM($O$6:O145),0) -> 0
... B148: 15 | C148: LVCB 4 Jurusan 630 A LBS | D148: MDU-KD | E148: Unit | F148: 15724250 | G148: 16589084 | I148: =IF($I$5=$G$4,G148,(IF($I$5=$F$4,F148,0))) -> 16589084 | J148: =IF(D148="MDU-KD",1,0) -> 1 | K148: =IF(D148="HDW",1,0) -> 0 | L148: =IF(J148=1,SUM($J$6:J148),0) -> 103 | M148: =IF(K148=1,SUM($K$6:K148),0) -> 0 | N148: =IF(L148=0,M148,L148) -> 103 | O148: =IF(E148=0,0,IF(LEFT(C148,11)="Tiang Beton",1,0)) -> 0 | P148: =IF(O148=1,SUM($O$6:O148),0) -> 0
I149: =IF($I$5=$G$4,G149,(IF($I$5=$F$4,F149,0))) -> 0 | J149: =IF(D149="MDU-KD",1,0) -> 0 | K149: =IF(D149="HDW",1,0) -> 0 | L149: =IF(J149=1,SUM($J$6:J149),0) -> 0 | M149: =IF(K149=1,SUM($K$6:K149),0) -> 0 | N149: =IF(L149=0,M149,L149) -> 0 | O149: =IF(E149=0,0,IF(LEFT(C149,11)="Tiang Beton",1,0)) -> 0 | P149: =IF(O149=1,SUM($O$6:O149),0) -> 0
B150: F | C150: PEMBATAS | I150: =IF($I$5=$G$4,G150,(IF($I$5=$F$4,F150,0))) -> 0 | J150: =IF(D150="MDU-KD",1,0) -> 0 | K150: =IF(D150="HDW",1,0) -> 0 | L150: =IF(J150=1,SUM($J$6:J150),0) -> 0 | M150: =IF(K150=1,SUM($K$6:K150),0) -> 0 | N150: =IF(L150=0,M150,L150) -> 0 | O150: =IF(E150=0,0,IF(LEFT(C150,11)="Tiang Beton",1,0)) -> 0 | P150: =IF(O150=1,SUM($O$6:O150),0) -> 0
B151: 1 | C151: FCO Polymer | D151: MDU-KD | E151: Bh | F151: 848250 | G151: 848250 | I151: =IF($I$5=$G$4,G151,(IF($I$5=$F$4,F151,0))) -> 848250 | J151: =IF(D151="MDU-KD",1,0) -> 1 | K151: =IF(D151="HDW",1,0) -> 0 | L151: =IF(J151=1,SUM($J$6:J151),0) -> 104 | M151: =IF(K151=1,SUM($K$6:K151),0) -> 0 | N151: =IF(L151=0,M151,L151) -> 104 | O151: =IF(E151=0,0,IF(LEFT(C151,11)="Tiang Beton",1,0)) -> 0 | P151: =IF(O151=1,SUM($O$6:O151),0) -> 0
B152: 2 | C152: Fuse Link 2 A | D152: HDW | E152: Bh | F152: 17500 | G152: 17500 | I152: =IF($I$5=$G$4,G152,(IF($I$5=$F$4,F152,0))) -> 17500 | J152: =IF(D152="MDU-KD",1,0) -> 0 | K152: =IF(D152="HDW",1,0) -> 1 | L152: =IF(J152=1,SUM($J$6:J152),0) -> 0 | M152: =IF(K152=1,SUM($K$6:K152),0) -> 2.0122707e+08 | N152: =IF(L152=0,M152,L152) -> 2.0122707e+08 | O152: =IF(E152=0,0,IF(LEFT(C152,11)="Tiang Beton",1,0)) -> 0 | P152: =IF(O152=1,SUM($O$6:O152),0) -> 0
B153: 3 | C153: Fuse Link 3 A | D153: HDW | E153: Bh | F153: 17500 | G153: 17500 | I153: =IF($I$5=$G$4,G153,(IF($I$5=$F$4,F153,0))) -> 17500 | J153: =IF(D153="MDU-KD",1,0) -> 0 | K153: =IF(D153="HDW",1,0) -> 1 | L153: =IF(J153=1,SUM($J$6:J153),0) -> 0 | M153: =IF(K153=1,SUM($K$6:K153),0) -> 2.0122707e+08 | N153: =IF(L153=0,M153,L153) -> 2.0122707e+08 | O153: =IF(E153=0,0,IF(LEFT(C153,11)="Tiang Beton",1,0)) -> 0 | P153: =IF(O153=1,SUM($O$6:O153),0) -> 0
B154: 4 | C154: Fuse Link 4 A | D154: HDW | E154: Bh | F154: 17500 | G154: 17500 | I154: =IF($I$5=$G$4,G154,(IF($I$5=$F$4,F154,0))) -> 17500 | J154: =IF(D154="MDU-KD",1,0) -> 0 | K154: =IF(D154="HDW",1,0) -> 1 | L154: =IF(J154=1,SUM($J$6:J154),0) -> 0 | M154: =IF(K154=1,SUM($K$6:K154),0) -> 2.0122707e+08 | N154: =IF(L154=0,M154,L154) -> 2.0122707e+08 | O154: =IF(E154=0,0,IF(LEFT(C154,11)="Tiang Beton",1,0)) -> 0 | P154: =IF(O154=1,SUM($O$6:O154),0) -> 0
B155: 5 | C155: Fuse Link 6 A | D155: HDW | E155: Bh | F155: 18000 | G155: 18000 | I155: =IF($I$5=$G$4,G155,(IF($I$5=$F$4,F155,0))) -> 18000 | J155: =IF(D155="MDU-KD",1,0) -> 0 | K155: =IF(D155="HDW",1,0) -> 1 | L155: =IF(J155=1,SUM($J$6:J155),0) -> 0 | M155: =IF(K155=1,SUM($K$6:K155),0) -> 2.0122707e+08 | N155: =IF(L155=0,M155,L155) -> 2.0122707e+08 | O155: =IF(E155=0,0,IF(LEFT(C155,11)="Tiang Beton",1,0)) -> 0 | P155: =IF(O155=1,SUM($O$6:O155),0) -> 0
B156: 6 | C156: Fuse Link 8 A | D156: HDW | E156: Bh | F156: 18000 | G156: 18000 | I156: =IF($I$5=$G$4,G156,(IF($I$5=$F$4,F156,0))) -> 18000 | J156: =IF(D156="MDU-KD",1,0) -> 0 | K156: =IF(D156="HDW",1,0) -> 1 | L156: =IF(J156=1,SUM($J$6:J156),0) -> 0 | M156: =IF(K156=1,SUM($K$6:K156),0) -> 2.0122708e+08 | N156: =IF(L156=0,M156,L156) -> 2.0122708e+08 | O156: =IF(E156=0,0,IF(LEFT(C156,11)="Tiang Beton",1,0)) -> 0 | P156: =IF(O156=1,SUM($O$6:O156),0) -> 0
B157: 7 | C157: Fuse Link 10 A | D157: HDW | E157: Bh | F157: 18000 | G157: 18000 | I157: =IF($I$5=$G$4,G157,(IF($I$5=$F$4,F157,0))) -> 18000 | J157: =IF(D157="MDU-KD",1,0) -> 0 | K157: =IF(D157="HDW",1,0) -> 1 | L157: =IF(J157=1,SUM($J$6:J157),0) -> 0 | M157: =IF(K157=1,SUM($K$6:K157),0) -> 2.0122708e+08 | N157: =IF(L157=0,M157,L157) -> 2.0122708e+08 | O157: =IF(E157=0,0,IF(LEFT(C157,11)="Tiang Beton",1,0)) -> 0 | P157: =IF(O157=1,SUM($O$6:O157),0) -> 0
B158: 8 | C158: Fuse Link 12 A | D158: HDW | E158: Bh | F158: 18000 | G158: 18000 | I158: =IF($I$5=$G$4,G158,(IF($I$5=$F$4,F158,0))) -> 18000 | J158: =IF(D158="MDU-KD",1,0) -> 0 | K158: =IF(D158="HDW",1,0) -> 1 | L158: =IF(J158=1,SUM($J$6:J158),0) -> 0 | M158: =IF(K158=1,SUM($K$6:K158),0) -> 2.0122708e+08 | N158: =IF(L158=0,M158,L158) -> 2.0122708e+08 | O158: =IF(E158=0,0,IF(LEFT(C158,11)="Tiang Beton",1,0)) -> 0 | P158: =IF(O158=1,SUM($O$6:O158),0) -> 0
B159: 9 | C159: Fuse Link 15 A | D159: HDW | E159: Bh | F159: 18000 | G159: 18000 | I159: =IF($I$5=$G$4,G159,(IF($I$5=$F$4,F159,0))) -> 18000 | J159: =IF(D159="MDU-KD",1,0) -> 0 | K159: =IF(D159="HDW",1,0) -> 1 | L159: =IF(J159=1,SUM($J$6:J159),0) -> 0 | M159: =IF(K159=1,SUM($K$6:K159),0) -> 2.0122708e+08 | N159: =IF(L159=0,M159,L159) -> 2.0122708e+08 | O159: =IF(E159=0,0,IF(LEFT(C159,11)="Tiang Beton",1,0)) -> 0 | P159: =IF(O159=1,SUM($O$6:O159),0) -> 0
B160: 10 | C160: Fuse Link 20 A | D160: HDW | E160: Bh | F160: 20000 | G160: 20000 | I160: =IF($I$5=$G$4,G160,(IF($I$5=$F$4,F160,0))) -> 20000 | J160: =IF(D160="MDU-KD",1,0) -> 0 | K160: =IF(D160="HDW",1,0) -> 1 | L160: =IF(J160=1,SUM($J$6:J160),0) -> 0 | M160: =IF(K160=1,SUM($K$6:K160),0) -> 2.0122708e+08 | N160: =IF(L160=0,M160,L160) -> 2.0122708e+08 | O160: =IF(E160=0,0,IF(LEFT(C160,11)="Tiang Beton",1,0)) -> 0 | P160: =IF(O160=1,SUM($O$6:O160),0) -> 0
B161: 11 | C161: Fuse Link 25 A | D161: HDW | E161: Bh | F161: 23000 | G161: 23000 | I161: =IF($I$5=$G$4,G161,(IF($I$5=$F$4,F161,0))) -> 23000 | J161: =IF(D161="MDU-KD",1,0) -> 0 | K161: =IF(D161="HDW",1,0) -> 1 | L161: =IF(J161=1,SUM($J$6:J161),0) -> 0 | M161: =IF(K161=1,SUM($K$6:K161),0) -> 2.0122708e+08 | N161: =IF(L161=0,M161,L161) -> 2.0122708e+08 | O161: =IF(E161=0,0,IF(LEFT(C161,11)="Tiang Beton",1,0)) -> 0 | P161: =IF(O161=1,SUM($O$6:O161),0) -> 0
B162: 12 | C162: Fuse Link 30 A | D162: HDW | E162: Bh | F162: 23700 | G162: 23700 | I162: =IF($I$5=$G$4,G162,(IF($I$5=$F$4,F162,0))) -> 23700 | J162: =IF(D162="MDU-KD",1,0) -> 0 | K162: =IF(D162="HDW",1,0) -> 1 | L162: =IF(J162=1,SUM($J$6:J162),0) -> 0 | M162: =IF(K162=1,SUM($K$6:K162),0) -> 2.0122708e+08 | N162: =IF(L162=0,M162,L162) -> 2.0122708e+08 | O162: =IF(E162=0,0,IF(LEFT(C162,11)="Tiang Beton",1,0)) -> 0 | P162: =IF(O162=1,SUM($O$6:O162),0) -> 0
... B182: 32 | C182: NH Fuse Puller Size 00-4 | D182: HDW | E182: Bh | F182: 37900 | G182: 37900 | I182: =IF($I$5=$G$4,G182,(IF($I$5=$F$4,F182,0))) -> 37900 | J182: =IF(D182="MDU-KD",1,0) -> 0 | K182: =IF(D182="HDW",1,0) -> 1 | L182: =IF(J182=1,SUM($J$6:J182),0) -> 0 | M182: =IF(K182=1,SUM($K$6:K182),0) -> 2.012271e+08 | N182: =IF(L182=0,M182,L182) -> 2.012271e+08 | O182: =IF(E182=0,0,IF(LEFT(C182,11)="Tiang Beton",1,0)) -> 0 | P182: =IF(O182=1,SUM($O$6:O182),0) -> 0
I183: =IF($I$5=$G$4,G183,(IF($I$5=$F$4,F183,0))) -> 0 | J183: =IF(D183="MDU-KD",1,0) -> 0 | K183: =IF(D183="HDW",1,0) -> 0 | L183: =IF(J183=1,SUM($J$6:J183),0) -> 0 | M183: =IF(K183=1,SUM($K$6:K183),0) -> 0 | N183: =IF(L183=0,M183,L183) -> 0 | O183: =IF(E183=0,0,IF(LEFT(C183,11)="Tiang Beton",1,0)) -> 0 | P183: =IF(O183=1,SUM($O$6:O183),0) -> 0
B184: G | C184: SWITCH | I184: =IF($I$5=$G$4,G184,(IF($I$5=$F$4,F184,0))) -> 0 | J184: =IF(D184="MDU-KD",1,0) -> 0 | K184: =IF(D184="HDW",1,0) -> 0 | L184: =IF(J184=1,SUM($J$6:J184),0) -> 0 | M184: =IF(K184=1,SUM($K$6:K184),0) -> 0 | N184: =IF(L184=0,M184,L184) -> 0 | O184: =IF(E184=0,0,IF(LEFT(C184,11)="Tiang Beton",1,0)) -> 0 | P184: =IF(O184=1,SUM($O$6:O184),0) -> 0
B185: 1 | C185: ABSW 20 KV | D185: HDW | E185: Set | F185: 22250000 | G185: 24784300 | I185: =IF($I$5=$G$4,G185,(IF($I$5=$F$4,F185,0))) -> 24784300 | J185: =IF(D185="MDU-KD",1,0) -> 0 | K185: =IF(D185="HDW",1,0) -> 1 | L185: =IF(J185=1,SUM($J$6:J185),0) -> 0 | M185: =IF(K185=1,SUM($K$6:K185),0) -> 2.012271e+08 | N185: =IF(L185=0,M185,L185) -> 2.012271e+08 | O185: =IF(E185=0,0,IF(LEFT(C185,11)="Tiang Beton",1,0)) -> 0 | P185: =IF(O185=1,SUM($O$6:O185),0) -> 0
B186: 2 | C186: Load Break Switch | D186: MDU-KD | E186: Set | F186: 80895000 | G186: 90108900 | I186: =IF($I$5=$G$4,G186,(IF($I$5=$F$4,F186,0))) -> 90108900 | J186: =IF(D186="MDU-KD",1,0) -> 1 | K186: =IF(D186="HDW",1,0) -> 0 | L186: =IF(J186=1,SUM($J$6:J186),0) -> 105 | M186: =IF(K186=1,SUM($K$6:K186),0) -> 0 | N186: =IF(L186=0,M186,L186) -> 105 | O186: =IF(E186=0,0,IF(LEFT(C186,11)="Tiang Beton",1,0)) -> 0 | P186: =IF(O186=1,SUM($O$6:O186),0) -> 0
B187: 3 | C187: Recloser | D187: MDU-KD | E187: Set | F187: 157800000 | G187: 175773400 | I187: =IF($I$5=$G$4,G187,(IF($I$5=$F$4,F187,0))) -> 175773400 | J187: =IF(D187="MDU-KD",1,0) -> 1 | K187: =IF(D187="HDW",1,0) -> 0 | L187: =IF(J187=1,SUM($J$6:J187),0) -> 106 | M187: =IF(K187=1,SUM($K$6:K187),0) -> 0 | N187: =IF(L187=0,M187,L187) -> 106 | O187: =IF(E187=0,0,IF(LEFT(C187,11)="Tiang Beton",1,0)) -> 0 | P187: =IF(O187=1,SUM($O$6:O187),0) -> 0
B188: 4 | C188: Disconnecting Switch 20 KV - 630 A Porcelein | D188: MDU-KD | E188: Set | F188: 8595700 | G188: 8703800 | I188: =IF($I$5=$G$4,G188,(IF($I$5=$F$4,F188,0))) -> 8703800 | J188: =IF(D188="MDU-KD",1,0) -> 1 | K188: =IF(D188="HDW",1,0) -> 0 | L188: =IF(J188=1,SUM($J$6:J188),0) -> 107 | M188: =IF(K188=1,SUM($K$6:K188),0) -> 0 | N188: =IF(L188=0,M188,L188) -> 107 | O188: =IF(E188=0,0,IF(LEFT(C188,11)="Tiang Beton",1,0)) -> 0 | P188: =IF(O188=1,SUM($O$6:O188),0) -> 0
B189: 5 | C189: Disconnecting Switch 20 KV - 630 A Polymer | D189: MDU-KD | E189: Set | F189: 8595700 | G189: 10441400 | I189: =IF($I$5=$G$4,G189,(IF($I$5=$F$4,F189,0))) -> 10441400 | J189: =IF(D189="MDU-KD",1,0) -> 1 | K189: =IF(D189="HDW",1,0) -> 0 | L189: =IF(J189=1,SUM($J$6:J189),0) -> 108 | M189: =IF(K189=1,SUM($K$6:K189),0) -> 0 | N189: =IF(L189=0,M189,L189) -> 108 | O189: =IF(E189=0,0,IF(LEFT(C189,11)="Tiang Beton",1,0)) -> 0 | P189: =IF(O189=1,SUM($O$6:O189),0) -> 0
...

Sheet KKO
B2: KAJIAN KELAYAKAN OPERASI
B4: DAYA LAMA | I4: DAYA BARU
B5: Nama Pelanggan | C5: : | D5: =DATA!D14 -> AGR UD NURA JAYA | I5: Nama Pelanggan | J5: : | K5: =D5 -> AGR UD NURA JAYA
B6: Daya Lama (VA) | C6: : | D6: =DATA!D17*1000 -> 0 | I6: Daya Baru (VA) | J6: : | K6: =DATA!D20*1000 -> 105000
B7: Jumlah Fasa | C7: : | D7: =DATA!D18 -> 1 | F7: * | I7: Jumlah Fasa | J7: : | K7: =DATA!D21 -> 3
B8: Tegangan Sekunder Pengukuran rata-rata (Fasa-Netral) (V) | C8: : | D8: =DATA!D19 -> 220 | F8: * | G8: 220 | I8: Tegangan Sekunder Pengukuran rata-rata (Fasa-Netral) (V) | J8: : | K8: =DATA!D22 -> 380
B9: Beban Pelanggan (A) | C9: : | D9: =IF(D7=1,D6/(380/3^0.5),(D6/(380*3^0.5))) -> 0 | G9: 380 | I9: Beban Pelanggan (A) | J9: : | K9: =IF(K7=1,K6/(380/3^0.5),(K6/(380*3^0.5))) -> 159.531
B11: SUPLAI TRAFO EKSISTING | I11: SUPLAI TRAFO RENCANA
B12: Nomor Tiang | C12: : | D12: K3-99/26 /3/1 | I12: Nomor Tiang | J12: : | K12: K3-99/26 /3/1
B13: Penyulang | C13: : | D13: SYG 10 | I13: Penyulang | J13: : | K13: SYG 10
B14: Daya | C14: : | F14: * | G14: 50 | I14: Daya | J14: :
B15: Jumlah Fasa | C15: : | F15: * | G15: 100 | I15: Jumlah Fasa | J15: :
B16: Beban TRAFO (Pengukuran Lapangan) | G16: 160 | I16: Beban TRAFO | J16: :
B17: Beban Primer | C17: : | D17: =IF(D15=1,D14/(20/3^0.5),(D14/(20*3^0.5))) -> 0 | F17: * | G17: 200 | I17: Beban Primer | J17: : | K17: =IF(K15=1,K14/(20/3^0.5),(K14/(20*3^0.5))) -> 0
B18: Beban Sekunder | C18: : | D18: =IF(D15=1,D14/(380/3^0.5),(D14/(380*3^0.5)))*1000 -> 0 | F18: * | G18: 250 | I18: Beban Sekunder | J18: : | K18: =IF(K15=1,K14/(380/3^0.5),(K14/(380*3^0.5)))*1000 -> 0
B19: Beban (A) | C19: : | D19: =IF(D15=1,D14/(380/3^0.5),(D14/(380*3^0.5))) -> 0 | I19: Beban (A) | J19: : | K19: =IF(K15=1,K14/(380/3^0.5),(K14/(380*3^0.5))) -> 0
B20: Prosentase Pembebanan | C20: : | D20: =D16/D18 -> #DIV/0! | I20: Beban (A) | J20: : | K20: =K16/K18 -> #DIV/0!
B21: Prosentase Pembebanan | C21: : | D21: 1 | I21: Beban (A) | J21: : | K21: 1

Sheet DATA
B2: DATA
B3: Tahun | C3: : | D3: 2022
B4: Discount Rate | C4: : | D4: 0.12
B5: Transfer price TM | C5: : | D5: 1084.125 | F5: Marginal COST maret 2022
B6: Umur ekonomis (tahun) | C6: : | D6: 25
B7: Selisih Susut Teknis | C7: : | D7: 0.0225
B8: ∑ Daya | C8: : | D8: =D20-D17 -> 105
B9: BP (Rp) | C9: : | D9: =(D8*D25)*1000 -> 81375000
B10: RAB (Rp) | C10: : | D10: =RAB!K166 -> 1.2617702e+08
B11: Biaya O&M (2% invest) | C11: : | D11: =2%*D10 -> 2523540.3
B14: Nama Pelanggan | C14: : | D14: AGR UD NURA JAYA | E14: *
B15: Golongan Pelanggan | C15: : | D15: I2 | E15: *
B16: Jenis Layanan | C16: : | D16: REGULER | E16: *
B17: Daya Lama (kVA) | C17: : | D17: 0 | E17: *
B18: Jml Phasa | D18: =IF((D17<=11),1,3) -> 1
B19: Tegangan | D19: =IF((D17<=11),220,380) -> 220
B20: Daya Baru (kVA) | C20: : | D20: 105 | E20: *
B21: Jml Phasa | D21: =IF((D20<=11),1,3) -> 3
B22: Tegangan | D22: =IF((D20<=11),220,380) -> 380
B23: Tarif WBP (Rp/kWh) | C23: : | D23: 1444.7 | E23: *
B24: Tarif LWBP (Rp/kWh) | C24: : | D24: 1444.7 | E24: *
B25: BP (Rp/VA) TR | C25: : | D25: 775 | E25: *
B26: Jam Nyala | C26: : | D26: 40 | E26: *

Sheet KKF
B3: II. KAJIAN KELAYAKAN FINANSIAL (KKF) | F3: =DATA!D14 -> AGR UD NURA JAYA
B5: Tahun | C5: Energi (kWh) | D5: E WBP (kWh) | E5: E LWBP (kWh) | F5: Cost (Juta IDR) | K5: Benefit (Juta IDR) | N5: Nett Benefit | O5: Factor PV | P5: PV Net Benefit | Q5: ΣPV Net Benefit | T5: Pay Back Periode
F6: Invest | G6: O&M | H6: Transfer Price | I6: Losses | J6: Total | K6: BP | L6: E Sales | M6: Total
A7: 0 | B7: 2023 | C7: =DATA!D8*DATA!D26*6 -> 25200 | D7: =C7*4/24 -> 4200 | E7: =C7-D7 -> 21000 | F7: =DATA!D10/1000000 -> 126.17702 | G7: =DATA!$D$11/1000000 -> 2.5235403 | H7: =C7*DATA!$D$5/1000000 -> 27.319951 | I7: =(C7*DATA!$D$5*DATA!$D$7)/1000000 -> 0.6146989 | J7: =SUM(F7:I7) -> 156.63521 | K7: =DATA!D9/1000000 -> 81.375 | L7: =((D7*DATA!$D$23)/1000000)+((E7*DATA!$D$24)/1000000) -> 36.40644 | M7: =K7+L7 -> 117.78144 | N7: =M7-J7 -> -38.853767 | O7: 1 | P7: =O7*N7 -> -38.853767 | Q7: =P7 -> -38.853767 | S7: =IF(Q7<0,"a","") -> a | T7: =IF(Q5>=0,"",IF(Q7<0,"",IF(Q7=0,A7,(A7-(Q7/N7)))))
A8: =A7+1 -> 1 | B8: =B7+1 -> 2024 | C8: =DATA!D8*DATA!D26*12 -> 50400 | D8: =C8*4/24 -> 8400 | E8: =C8-D8 -> 42000 | G8: =DATA!$D$11/1000000 -> 2.5235403 | H8: =C8*DATA!$D$5/1000000 -> 54.639902 | I8: =(C8*DATA!$D$5*DATA!$D$7)/1000000 -> 1.2293978 | J8: =SUM(F8:I8) -> 58.39284 | L8: =((D8*DATA!$D$23)/1000000)+((E8*DATA!$D$24)/1000000) -> 72.81288 | M8: =K8+L8 -> 72.81288 | N8: =M8-J8 -> 14.42004 | O8: =1/(1+'[93]Asumsi I'!$C$3)^(KKF!A8) -> 0.89285714 | P8: =O8*N8 -> 12.875035 | Q8: =Q7+P8 -> -25.978732 | S8: =IF(Q8<0,"a","") -> a | T8: =IF(Q6>=0,"",IF(Q8<0,"",IF(Q8=0,A8,(A8-(Q8/N8)))))
A9: =A8+1 -> 2 | B9: =B8+1 -> 2025 | C9: =+C8 -> 50400 | D9: =C9*4/24 -> 8400 | E9: =C9-D9 -> 42000 | G9: =DATA!$D$11/1000000 -> 2.5235403 | H9: =C9*DATA!$D$5/1000000 -> 54.639902 | I9: =(C9*DATA!$D$5*DATA!$D$7)/1000000 -> 1.2293978 | J9: =SUM(F9:I9) -> 58.39284 | L9: =((D9*DATA!$D$23)/1000000)+((E9*DATA!$D$24)/1000000) -> 72.81288 | M9: =K9+L9 -> 72.81288 | N9: =M9-J9 -> 14.42004 | O9: =1/(1+'[93]Asumsi I'!$C$3)^(KKF!A9) -> 0.79719388 | P9: =O9*N9 -> 11.495567 | Q9: =Q8+P9 -> -14.483164 | S9: =IF(Q9<0,"a","") -> a | T9: =IF(Q7>=0,"",IF(Q9<0,"",IF(Q9=0,A9,(A9-(Q9/N9)))))
A10: =A9+1 -> 3 | B10: =B9+1 -> 2026 | C10: =+C9 -> 50400 | D10: =C10*4/24 -> 8400 | E10: =C10-D10 -> 42000 | G10: =DATA!$D$11/1000000 -> 2.5235403 | H10: =C10*DATA!$D$5/1000000 -> 54.639902 | I10: =(C10*DATA!$D$5*DATA!$D$7)/1000000 -> 1.2293978 | J10: =SUM(F10:I10) -> 58.39284 | L10: =((D10*DATA!$D$23)/1000000)+((E10*DATA!$D$24)/1000000) -> 72.81288 | M10: =K10+L10 -> 72.81288 | N10: =M10-J10 -> 14.42004 | O10: =1/(1+'[93]Asumsi I'!$C$3)^(KKF!A10) -> 0.71178025 | P10: =O10*N10 -> 10.263899 | Q10: =Q9+P10 -> -4.2192651 | S10: =IF(Q10<0,"a","") -> a | T10: =IF(Q8>=0,"",IF(Q10<0,"",IF(Q10=0,A10,(A10-(Q10/N10)))))
A11: =A10+1 -> 4 | B11: =B10+1 -> 2027 | C11: =+C10 -> 50400 | D11: =C11*4/24 -> 8400 | E11: =C11-D11 -> 42000 | G11: =DATA!$D$11/1000000 -> 2.5235403 | H11: =C11*DATA!$D$5/1000000 -> 54.639902 | I11: =(C11*DATA!$D$5*DATA!$D$7)/1000000 -> 1.2293978 | J11: =SUM(F11:I11) -> 58.39284 | L11: =((D11*DATA!$D$23)/1000000)+((E11*DATA!$D$24)/1000000) -> 72.81288 | M11: =K11+L11 -> 72.81288 | N11: =M11-J11 -> 14.42004 | O11: =1/(1+'[93]Asumsi I'!$C$3)^(KKF!A11) -> 0.63551808 | P11: =O11*N11 -> 9.1641958 | Q11: =Q10+P11 -> 4.9449307 | S11: =IF(Q11<0,"a","") | T11: =IF(Q9>=0,"",IF(Q11<0,"",IF(Q11=0,A11,(A11-(Q11/N11))))) -> 3.6570793
A12: =A11+1 -> 5 | B12: =B11+1 -> 2028 | C12: =+C11 -> 50400 | D12: =C12*4/24 -> 8400 | E12: =C12-D12 -> 42000 | G12: =DATA!$D$11/1000000 -> 2.5235403 | H12: =C12*DATA!$D$5/1000000 -> 54.639902 | I12: =(C12*DATA!$D$5*DATA!$D$7)/1000000 -> 1.2293978 | J12: =SUM(F12:I12) -> 58.39284 | L12: =((D12*DATA!$D$23)/1000000)+((E12*DATA!$D$24)/1000000) -> 72.81288 | M12: =K12+L12 -> 72.81288 | N12: =M12-J12 -> 14.42004 | O12: =1/(1+'[93]Asumsi I'!$C$3)^(KKF!A12) -> 0.56742686 | P12: =O12*N12 -> 8.1823177 | Q12: =Q11+P12 -> 13.127248 | S12: =IF(Q12<0,"a","") | T12: =IF(Q10>=0,"",IF(Q12<0,"",IF(Q12=0,A12,(A12-(Q12/N12))))) -> 4.0896524
A13: =A12+1 -> 6 | B13: =B12+1 -> 2029 | C13: =+C12 -> 50400 | D13: =C13*4/24 -> 8400 | E13: =C13-D13 -> 42000 | G13: =DATA!$D$11/1000000 -> 2.5235403 | H13: =C13*DATA!$D$5/1000000 -> 54.639902 | I13: =(C13*DATA!$D$5*DATA!$D$7)/1000000 -> 1.2293978 | J13: =SUM(F13:I13) -> 58.39284 | L13: =((D13*DATA!$D$23)/1000000)+((E13*DATA!$D$24)/1000000) -> 72.81288 | M13: =K13+L13 -> 72.81288 | N13: =M13-J13 -> 14.42004 | O13: =1/(1+'[93]Asumsi I'!$C$3)^(KKF!A13) -> 0.50663112 | P13: =O13*N13 -> 7.3056408 | Q13: =Q12+P13 -> 20.432889 | S13: =IF(Q13<0,"a","") | T13: =IF(Q11>=0,"",IF(Q13<0,"",IF(Q13=0,A13,(A13-(Q13/N13)))))
A14: =A13+1 -> 7 | B14: =B13+1 -> 2030 | C14: =+C13 -> 50400 | D14: =C14*4/24 -> 8400 | E14: =C14-D14 -> 42000 | G14: =DATA!$D$11/1000000 -> 2.5235403 | H14: =C14*DATA!$D$5/1000000 -> 54.639902 | I14: =(C14*DATA!$D$5*DATA!$D$7)/1000000 -> 1.2293978 | J14: =SUM(F14:I14) -> 58.39284 | L14: =((D14*DATA!$D$23)/1000000)+((E14*DATA!$D$24)/1000000) -> 72.81288 | M14: =K14+L14 -> 72.81288 | N14: =M14-J14 -> 14.42004 | O14: =1/(1+'[93]Asumsi I'!$C$3)^(KKF!A14) -> 0.45234922 | P14: =O14*N14 -> 6.5228936 | Q14: =Q13+P14 -> 26.955783 | S14: =IF(Q14<0,"a","") | T14: =IF(Q12>=0,"",IF(Q14<0,"",IF(Q14=0,A14,(A14-(Q14/N14)))))
A15: =A14+1 -> 8 | B15: =B14+1 -> 2031 | C15: =+C14 -> 50400 | D15: =C15*4/24 -> 8400 | E15: =C15-D15 -> 42000 | G15: =DATA!$D$11/1000000 -> 2.5235403 | H15: =C15*DATA!$D$5/1000000 -> 54.639902 | I15: =(C15*DATA!$D$5*DATA!$D$7)/1000000 -> 1.2293978 | J15: =SUM(F15:I15) -> 58.39284 | L15: =((D15*DATA!$D$23)/1000000)+((E15*DATA!$D$24)/1000000) -> 72.81288 | M15: =K15+L15 -> 72.81288 | N15: =M15-J15 -> 14.42004 | O15: =1/(1+'[93]Asumsi I'!$C$3)^(KKF!A15) -> 0.40388323 | P15: =O15*N15 -> 5.8240121 | Q15: =Q14+P15 -> 32.779795 | S15: =IF(Q15<0,"a","") | T15: =IF(Q13>=0,"",IF(Q15<0,"",IF(Q15=0,A15,(A15-(Q15/N15)))))
A16: =A15+1 -> 9 | B16: =B15+1 -> 2032 | C16: =+C15 -> 50400 | D16: =C16*4/24 -> 8400 | E16: =C16-D16 -> 42000 | G16: =DATA!$D$11/1000000 -> 2.5235403 | H16: =C16*DATA!$D$5/1000000 -> 54.639902 | I16: =(C16*DATA!$D$5*DATA!$D$7)/1000000 -> 1.2293978 | J16: =SUM(F16:I16) -> 58.39284 | L16: =((D16*DATA!$D$23)/1000000)+((E16*DATA!$D$24)/1000000) -> 72.81288 | M16: =K16+L16 -> 72.81288 | N16: =M16-J16 -> 14.42004 | O16: =1/(1+'[93]Asumsi I'!$C$3)^(KKF!A16) -> 0.36061002 | P16: =O16*N16 -> 5.2000108 | Q16: =Q15+P16 -> 37.979806 | S16: =IF(Q16<0,"a","") | T16: =IF(Q14>=0,"",IF(Q16<0,"",IF(Q16=0,A16,(A16-(Q16/N16)))))
A17: =A16+1 -> 10 | B17: =B16+1 -> 2033 | C17: =+C16 -> 50400 | D17: =C17*4/24 -> 8400 | E17: =C17-D17 -> 42000 | G17: =DATA!$D$11/1000000 -> 2.5235403 | H17: =C17*DATA!$D$5/1000000 -> 54.639902 | I17: =(C17*DATA!$D$5*DATA!$D$7)/1000000 -> 1.2293978 | J17: =SUM(F17:I17) -> 58.39284 | L17: =((D17*DATA!$D$23)/1000000)+((E17*DATA!$D$24)/1000000) -> 72.81288 | M17: =K17+L17 -> 72.81288 | N17: =M17-J17 -> 14.42004 | O17: =1/(1+'[93]Asumsi I'!$C$3)^(KKF!A17) -> 0.32197324 | P17: =O17*N17 -> 4.6428668 | Q17: =Q16+P17 -> 42.622673 | S17: =IF(Q17<0,"a","") | T17: =IF(Q15>=0,"",IF(Q17<0,"",IF(Q17=0,A17,(A17-(Q17/N17)))))
A18: =A17+1 -> 11 | B18: =B17+1 -> 2034 | C18: =+C17 -> 50400 | D18: =C18*4/24 -> 8400 | E18: =C18-D18 -> 42000 | G18: =DATA!$D$11/1000000 -> 2.5235403 | H18: =C18*DATA!$D$5/1000000 -> 54.639902 | I18: =(C18*DATA!$D$5*DATA!$D$7)/1000000 -> 1.2293978 | J18: =SUM(F18:I18) -> 58.39284 | L18: =((D18*DATA!$D$23)/1000000)+((E18*DATA!$D$24)/1000000) -> 72.81288 | M18: =K18+L18 -> 72.81288 | N18: =M18-J18 -> 14.42004 | O18: =1/(1+'[93]Asumsi I'!$C$3)^(KKF!A18) -> 0.2874761 | P18: =O18*N18 -> 4.1454168 | Q18: =Q17+P18 -> 46.768089 | S18: =IF(Q18<0,"a","") | T18: =IF(Q16>=0,"",IF(Q18<0,"",IF(Q18=0,A18,(A18-(Q18/N18)))))
A19: =A18+1 -> 12 | B19: =B18+1 -> 2035 | C19: =+C18 -> 50400 | D19: =C19*4/24 -> 8400 | E19: =C19-D19 -> 42000 | G19: =DATA!$D$11/1000000 -> 2.5235403 | H19: =C19*DATA!$D$5/1000000 -> 54.639902 | I19: =(C19*DATA!$D$5*DATA!$D$7)/1000000 -> 1.2293978 | J19: =SUM(F19:I19) -> 58.39284 | L19: =((D19*DATA!$D$23)/1000000)+((E19*DATA!$D$24)/1000000) -> 72.81288 | M19: =K19+L19 -> 72.81288 | N19: =M19-J19 -> 14.42004 | O19: =1/(1+'[93]Asumsi I'!$C$3)^(KKF!A19) -> 0.25667509 | P19: =O19*N19 -> 3.701265 | Q19: =Q18+P19 -> 50.469354 | S19: =IF(Q19<0,"a","") | T19: =IF(Q17>=0,"",IF(Q19<0,"",IF(Q19=0,A19,(A19-(Q19/N19)))))
A20: =A19+1 -> 13 | B20: =B19+1 -> 2036 | C20: =+C19 -> 50400 | D20: =C20*4/24 -> 8400 | E20: =C20-D20 -> 42000 | G20: =DATA!$D$11/1000000 -> 2.5235403 | H20: =C20*DATA!$D$5/1000000 -> 54.639902 | I20: =(C20*DATA!$D$5*DATA!$D$7)/1000000 -> 1.2293978 | J20: =SUM(F20:I20) -> 58.39284 | L20: =((D20*DATA!$D$23)/1000000)+((E20*DATA!$D$24)/1000000) -> 72.81288 | M20: =K20+L20 -> 72.81288 | N20: =M20-J20 -> 14.42004 | O20: =1/(1+'[93]Asumsi I'!$C$3)^(KKF!A20) -> 0.22917419 | P20: =O20*N20 -> 3.3047009 | Q20: =Q19+P20 -> 53.774055 | S20: =IF(Q20<0,"a","") | T20: =IF(Q18>=0,"",IF(Q20<0,"",IF(Q20=0,A20,(A20-(Q20/N20)))))
... A31: =A30+1 -> 24 | B31: =B30+1 -> 2047 | C31: =+C30 -> 50400 | D31: =C31*4/24 -> 8400 | E31: =C31-D31 -> 42000 | G31: =DATA!$D$11/1000000 -> 2.5235403 | H31: =C31*DATA!$D$5/1000000 -> 54.639902 | I31: =(C31*DATA!$D$5*DATA!$D$7)/1000000 -> 1.2293978 | J31: =SUM(F31:I31) -> 58.39284 | L31: =((D31*DATA!$D$23)/1000000)+((E31*DATA!$D$24)/1000000) -> 72.81288 | M31: =K31+L31 -> 72.81288 | N31: =M31-J31 -> 14.42004 | O31: =1/(1+'[93]Asumsi I'!$C$3)^(KKF!A31) -> 0.065882103 | P31: =O31*N31 -> 0.95002254 | Q31: =Q30+P31 -> 73.396375 | S31: =IF(Q31<0,"a","") | T31: =IF(Q29>=0,"",IF(Q31<0,"",IF(Q31=0,A31,(A31-(Q31/N31)))))
A32: =A31+1 -> 25 | B32: =B30+1 -> 2047 | C32: =+C31 -> 50400 | D32: =C32*4/24 -> 8400 | E32: =C32-D32 -> 42000 | G32: =DATA!$D$11/1000000 -> 2.5235403 | H32: =C32*DATA!$D$5/1000000 -> 54.639902 | I32: =(C32*DATA!$D$5*DATA!$D$7)/1000000 -> 1.2293978 | J32: =SUM(F32:I32) -> 58.39284 | L32: =((D32*DATA!$D$23)/1000000)+((E32*DATA!$D$24)/1000000) -> 72.81288 | M32: =K32+L32 -> 72.81288 | N32: =M32-J32 -> 14.42004 | O32: =1/(1+'[93]Asumsi I'!$C$3)^(KKF!A32) -> 0.058823307 | P32: =O32*N32 -> 0.84823441 | Q32: =Q31+P32 -> 74.244609 | S32: =IF(Q32<0,"a","") | T32: =IF(Q30>=0,"",IF(Q32<0,"",IF(Q32=0,A32,(A32-(Q32/N32)))))
F33: Total Cost | J33: =SUM(J7:J32) -> 1616.4562 | K33: Total Benefit | M33: =SUM(M7:M32) -> 1938.1034 | S33: =COUNTIF(S7:S32,"a") -> 4
P34: BEP | Q34: =+J7/N32 -> 10.862329
P35: PP | Q35: =AVERAGE(T7:T32) -> 3.8733658
P36: BCR | Q36: =M33/J33 -> 1.1989829
P37: NPV | Q37: =+NPV(0.12,N7:N32) -> 66.28983
P38: IRR | Q38: =IRR(N7:N32,DATA!D4) -> 0.37099701

Sheet RAB
C1: PT. PLN ( PERSERO )
C2: UNIT INDUK DISTRIBUSI JAWA TENGAH & DI YOGYAKARTA | U2: RAB TOTAL
C3: UP3 DEMAK | O3: RAB TOTAL | U3: RAB NON MDU
B4: RENCANA ANGGARAN BIAYA (RAB)
E6: Pekerjaan | F6: : | G6: =DATA!D14 -> AGR UD NURA JAYA
E7: Lokasi | F7: : | G7: DS SIDOMULYO 07/04 WONOSALAM
E8: Pelaksana | F8: :
E9: Anggaran | F9: : | G9: SAR 2023
B11: NO | C11: URAIAN | D11: GOL | E11: SAT | F11: VOL | G11: HARGA SATUAN | H11: BIAYA YANG DIPERLUKAN ( Rp )
H12: MDU | I12: HARDWARE | J12: JASA | K12: JUMLAH
D14: =IF(ISERROR(OFFSET('HARGA SATUAN'!$D$6,MATCH(RAB!C14,'HARGA SATUAN'!$C$7:$C$1492,0),0)),"",OFFSET('HARGA SATUAN'!$D$6,MATCH(RAB!C14,'HARGA SATUAN'!$C$7:$C$1492,0),0)) | E14: =IF(B14="+","Unit",IF(ISERROR(OFFSET('HARGA SATUAN'!$E$6,MATCH(RAB!C14,'HARGA SATUAN'!$C$7:$C$1492,0),0)),"",OFFSET('HARGA SATUAN'!$E$6,MATCH(RAB!C14,'HARGA SATUAN'!$C$7:$C$1492,0),0))) | G14: =IF(ISERROR(OFFSET('HARGA SATUAN'!$I$6,MATCH(RAB!C14,'HARGA SATUAN'!$C$7:$C$1492,0),0)),0,OFFSET('HARGA SATUAN'!$I$6,MATCH(RAB!C14,'HARGA SATUAN'!$C$7:$C$1492,0),0)) -> 0 | H14: =IF(OR(D14="MDU",D14="MDU-KD"),(IF($O$3="RAB NON MDU","PLN KD",G14*F14)),0) -> 0 | I14: =IF(D14="HDW",G14*F14,0) -> 0 | J14: =IF(D14="JASA",G14*F14,0) -> 0 | K14: =SUM(H14:J14) -> 0
A15: =IF(AND(C15=0,#REF!=0,#REF!=0),"BLANKS",1) -> #REF! | B15: I | C15: PEKERJAAN PEMASANGAN TIANG | D15: =IF(ISERROR(OFFSET('HARGA SATUAN'!$D$6,MATCH(RAB!C15,'HARGA SATUAN'!$C$7:$C$1492,0),0)),"",OFFSET('HARGA SATUAN'!$D$6,MATCH(RAB!C15,'HARGA SATUAN'!$C$7:$C$1492,0),0)) | E15: =IF(B15="+","Unit",IF(ISERROR(OFFSET('HARGA SATUAN'!$E$6,MATCH(RAB!C15,'HARGA SATUAN'!$C$7:$C$1492,0),0)),"",OFFSET('HARGA SATUAN'!$E$6,MATCH(RAB!C15,'HARGA SATUAN'!$C$7:$C$1492,0),0))) | G15: =IF(ISERROR(OFFSET('HARGA SATUAN'!$I$6,MATCH(RAB!C15,'HARGA SATUAN'!$C$7:$C$1492,0),0)),0,OFFSET('HARGA SATUAN'!$I$6,MATCH(RAB!C15,'HARGA SATUAN'!$C$7:$C$1492,0),0)) -> 0 | H15: =IF(OR(D15="MDU",D15="MDU-KD"),(IF($O$3="RAB NON MDU","PLN KD",G15*F15)),0) -> 0 | I15: =IF(D15="HDW",G15*F15,0) -> 0 | J15: =IF(D15="JASA",G15*F15,0) -> 0 | K15: =SUM(H15:J15) -> 0
D16: =IF(ISERROR(OFFSET('HARGA SATUAN'!$D$6,MATCH(RAB!C16,'HARGA SATUAN'!$C$7:$C$1492,0),0)),"",OFFSET('HARGA SATUAN'!$D$6,MATCH(RAB!C16,'HARGA SATUAN'!$C$7:$C$1492,0),0)) | E16: =IF(B16="+","Unit",IF(ISERROR(OFFSET('HARGA SATUAN'!$E$6,MATCH(RAB!C16,'HARGA SATUAN'!$C$7:$C$1492,0),0)),"",OFFSET('HARGA SATUAN'!$E$6,MATCH(RAB!C16,'HARGA SATUAN'!$C$7:$C$1492,0),0))) | G16: =IF(ISERROR(OFFSET('HARGA SATUAN'!$I$6,MATCH(RAB!C16,'HARGA SATUAN'!$C$7:$C$1492,0),0)),0,OFFSET('HARGA SATUAN'!$I$6,MATCH(RAB!C16,'HARGA SATUAN'!$C$7:$C$1492,0),0)) -> 0 | H16: =IF(OR(D16="MDU",D16="MDU-KD"),(IF($O$3="RAB NON MDU","PLN KD",G16*F16)),0) -> 0 | I16: =IF(D16="HDW",G16*F16,0) -> 0 | J16: =IF(D16="JASA",G16*F16,0) -> 0 | K16: =SUM(H16:J16) -> 0
B17: 1 | C17: Tiang Beton 12M-350 daN+E | D17: =IF(ISERROR(OFFSET('HARGA SATUAN'!$D$6,MATCH(RAB!C17,'HARGA SATUAN'!$C$7:$C$1492,0),0)),"",OFFSET('HARGA SATUAN'!$D$6,MATCH(RAB!C17,'HARGA SATUAN'!$C$7:$C$1492,0),0)) -> HDW | E17: =IF(B17="+","Unit",IF(ISERROR(OFFSET('HARGA SATUAN'!$E$6,MATCH(RAB!C17,'HARGA SATUAN'!$C$7:$C$1492,0),0)),"",OFFSET('HARGA SATUAN'!$E$6,MATCH(RAB!C17,'HARGA SATUAN'!$C$7:$C$1492,0),0))) -> Btg | F17: 1 | G17: =IF(ISERROR(OFFSET('HARGA SATUAN'!$I$6,MATCH(RAB!C17,'HARGA SATUAN'!$C$7:$C$1492,0),0)),0,OFFSET('HARGA SATUAN'!$I$6,MATCH(RAB!C17,'HARGA SATUAN'!$C$7:$C$1492,0),0)) -> 6074400 | H17: =IF(OR(D17="MDU",D17="MDU-KD"),(IF($O$3="RAB NON MDU","PLN KD",G17*F17)),0) -> 0 | I17: =IF(D17="HDW",G17*F17,0) -> 6074400 | J17: =IF(D17="JASA",G17*F17,0) -> 0 | K17: =SUM(H17:J17) -> 6074400
B18: 2 | C18: Penomoran Tiang | D18: =IF(ISERROR(OFFSET('HARGA SATUAN'!$D$6,MATCH(RAB!C18,'HARGA SATUAN'!$C$7:$C$1492,0),0)),"",OFFSET('HARGA SATUAN'!$D$6,MATCH(RAB!C18,'HARGA SATUAN'!$C$7:$C$1492,0),0)) -> JASA | E18: =IF(B18="+","Unit",IF(ISERROR(OFFSET('HARGA SATUAN'!$E$6,MATCH(RAB!C18,'HARGA SATUAN'!$C$7:$C$1492,0),0)),"",OFFSET('HARGA SATUAN'!$E$6,MATCH(RAB!C18,'HARGA SATUAN'!$C$7:$C$1492,0),0))) -> Btg | F18: 2 | G18: =IF(ISERROR(OFFSET('HARGA SATUAN'!$I$6,MATCH(RAB!C18,'HARGA SATUAN'!$C$7:$C$1492,0),0)),0,OFFSET('HARGA SATUAN'!$I$6,MATCH(RAB!C18,'HARGA SATUAN'!$C$7:$C$1492,0),0)) -> 10066.667 | H18: =IF(OR(D18="MDU",D18="MDU-KD"),(IF($O$3="RAB NON MDU","PLN KD",G18*F18)),0) -> 0 | I18: =IF(D18="HDW",G18*F18,0) -> 0 | J18: =IF(D18="JASA",G18*F18,0) -> 20133.333 | K18: =SUM(H18:J18) -> 20133.333
B19: 3 | C19: Penghalang Panjat dan Papan Peringatan | D19: =IF(ISERROR(OFFSET('HARGA SATUAN'!$D$6,MATCH(RAB!C19,'HARGA SATUAN'!$C$7:$C$1492,0),0)),"",OFFSET('HARGA SATUAN'!$D$6,MATCH(RAB!C19,'HARGA SATUAN'!$C$7:$C$1492,0),0)) -> HDW | E19: =IF(B19="+","Unit",IF(ISERROR(OFFSET('HARGA SATUAN'!$E$6,MATCH(RAB!C19,'HARGA SATUAN'!$C$7:$C$1492,0),0)),"",OFFSET('HARGA SATUAN'!$E$6,MATCH(RAB!C19,'HARGA SATUAN'!$C$7:$C$1492,0),0))) -> Set | F19: 1 | G19: =IF(ISERROR(OFFSET('HARGA SATUAN'!$I$6,MATCH(RAB!C19,'HARGA SATUAN'!$C$7:$C$1492,0),0)),0,OFFSET('HARGA SATUAN'!$I$6,MATCH(RAB!C19,'HARGA SATUAN'!$C$7:$C$1492,0),0)) -> 200000 | H19: =IF(OR(D19="MDU",D19="MDU-KD"),(IF($O$3="RAB NON MDU","PLN KD",G19*F19)),0) -> 0 | I19: =IF(D19="HDW",G19*F19,0) -> 200000 | J19: =IF(D19="JASA",G19*F19,0) -> 0 | K19: =SUM(H19:J19) -> 200000
D20: =IF(ISERROR(OFFSET('HARGA SATUAN'!$D$6,MATCH(RAB!C20,'HARGA SATUAN'!$C$7:$C$1492,0),0)),"",OFFSET('HARGA SATUAN'!$D$6,MATCH(RAB!C20,'HARGA SATUAN'!$C$7:$C$1492,0),0)) | E20: =IF(B20="+","Unit",IF(ISERROR(OFFSET('HARGA SATUAN'!$E$6,MATCH(RAB!C20,'HARGA SATUAN'!$C$7:$C$1492,0),0)),"",OFFSET('HARGA SATUAN'!$E$6,MATCH(RAB!C20,'HARGA SATUAN'!$C$7:$C$1492,0),0))) | G20: =IF(ISERROR(OFFSET('HARGA SATUAN'!$I$6,MATCH(RAB!C20,'HARGA SATUAN'!$C$7:$C$1492,0),0)),0,OFFSET('HARGA SATUAN'!$I$6,MATCH(RAB!C20,'HARGA SATUAN'!$C$7:$C$1492,0),0)) -> 0 | H20: =IF(OR(D20="MDU",D20="MDU-KD"),(IF($O$3="RAB NON MDU","PLN KD",G20*F20)),0) -> 0 | I20: =IF(D20="HDW",G20*F20,0) -> 0 | J20: =IF(D20="JASA",G20*F20,0) -> 0 | K20: =SUM(H20:J20) -> 0
A21: =IF(AND(C21=0,#REF!=0,#REF!=0),"BLANKS",1) -> #REF! | B21: II | C21: PEMBANGUNAN JARINGAN TM | D21: =IF(ISERROR(OFFSET('HARGA SATUAN'!$D$6,MATCH(RAB!C21,'HARGA SATUAN'!$C$7:$C$1492,0),0)),"",OFFSET('HARGA SATUAN'!$D$6,MATCH(RAB!C21,'HARGA SATUAN'!$C$7:$C$1492,0),0)) | E21: =IF(B21="+","Unit",IF(ISERROR(OFFSET('HARGA SATUAN'!$E$6,MATCH(RAB!C21,'HARGA SATUAN'!$C$7:$C$1492,0),0)),"",OFFSET('HARGA SATUAN'!$E$6,MATCH(RAB!C21,'HARGA SATUAN'!$C$7:$C$1492,0),0))) | G21: =IF(ISERROR(OFFSET('HARGA SATUAN'!$I$6,MATCH(RAB!C21,'HARGA SATUAN'!$C$7:$C$1492,0),0)),0,OFFSET('HARGA SATUAN'!$I$6,MATCH(RAB!C21,'HARGA SATUAN'!$C$7:$C$1492,0),0)) -> 0 | H21: =IF(OR(D21="MDU",D21="MDU-KD"),(IF($O$3="RAB NON MDU","PLN KD",G21*F21)),0) -> 0 | I21: =IF(D21="HDW",G21*F21,0) -> 0 | J21: =IF(D21="JASA",G21*F21,0) -> 0 | K21: =SUM(H21:J21) -> 0
D22: =IF(ISERROR(OFFSET('HARGA SATUAN'!$D$6,MATCH(RAB!C22,'HARGA SATUAN'!$C$7:$C$1492,0),0)),"",OFFSET('HARGA SATUAN'!$D$6,MATCH(RAB!C22,'HARGA SATUAN'!$C$7:$C$1492,0),0)) | E22: =IF(B22="+","Unit",IF(ISERROR(OFFSET('HARGA SATUAN'!$E$6,MATCH(RAB!C22,'HARGA SATUAN'!$C$7:$C$1492,0),0)),"",OFFSET('HARGA SATUAN'!$E$6,MATCH(RAB!C22,'HARGA SATUAN'!$C$7:$C$1492,0),0))) | G22: =IF(ISERROR(OFFSET('HARGA SATUAN'!$I$6,MATCH(RAB!C22,'HARGA SATUAN'!$C$7:$C$1492,0),0)),0,OFFSET('HARGA SATUAN'!$I$6,MATCH(RAB!C22,'HARGA SATUAN'!$C$7:$C$1492,0),0)) -> 0 | H22: =IF(OR(D22="MDU",D22="MDU-KD"),(IF($O$3="RAB NON MDU","PLN KD",G22*F22)),0) -> 0 | I22: =IF(D22="HDW",G22*F22,0) -> 0 | J22: =IF(D22="JASA",G22*F22,0) -> 0 | K22: =SUM(H22:J22) -> 0
B23: + | C23: CC7 | D23: =IF(ISERROR(OFFSET('HARGA SATUAN'!$D$6,MATCH(RAB!C23,'HARGA SATUAN'!$C$7:$C$1492,0),0)),"",OFFSET('HARGA SATUAN'!$D$6,MATCH(RAB!C23,'HARGA SATUAN'!$C$7:$C$1492,0),0)) | E23: =IF(B23="+","Unit",IF(ISERROR(OFFSET('HARGA SATUAN'!$E$6,MATCH(RAB!C23,'HARGA SATUAN'!$C$7:$C$1492,0),0)),"",OFFSET('HARGA SATUAN'!$E$6,MATCH(RAB!C23,'HARGA SATUAN'!$C$7:$C$1492,0),0))) -> Unit | F23: 2 | G23: =IF(ISERROR(OFFSET('HARGA SATUAN'!$I$6,MATCH(RAB!C23,'HARGA SATUAN'!$C$7:$C$1492,0),0)),0,OFFSET('HARGA SATUAN'!$I$6,MATCH(RAB!C23,'HARGA SATUAN'!$C$7:$C$1492,0),0)) -> 0 | H23: =IF(OR(D23="MDU",D23="MDU-KD"),(IF($O$3="RAB NON MDU","PLN KD",G23*F23)),0) -> 0 | I23: =IF(D23="HDW",G23*F23,0) -> 0 | J23: =IF(D23="JASA",G23*F23,0) -> 0 | K23: =SUM(H23:J23) -> 0
B24: 1 | C24: Isolator Tarik ( Suspension Polymer ) 20 KV | D24: =IF(ISERROR(OFFSET('HARGA SATUAN'!$D$6,MATCH(RAB!C24,'HARGA SATUAN'!$C$7:$C$1492,0),0)),"",OFFSET('HARGA SATUAN'!$D$6,MATCH(RAB!C24,'HARGA SATUAN'!$C$7:$C$1492,0),0)) -> MDU-KD | E24: =IF(B24="+","Unit",IF(ISERROR(OFFSET('HARGA SATUAN'!$E$6,MATCH(RAB!C24,'HARGA SATUAN'!$C$7:$C$1492,0),0)),"",OFFSET('HARGA SATUAN'!$E$6,MATCH(RAB!C24,'HARGA SATUAN'!$C$7:$C$1492,0),0))) -> Set | F24: =F23*3 -> 6 | G24: =IF(ISERROR(OFFSET('HARGA SATUAN'!$I$6,MATCH(RAB!C24,'HARGA SATUAN'!$C$7:$C$1492,0),0)),0,OFFSET('HARGA SATUAN'!$I$6,MATCH(RAB!C24,'HARGA SATUAN'!$C$7:$C$1492,0),0)) -> 205700 | H24: =IF(OR(D24="MDU",D24="MDU-KD"),(IF($O$3="RAB NON MDU","PLN KD",G24*F24)),0) -> 1234200 | I24: =IF(D24="HDW",G24*F24,0) -> 0 | J24: =IF(D24="JASA",G24*F24,0) -> 0 | K24: =SUM(H24:J24) -> 1234200
B25: 2 | C25: Armour Tape ¼" wide | D25: =IF(ISERROR(OFFSET('HARGA SATUAN'!$D$6,MATCH(RAB!C25,'HARGA SATUAN'!$C$7:$C$1492,0),0)),"",OFFSET('HARGA SATUAN'!$D$6,MATCH(RAB!C25,'HARGA SATUAN'!$C$7:$C$1492,0),0)) -> HDW | E25: =IF(B25="+","Unit",IF(ISERROR(OFFSET('HARGA SATUAN'!$E$6,MATCH(RAB!C25,'HARGA SATUAN'!$C$7:$C$1492,0),0)),"",OFFSET('HARGA SATUAN'!$E$6,MATCH(RAB!C25,'HARGA SATUAN'!$C$7:$C$1492,0),0))) -> Mtr | F25: =F23*1 -> 2 | G25: =IF(ISERROR(OFFSET('HARGA SATUAN'!$I$6,MATCH(RAB!C25,'HARGA SATUAN'!$C$7:$C$1492,0),0)),0,OFFSET('HARGA SATUAN'!$I$6,MATCH(RAB!C25,'HARGA SATUAN'!$C$7:$C$1492,0),0)) -> 7789 | H25: =IF(OR(D25="MDU",D25="MDU-KD"),(IF($O$3="RAB NON MDU","PLN KD",G25*F25)),0) -> 0 | I25: =IF(D25="HDW",G25*F25,0) -> 15578 | J25: =IF(D25="JASA",G25*F25,0) -> 0 | K25: =SUM(H25:J25) -> 15578
B26: 3 | C26: Bolt Double Arming ⅝" x 14" | D26: =IF(ISERROR(OFFSET('HARGA SATUAN'!$D$6,MATCH(RAB!C26,'HARGA SATUAN'!$C$7:$C$1492,0),0)),"",OFFSET('HARGA SATUAN'!$D$6,MATCH(RAB!C26,'HARGA SATUAN'!$C$7:$C$1492,0),0)) -> HDW | E26: =IF(B26="+","Unit",IF(ISERROR(OFFSET('HARGA SATUAN'!$E$6,MATCH(RAB!C26,'HARGA SATUAN'!$C$7:$C$1492,0),0)),"",OFFSET('HARGA SATUAN'!$E$6,MATCH(RAB!C26,'HARGA SATUAN'!$C$7:$C$1492,0),0))) -> Bh | F26: =F23*2 -> 4 | G26: =IF(ISERROR(OFFSET('HARGA SATUAN'!$I$6,MATCH(RAB!C26,'HARGA SATUAN'!$C$7:$C$1492,0),0)),0,OFFSET('HARGA SATUAN'!$I$6,MATCH(RAB!C26,'HARGA SATUAN'!$C$7:$C$1492,0),0)) -> 40000 | H26: =IF(OR(D26="MDU",D26="MDU-KD"),(IF($O$3="RAB NON MDU","PLN KD",G26*F26)),0) -> 0 | I26: =IF(D26="HDW",G26*F26,0) -> 160000 | J26: =IF(D26="JASA",G26*F26,0) -> 0 | K26: =SUM(H26:J26) -> 160000
B27: 4 | C27: Bolt Machine ⅝" x 10" | D27: =IF(ISERROR(OFFSET('HARGA SATUAN'!$D$6,MATCH(RAB!C27,'HARGA SATUAN'!$C$7:$C$1492,0),0)),"",OFFSET('HARGA SATUAN'!$D$6,MATCH(RAB!C27,'HARGA SATUAN'!$C$7:$C$1492,0),0)) -> HDW | E27: =IF(B27="+","Unit",IF(ISERROR(OFFSET('HARGA SATUAN'!$E$6,MATCH(RAB!C27,'HARGA SATUAN'!$C$7:$C$1492,0),0)),"",OFFSET('HARGA SATUAN'!$E$6,MATCH(RAB!C27,'HARGA SATUAN'!$C$7:$C$1492,0),0))) -> Bh | F27: =F23*1 -> 2 | G27: =IF(ISERROR(OFFSET('HARGA SATUAN'!$I$6,MATCH(RAB!C27,'HARGA SATUAN'!$C$7:$C$1492,0),0)),0,OFFSET('HARGA SATUAN'!$I$6,MATCH(RAB!C27,'HARGA SATUAN'!$C$7:$C$1492,0),0)) -> 26500 | H27: =IF(OR(D27="MDU",D27="MDU-KD"),(IF($O$3="RAB NON MDU","PLN KD",G27*F27)),0) -> 0 | I27: =IF(D27="HDW",G27*F27,0) -> 53000 | J27: =IF(D27="JASA",G27*F27,0) -> 0 | K27: =SUM(H27:J27) -> 53000
B28: 5 | C28: Bolt Machine / Bolt cariage ½" x ¾" | D28: =IF(ISERROR(OFFSET('HARGA SATUAN'!$D$6,MATCH(RAB!C28,'HARGA SATUAN'!$C$7:$C$1492,0),0)),"",OFFSET('HARGA SATUAN'!$D$6,MATCH(RAB!C28,'HARGA SATUAN'!$C$7:$C$1492,0),0)) -> HDW | E28: =IF(B28="+","Unit",IF(ISERROR(OFFSET('HARGA SATUAN'!$E$6,MATCH(RAB!C28,'HARGA SATUAN'!$C$7:$C$1492,0),0)),"",OFFSET('HARGA SATUAN'!$E$6,MATCH(RAB!C28,'HARGA SATUAN'!$C$7:$C$1492,0),0))) -> Bh | F28: =F23*4 -> 8 | G28: =IF(ISERROR(OFFSET('HARGA SATUAN'!$I$6,MATCH(RAB!C28,'HARGA SATUAN'!$C$7:$C$1492,0),0)),0,OFFSET('HARGA SATUAN'!$I$6,MATCH(RAB!C28,'HARGA SATUAN'!$C$7:$C$1492,0),0)) -> 7938 | H28: =IF(OR(D28="MDU",D28="MDU-KD"),(IF($O$3="RAB NON MDU","PLN KD",G28*F28)),0) -> 0 | I28: =IF(D28="HDW",G28*F28,0) -> 63504 | J28: =IF(D28="JASA",G28*F28,0) -> 0 | K28: =SUM(H28:J28) -> 63504
B29: 6 | C29: Brace Steel 770 mm | D29: =IF(ISERROR(OFFSET('HARGA SATUAN'!$D$6,MATCH(RAB!C29,'HARGA SATUAN'!$C$7:$C$1492,0),0)),"",OFFSET('HARGA SATUAN'!$D$6,MATCH(RAB!C29,'HARGA SATUAN'!$C$7:$C$1492,0),0)) -> HDW | E29: =IF(B29="+","Unit",IF(ISERROR(OFFSET('HARGA SATUAN'!$E$6,MATCH(RAB!C29,'HARGA SATUAN'!$C$7:$C$1492,0),0)),"",OFFSET('HARGA SATUAN'!$E$6,MATCH(RAB!C29,'HARGA SATUAN'!$C$7:$C$1492,0),0))) -> Bh | F29: =F23*4 -> 8 | G29: =IF(ISERROR(OFFSET('HARGA SATUAN'!$I$6,MATCH(RAB!C29,'HARGA SATUAN'!$C$7:$C$1492,0),0)),0,OFFSET('HARGA SATUAN'!$I$6,MATCH(RAB!C29,'HARGA SATUAN'!$C$7:$C$1492,0),0)) -> 45000 | H29: =IF(OR(D29="MDU",D29="MDU-KD"),(IF($O$3="RAB NON MDU","PLN KD",G29*F29)),0) -> 0 | I29: =IF(D29="HDW",G29*F29,0) -> 360000 | J29: =IF(D29="JASA",G29*F29,0) -> 0 | K29: =SUM(H29:J29) -> 360000
B30: 7 | C30: Clevis Swinging Secondary | D30: =IF(ISERROR(OFFSET('HARGA SATUAN'!$D$6,MATCH(RAB!C30,'HARGA SATUAN'!$C$7:$C$1492,0),0)),"",OFFSET('HARGA SATUAN'!$D$6,MATCH(RAB!C30,'HARGA SATUAN'!$C$7:$C$1492,0),0)) -> HDW | E30: =IF(B30="+","Unit",IF(ISERROR(OFFSET('HARGA SATUAN'!$E$6,MATCH(RAB!C30,'HARGA SATUAN'!$C$7:$C$1492,0),0)),"",OFFSET('HARGA SATUAN'!$E$6,MATCH(RAB!C30,'HARGA SATUAN'!$C$7:$C$1492,0),0))) -> Bh | F30: =F23*1 -> 2 | G30: =IF(ISERROR(OFFSET('HARGA SATUAN'!$I$6,MATCH(RAB!C30,'HARGA SATUAN'!$C$7:$C$1492,0),0)),0,OFFSET('HARGA SATUAN'!$I$6,MATCH(RAB!C30,'HARGA SATUAN'!$C$7:$C$1492,0),0)) -> 15500 | H30: =IF(OR(D30="MDU",D30="MDU-KD"),(IF($O$3="RAB NON MDU","PLN KD",G30*F30)),0) -> 0 | I30: =IF(D30="HDW",G30*F30,0) -> 31000 | J30: =IF(D30="JASA",G30*F30,0) -> 0 | K30: =SUM(H30:J30) -> 31000
B31: 8 | C31: Cross Arm Steel 2.000 mm ( UNSP 10 ) galvanis | D31: =IF(ISERROR(OFFSET('HARGA SATUAN'!$D$6,MATCH(RAB!C31,'HARGA SATUAN'!$C$7:$C$1492,0),0)),"",OFFSET('HARGA SATUAN'!$D$6,MATCH(RAB!C31,'HARGA SATUAN'!$C$7:$C$1492,0),0)) -> HDW | E31: =IF(B31="+","Unit",IF(ISERROR(OFFSET('HARGA SATUAN'!$E$6,MATCH(RAB!C31,'HARGA SATUAN'!$C$7:$C$1492,0),0)),"",OFFSET('HARGA SATUAN'!$E$6,MATCH(RAB!C31,'HARGA SATUAN'!$C$7:$C$1492,0),0))) -> Bh | F31: =F23*2 -> 4 | G31: =IF(ISERROR(OFFSET('HARGA SATUAN'!$I$6,MATCH(RAB!C31,'HARGA SATUAN'!$C$7:$C$1492,0),0)),0,OFFSET('HARGA SATUAN'!$I$6,MATCH(RAB!C31,'HARGA SATUAN'!$C$7:$C$1492,0),0)) -> 380500 | H31: =IF(OR(D31="MDU",D31="MDU-KD"),(IF($O$3="RAB NON MDU","PLN KD",G31*F31)),0) -> 0 | I31: =IF(D31="HDW",G31*F31,0) -> 1522000 | J31: =IF(D31="JASA",G31*F31,0) -> 0 | K31: =SUM(H31:J31) -> 1522000
B32: 9 | C32: Lock Nut ⅝" | D32: =IF(ISERROR(OFFSET('HARGA SATUAN'!$D$6,MATCH(RAB!C32,'HARGA SATUAN'!$C$7:$C$1492,0),0)),"",OFFSET('HARGA SATUAN'!$D$6,MATCH(RAB!C32,'HARGA SATUAN'!$C$7:$C$1492,0),0)) -> HDW | E32: =IF(B32="+","Unit",IF(ISERROR(OFFSET('HARGA SATUAN'!$E$6,MATCH(RAB!C32,'HARGA SATUAN'!$C$7:$C$1492,0),0)),"",OFFSET('HARGA SATUAN'!$E$6,MATCH(RAB!C32,'HARGA SATUAN'!$C$7:$C$1492,0),0))) -> Bh | F32: =F23*4 -> 8 | G32: =IF(ISERROR(OFFSET('HARGA SATUAN'!$I$6,MATCH(RAB!C32,'HARGA SATUAN'!$C$7:$C$1492,0),0)),0,OFFSET('HARGA SATUAN'!$I$6,MATCH(RAB!C32,'HARGA SATUAN'!$C$7:$C$1492,0),0)) -> 11400 | H32: =IF(OR(D32="MDU",D32="MDU-KD"),(IF($O$3="RAB NON MDU","PLN KD",G32*F32)),0) -> 0 | I32: =IF(D32="HDW",G32*F32,0) -> 91200 | J32: =IF(D32="JASA",G32*F32,0) -> 0 | K32: =SUM(H32:J32) -> 91200
B33: 10 | C33: Loop Dead End Clamp / LC ( 35 s/d 240 ) mm² | D33: =IF(ISERROR(OFFSET('HARGA SATUAN'!$D$6,MATCH(RAB!C33,'HARGA SATUAN'!$C$7:$C$1492,0),0)),"",OFFSET('HARGA SATUAN'!$D$6,MATCH(RAB!C33,'HARGA SATUAN'!$C$7:$C$1492,0),0)) -> HDW | E33: =IF(B33="+","Unit",IF(ISERROR(OFFSET('HARGA SATUAN'!$E$6,MATCH(RAB!C33,'HARGA SATUAN'!$C$7:$C$1492,0),0)),"",OFFSET('HARGA SATUAN'!$E$6,MATCH(RAB!C33,'HARGA SATUAN'!$C$7:$C$1492,0),0))) -> Bh | F33: =F23*2 -> 4 | G33: =IF(ISERROR(OFFSET('HARGA SATUAN'!$I$6,MATCH(RAB!C33,'HARGA SATUAN'!$C$7:$C$1492,0),0)),0,OFFSET('HARGA SATUAN'!$I$6,MATCH(RAB!C33,'HARGA SATUAN'!$C$7:$C$1492,0),0)) -> 29600 | H33: =IF(OR(D33="MDU",D33="MDU-KD"),(IF($O$3="RAB NON MDU","PLN KD",G33*F33)),0) -> 0 | I33: =IF(D33="HDW",G33*F33,0) -> 118400 | J33: =IF(D33="JASA",G33*F33,0) -> 0 | K33: =SUM(H33:J33) -> 118400
B34: 11 | C34: Oval Eye Bolt ⅝" x 10" | D34: =IF(ISERROR(OFFSET('HARGA SATUAN'!$D$6,MATCH(RAB!C34,'HARGA SATUAN'!$C$7:$C$1492,0),0)),"",OFFSET('HARGA SATUAN'!$D$6,MATCH(RAB!C34,'HARGA SATUAN'!$C$7:$C$1492,0),0)) -> HDW | E34: =IF(B34="+","Unit",IF(ISERROR(OFFSET('HARGA SATUAN'!$E$6,MATCH(RAB!C34,'HARGA SATUAN'!$C$7:$C$1492,0),0)),"",OFFSET('HARGA SATUAN'!$E$6,MATCH(RAB!C34,'HARGA SATUAN'!$C$7:$C$1492,0),0))) -> Bh | F34: =F23*1 -> 2 | G34: =IF(ISERROR(OFFSET('HARGA SATUAN'!$I$6,MATCH(RAB!C34,'HARGA SATUAN'!$C$7:$C$1492,0),0)),0,OFFSET('HARGA SATUAN'!$I$6,MATCH(RAB!C34,'HARGA SATUAN'!$C$7:$C$1492,0),0)) -> 27815 | H34: =IF(OR(D34="MDU",D34="MDU-KD"),(IF($O$3="RAB NON MDU","PLN KD",G34*F34)),0) -> 0 | I34: =IF(D34="HDW",G34*F34,0) -> 55630 | J34: =IF(D34="JASA",G34*F34,0) -> 0 | K34: =SUM(H34:J34) -> 55630
B35: 12 | C35: Oval Eye Nut ⅝" | D35: =IF(ISERROR(OFFSET('HARGA SATUAN'!$D$6,MATCH(RAB!C35,'HARGA SATUAN'!$C$7:$C$1492,0),0)),"",OFFSET('HARGA SATUAN'!$D$6,MATCH(RAB!C35,'HARGA SATUAN'!$C$7:$C$1492,0),0)) -> HDW | E35: =IF(B35="+","Unit",IF(ISERROR(OFFSET('HARGA SATUAN'!$E$6,MATCH(RAB!C35,'HARGA SATUAN'!$C$7:$C$1492,0),0)),"",OFFSET('HARGA SATUAN'!$E$6,MATCH(RAB!C35,'HARGA SATUAN'!$C$7:$C$1492,0),0))) -> Bh | F35: =F23*3 -> 6 | G35: =IF(ISERROR(OFFSET('HARGA SATUAN'!$I$6,MATCH(RAB!C35,'HARGA SATUAN'!$C$7:$C$1492,0),0)),0,OFFSET('HARGA SATUAN'!$I$6,MATCH(RAB!C35,'HARGA SATUAN'!$C$7:$C$1492,0),0)) -> 23936 | H35: =IF(OR(D35="MDU",D35="MDU-KD"),(IF($O$3="RAB NON MDU","PLN KD",G35*F35)),0) -> 0 | I35: =IF(D35="HDW",G35*F35,0) -> 143616 | J35: =IF(D35="JASA",G35*F35,0) -> 0 | K35: =SUM(H35:J35) -> 143616
B36: 13 | C36: Pole Band Double Rack 7" atau 7 ½" | D36: =IF(ISERROR(OFFSET('HARGA SATUAN'!$D$6,MATCH(RAB!C36,'HARGA SATUAN'!$C$7:$C$1492,0),0)),"",OFFSET('HARGA SATUAN'!$D$6,MATCH(RAB!C36,'HARGA SATUAN'!$C$7:$C$1492,0),0)) -> HDW | E36: =IF(B36="+","Unit",IF(ISERROR(OFFSET('HARGA SATUAN'!$E$6,MATCH(RAB!C36,'HARGA SATUAN'!$C$7:$C$1492,0),0)),"",OFFSET('HARGA SATUAN'!$E$6,MATCH(RAB!C36,'HARGA SATUAN'!$C$7:$C$1492,0),0))) -> Bh | F36: =F23*1 -> 2 | G36: =IF(ISERROR(OFFSET('HARGA SATUAN'!$I$6,MATCH(RAB!C36,'HARGA SATUAN'!$C$7:$C$1492,0),0)),0,OFFSET('HARGA SATUAN'!$I$6,MATCH(RAB!C36,'HARGA SATUAN'!$C$7:$C$1492,0),0)) -> 63500 | H36: =IF(OR(D36="MDU",D36="MDU-KD"),(IF($O$3="RAB NON MDU","PLN KD",G36*F36)),0) -> 0 | I36: =IF(D36="HDW",G36*F36,0) -> 127000 | J36: =IF(D36="JASA",G36*F36,0) -> 0 | K36: =SUM(H36:J36) -> 127000
B37: 14 | C37: Pole Band Single Rack 7" atau 7 ½" | D37: =IF(ISERROR(OFFSET('HARGA SATUAN'!$D$6,MATCH(RAB!C37,'HARGA SATUAN'!$C$7:$C$1492,0),0)),"",OFFSET('HARGA SATUAN'!$D$6,MATCH(RAB!C37,'HARGA SATUAN'!$C$7:$C$1492,0),0)) -> HDW | E37: =IF(B37="+","Unit",IF(ISERROR(OFFSET('HARGA SATUAN'!$E$6,MATCH(RAB!C37,'HARGA SATUAN'!$C$7:$C$1492,0),0)),"",OFFSET('HARGA SATUAN'!$E$6,MATCH(RAB!C37,'HARGA SATUAN'!$C$7:$C$1492,0),0))) -> Bh | F37: =F23*1 -> 2 | G37: =IF(ISERROR(OFFSET('HARGA SATUAN'!$I$6,MATCH(RAB!C37,'HARGA SATUAN'!$C$7:$C$1492,0),0)),0,OFFSET('HARGA SATUAN'!$I$6,MATCH(RAB!C37,'HARGA SATUAN'!$C$7:$C$1492,0),0)) -> 57690 | H37: =IF(OR(D37="MDU",D37="MDU-KD"),(IF($O$3="RAB NON MDU","PLN KD",G37*F37)),0) -> 0 | I37: =IF(D37="HDW",G37*F37,0) -> 115380 | J37: =IF(D37="JASA",G37*F37,0) -> 0 | K37: =SUM(H37:J37) -> 115380
B38: 15 | C38: Schackle Anchor ⅝" | D38: =IF(ISERROR(OFFSET('HARGA SATUAN'!$D$6,MATCH(RAB!C38,'HARGA SATUAN'!$C$7:$C$1492,0),0)),"",OFFSET('HARGA SATUAN'!$D$6,MATCH(RAB!C38,'HARGA SATUAN'!$C$7:$C$1492,0),0)) -> HDW | E38: =IF(B38="+","Unit",IF(ISERROR(OFFSET('HARGA SATUAN'!$E$6,MATCH(RAB!C38,'HARGA SATUAN'!$C$7:$C$1492,0),0)),"",OFFSET('HARGA SATUAN'!$E$6,MATCH(RAB!C38,'HARGA SATUAN'!$C$7:$C$1492,0),0))) -> Bh | F38: =F23*3 -> 6 | G38: =IF(ISERROR(OFFSET('HARGA SATUAN'!$I$6,MATCH(RAB!C38,'HARGA SATUAN'!$C$7:$C$1492,0),0)),0,OFFSET('HARGA SATUAN'!$I$6,MATCH(RAB!C38,'HARGA SATUAN'!$C$7:$C$1492,0),0)) -> 16000 | H38: =IF(OR(D38="MDU",D38="MDU-KD"),(IF($O$3="RAB NON MDU","PLN KD",G38*F38)),0) -> 0 | I38: =IF(D38="HDW",G38*F38,0) -> 96000 | J38: =IF(D38="JASA",G38*F38,0) -> 0 | K38: =SUM(H38:J38) -> 96000
B39: 16 | C39: Spool Insulator ANSI 53 - 4 | D39: =IF(ISERROR(OFFSET('HARGA SATUAN'!$D$6,MATCH(RAB!C39,'HARGA SATUAN'!$C$7:$C$1492,0),0)),"",OFFSET('HARGA SATUAN'!$D$6,MATCH(RAB!C39,'HARGA SATUAN'!$C$7:$C$1492,0),0)) -> HDW | E39: =IF(B39="+","Unit",IF(ISERROR(OFFSET('HARGA SATUAN'!$E$6,MATCH(RAB!C39,'HARGA SATUAN'!$C$7:$C$1492,0),0)),"",OFFSET('HARGA SATUAN'!$E$6,MATCH(RAB!C39,'HARGA SATUAN'!$C$7:$C$1492,0),0))) -> Bh | F39: =F23*1 -> 2 | G39: =IF(ISERROR(OFFSET('HARGA SATUAN'!$I$6,MATCH(RAB!C39,'HARGA SATUAN'!$C$7:$C$1492,0),0)),0,OFFSET('HARGA SATUAN'!$I$6,MATCH(RAB!C39,'HARGA SATUAN'!$C$7:$C$1492,0),0)) -> 33501.867 | H39: =IF(OR(D39="MDU",D39="MDU-KD"),(IF($O$3="RAB NON MDU","PLN KD",G39*F39)),0) -> 0 | I39: =IF(D39="HDW",G39*F39,0) -> 67003.733 | J39: =IF(D39="JASA",G39*F39,0) -> 0 | K39: =SUM(H39:J39) -> 67003.733
B40: 17 | C40: Washer Square 2 ¼" | D40: =IF(ISERROR(OFFSET('HARGA SATUAN'!$D$6,MATCH(RAB!C40,'HARGA SATUAN'!$C$7:$C$1492,0),0)),"",OFFSET('HARGA SATUAN'!$D$6,MATCH(RAB!C40,'HARGA SATUAN'!$C$7:$C$1492,0),0)) -> HDW | E40: =IF(B40="+","Unit",IF(ISERROR(OFFSET('HARGA SATUAN'!$E$6,MATCH(RAB!C40,'HARGA SATUAN'!$C$7:$C$1492,0),0)),"",OFFSET('HARGA SATUAN'!$E$6,MATCH(RAB!C40,'HARGA SATUAN'!$C$7:$C$1492,0),0))) -> Bh | F40: =F23*11 -> 22 | G40: =IF(ISERROR(OFFSET('HARGA SATUAN'!$I$6,MATCH(RAB!C40,'HARGA SATUAN'!$C$7:$C$1492,0),0)),0,OFFSET('HARGA SATUAN'!$I$6,MATCH(RAB!C40,'HARGA SATUAN'!$C$7:$C$1492,0),0)) -> 2500 | H40: =IF(OR(D40="MDU",D40="MDU-KD"),(IF($O$3="RAB NON MDU","PLN KD",G40*F40)),0) -> 0 | I40: =IF(D40="HDW",G40*F40,0) -> 55000 | J40: =IF(D40="JASA",G40*F40,0) -> 0 | K40: =SUM(H40:J40) -> 55000
B41: 18 | C41: Upah Pasang Konst. JTM 3 Fasa C7 | D41: =IF(ISERROR(OFFSET('HARGA SATUAN'!$D$6,MATCH(RAB!C41,'HARGA SATUAN'!$C$7:$C$1492,0),0)),"",OFFSET('HARGA SATUAN'!$D$6,MATCH(RAB!C41,'HARGA SATUAN'!$C$7:$C$1492,0),0)) -> JASA | E41: =IF(B41="+","Unit",IF(ISERROR(OFFSET('HARGA SATUAN'!$E$6,MATCH(RAB!C41,'HARGA SATUAN'!$C$7:$C$1492,0),0)),"",OFFSET('HARGA SATUAN'!$E$6,MATCH(RAB!C41,'HARGA SATUAN'!$C$7:$C$1492,0),0))) -> Unit | F41: =F23*1 -> 2 | G41: =IF(ISERROR(OFFSET('HARGA SATUAN'!$I$6,MATCH(RAB!C41,'HARGA SATUAN'!$C$7:$C$1492,0),0)),0,OFFSET('HARGA SATUAN'!$I$6,MATCH(RAB!C41,'HARGA SATUAN'!$C$7:$C$1492,0),0)) -> 134700 | H41: =IF(OR(D41="MDU",D41="MDU-KD"),(IF($O$3="RAB NON MDU","PLN KD",G41*F41)),0) -> 0 | I41: =IF(D41="HDW",G41*F41,0) -> 0 | J41: =IF(D41="JASA",G41*F41,0) -> 269400 | K41: =SUM(H41:J41) -> 269400
D42: =IF(ISERROR(OFFSET('HARGA SATUAN'!$D$6,MATCH(RAB!C42,'HARGA SATUAN'!$C$7:$C$1492,0),0)),"",OFFSET('HARGA SATUAN'!$D$6,MATCH(RAB!C42,'HARGA SATUAN'!$C$7:$C$1492,0),0)) | E42: =IF(B42="+","Unit",IF(ISERROR(OFFSET('HARGA SATUAN'!$E$6,MATCH(RAB!C42,'HARGA SATUAN'!$C$7:$C$1492,0),0)),"",OFFSET('HARGA SATUAN'!$E$6,MATCH(RAB!C42,'HARGA SATUAN'!$C$7:$C$1492,0),0))) | G42: =IF(ISERROR(OFFSET('HARGA SATUAN'!$I$6,MATCH(RAB!C42,'HARGA SATUAN'!$C$7:$C$1492,0),0)),0,OFFSET('HARGA SATUAN'!$I$6,MATCH(RAB!C42,'HARGA SATUAN'!$C$7:$C$1492,0),0)) -> 0 | H42: =IF(OR(D42="MDU",D42="MDU-KD"),(IF($O$3="RAB NON MDU","PLN KD",G42*F42)),0) -> 0 | I42: =IF(D42="HDW",G42*F42,0) -> 0 | J42: =IF(D42="JASA",G42*F42,0) -> 0 | K42: =SUM(H42:J42) -> 0
B43: + | C43: CC1-A | D43: =IF(ISERROR(OFFSET('HARGA SATUAN'!$D$6,MATCH(RAB!C43,'HARGA SATUAN'!$C$7:$C$1492,0),0)),"",OFFSET('HARGA SATUAN'!$D$6,MATCH(RAB!C43,'HARGA SATUAN'!$C$7:$C$1492,0),0)) | E43: =IF(B43="+","Unit",IF(ISERROR(OFFSET('HARGA SATUAN'!$E$6,MATCH(RAB!C43,'HARGA SATUAN'!$C$7:$C$1492,0),0)),"",OFFSET('HARGA SATUAN'!$E$6,MATCH(RAB!C43,'HARGA SATUAN'!$C$7:$C$1492,0),0))) -> Unit | F43: 1 | G43: =IF(ISERROR(OFFSET('HARGA SATUAN'!$I$6,MATCH(RAB!C43,'HARGA SATUAN'!$C$7:$C$1492,0),0)),0,OFFSET('HARGA SATUAN'!$I$6,MATCH(RAB!C43,'HARGA SATUAN'!$C$7:$C$1492,0),0)) -> 0 | H43: =IF(OR(D43="MDU",D43="MDU-KD"),(IF($O$3="RAB NON MDU","PLN KD",G43*F43)),0) -> 0 | I43: =IF(D43="HDW",G43*F43,0) -> 0 | J43: =IF(D43="JASA",G43*F43,0) -> 0 | K43: =SUM(H43:J43) -> 0
B44: 1 | C44: Isolator Tumpu ( Pin Post ) 20 KV Porcelein | D44: =IF(ISERROR(OFFSET('HARGA SATUAN'!$D$6,MATCH(RAB!C44,'HARGA SATUAN'!$C$7:$C$1492,0),0)),"",OFFSET('HARGA SATUAN'!$D$6,MATCH(RAB!C44,'HARGA SATUAN'!$C$7:$C$1492,0),0)) -> MDU-KD | E44: =IF(B44="+","Unit",IF(ISERROR(OFFSET('HARGA SATUAN'!$E$6,MATCH(RAB!C44,'HARGA SATUAN'!$C$7:$C$1492,0),0)),"",OFFSET('HARGA SATUAN'!$E$6,MATCH(RAB!C44,'HARGA SATUAN'!$C$7:$C$1492,0),0))) -> Bh | F44: 1 | G44: =IF(ISERROR(OFFSET('HARGA SATUAN'!$I$6,MATCH(RAB!C44,'HARGA SATUAN'!$C$7:$C$1492,0),0)),0,OFFSET('HARGA SATUAN'!$I$6,MATCH(RAB!C44,'HARGA SATUAN'!$C$7:$C$1492,0),0)) -> 235900 | H44: =IF(OR(D44="MDU",D44="MDU-KD"),(IF($O$3="RAB NON MDU","PLN KD",G44*F44)),0) -> 235900 | I44: =IF(D44="HDW",G44*F44,0) -> 0 | J44: =IF(D44="JASA",G44*F44,0) -> 0 | K44: =SUM(H44:J44) -> 235900
B45: 2 | C45: Isolator Tumpu ( Pin Post ) 20 KV Porcelein | D45: =IF(ISERROR(OFFSET('HARGA SATUAN'!$D$6,MATCH(RAB!C45,'HARGA SATUAN'!$C$7:$C$1492,0),0)),"",OFFSET('HARGA SATUAN'!$D$6,MATCH(RAB!C45,'HARGA SATUAN'!$C$7:$C$1492,0),0)) -> MDU-KD | E45: =IF(B45="+","Unit",IF(ISERROR(OFFSET('HARGA SATUAN'!$E$6,MATCH(RAB!C45,'HARGA SATUAN'!$C$7:$C$1492,0),0)),"",OFFSET('HARGA SATUAN'!$E$6,MATCH(RAB!C45,'HARGA SATUAN'!$C$7:$C$1492,0),0))) -> Bh | F45: 2 | G45: =IF(ISERROR(OFFSET('HARGA SATUAN'!$I$6,MATCH(RAB!C45,'HARGA SATUAN'!$C$7:$C$1492,0),0)),0,OFFSET('HARGA SATUAN'!$I$6,MATCH(RAB!C45,'HARGA SATUAN'!$C$7:$C$1492,0),0)) -> 235900 | H45: =IF(OR(D45="MDU",D45="MDU-KD"),(IF($O$3="RAB NON MDU","PLN KD",G45*F45)),0) -> 471800 | I45: =IF(D45="HDW",G45*F45,0) -> 0 | J45: =IF(D45="JASA",G45*F45,0) -> 0 | K45: =SUM(H45:J45) -> 471800
B46: 3 | C46: Bolt Machine ⅝" x 10" | D46: =IF(ISERROR(OFFSET('HARGA SATUAN'!$D$6,MATCH(RAB!C46,'HARGA SATUAN'!$C$7:$C$1492,0),0)),"",OFFSET('HARGA SATUAN'!$D$6,MATCH(RAB!C46,'HARGA SATUAN'!$C$7:$C$1492,0),0)) -> HDW | E46: =IF(B46="+","Unit",IF(ISERROR(OFFSET('HARGA SATUAN'!$E$6,MATCH(RAB!C46,'HARGA SATUAN'!$C$7:$C$1492,0),0)),"",OFFSET('HARGA SATUAN'!$E$6,MATCH(RAB!C46,'HARGA SATUAN'!$C$7:$C$1492,0),0))) -> Bh | F46: 3 | G46: =IF(ISERROR(OFFSET('HARGA SATUAN'!$I$6,MATCH(RAB!C46,'HARGA SATUAN'!$C$7:$C$1492,0),0)),0,OFFSET('HARGA SATUAN'!$I$6,MATCH(RAB!C46,'HARGA SATUAN'!$C$7:$C$1492,0),0)) -> 26500 | H46: =IF(OR(D46="MDU",D46="MDU-KD"),(IF($O$3="RAB NON MDU","PLN KD",G46*F46)),0) -> 0 | I46: =IF(D46="HDW",G46*F46,0) -> 79500 | J46: =IF(D46="JASA",G46*F46,0) -> 0 | K46: =SUM(H46:J46) -> 79500
B47: 4 | C47: Bolt Machine / Bolt cariage ½" x ¾" | D47: =IF(ISERROR(OFFSET('HARGA SATUAN'!$D$6,MATCH(RAB!C47,'HARGA SATUAN'!$C$7:$C$1492,0),0)),"",OFFSET('HARGA SATUAN'!$D$6,MATCH(RAB!C47,'HARGA SATUAN'!$C$7:$C$1492,0),0)) -> HDW | E47: =IF(B47="+","Unit",IF(ISERROR(OFFSET('HARGA SATUAN'!$E$6,MATCH(RAB!C47,'HARGA SATUAN'!$C$7:$C$1492,0),0)),"",OFFSET('HARGA SATUAN'!$E$6,MATCH(RAB!C47,'HARGA SATUAN'!$C$7:$C$1492,0),0))) -> Bh | F47: 2 | G47: =IF(ISERROR(OFFSET('HARGA SATUAN'!$I$6,MATCH(RAB!C47,'HARGA SATUAN'!$C$7:$C$1492,0),0)),0,OFFSET('HARGA SATUAN'!$I$6,MATCH(RAB!C47,'HARGA SATUAN'!$C$7:$C$1492,0),0)) -> 7938 | H47: =IF(OR(D47="MDU",D47="MDU-KD"),(IF($O$3="RAB NON MDU","PLN KD",G47*F47)),0) -> 0 | I47: =IF(D47="HDW",G47*F47,0) -> 15876 | J47: =IF(D47="JASA",G47*F47,0) -> 0 | K47: =SUM(H47:J47) -> 15876
B48: 5 | C48: Bolt Single Up Side ⅝" x 10" | D48: =IF(ISERROR(OFFSET('HARGA SATUAN'!$D$6,MATCH(RAB!C48,'HARGA SATUAN'!$C$7:$C$1492,0),0)),"",OFFSET('HARGA SATUAN'!$D$6,MATCH(RAB!C48,'HARGA SATUAN'!$C$7:$C$1492,0),0)) -> HDW | E48: =IF(B48="+","Unit",IF(ISERROR(OFFSET('HARGA SATUAN'!$E$6,MATCH(RAB!C48,'HARGA SATUAN'!$C$7:$C$1492,0),0)),"",OFFSET('HARGA SATUAN'!$E$6,MATCH(RAB!C48,'HARGA SATUAN'!$C$7:$C$1492,0),0))) -> Bh | F48: 1 | G48: =IF(ISERROR(OFFSET('HARGA SATUAN'!$I$6,MATCH(RAB!C48,'HARGA SATUAN'!$C$7:$C$1492,0),0)),0,OFFSET('HARGA SATUAN'!$I$6,MATCH(RAB!C48,'HARGA SATUAN'!$C$7:$C$1492,0),0)) -> 33600 | H48: =IF(OR(D48="MDU",D48="MDU-KD"),(IF($O$3="RAB NON MDU","PLN KD",G48*F48)),0) -> 0 | I48: =IF(D48="HDW",G48*F48,0) -> 33600 | J48: =IF(D48="JASA",G48*F48,0) -> 0 | K48: =SUM(H48:J48) -> 33600
B49: 6 | C49: Brace Steel 770 mm | D49: =IF(ISERROR(OFFSET('HARGA SATUAN'!$D$6,MATCH(RAB!C49,'HARGA SATUAN'!$C$7:$C$1492,0),0)),"",OFFSET('HARGA SATUAN'!$D$6,MATCH(RAB!C49,'HARGA SATUAN'!$C$7:$C$1492,0),0)) -> HDW | E49: =IF(B49="+","Unit",IF(ISERROR(OFFSET('HARGA SATUAN'!$E$6,MATCH(RAB!C49,'HARGA SATUAN'!$C$7:$C$1492,0),0)),"",OFFSET('HARGA SATUAN'!$E$6,MATCH(RAB!C49,'HARGA SATUAN'!$C$7:$C$1492,0),0))) -> Bh | F49: 2 | G49: =IF(ISERROR(OFFSET('HARGA SATUAN'!$I$6,MATCH(RAB!C49,'HARGA SATUAN'!$C$7:$C$1492,0),0)),0,OFFSET('HARGA SATUAN'!$I$6,MATCH(RAB!C49,'HARGA SATUAN'!$C$7:$C$1492,0),0)) -> 45000 | H49: =IF(OR(D49="MDU",D49="MDU-KD"),(IF($O$3="RAB NON MDU","PLN KD",G49*F49)),0) -> 0 | I49: =IF(D49="HDW",G49*F49,0) -> 90000 | J49: =IF(D49="JASA",G49*F49,0) -> 0 | K49: =SUM(H49:J49) -> 90000
B50: 7 | C50: Center Bracket 12.5 KN | D50: =IF(ISERROR(OFFSET('HARGA SATUAN'!$D$6,MATCH(RAB!C50,'HARGA SATUAN'!$C$7:$C$1492,0),0)),"",OFFSET('HARGA SATUAN'!$D$6,MATCH(RAB!C50,'HARGA SATUAN'!$C$7:$C$1492,0),0)) -> HDW | E50: =IF(B50="+","Unit",IF(ISERROR(OFFSET('HARGA SATUAN'!$E$6,MATCH(RAB!C50,'HARGA SATUAN'!$C$7:$C$1492,0),0)),"",OFFSET('HARGA SATUAN'!$E$6,MATCH(RAB!C50,'HARGA SATUAN'!$C$7:$C$1492,0),0))) -> Bh | F50: 1 | G50: =IF(ISERROR(OFFSET('HARGA SATUAN'!$I$6,MATCH(RAB!C50,'HARGA SATUAN'!$C$7:$C$1492,0),0)),0,OFFSET('HARGA SATUAN'!$I$6,MATCH(RAB!C50,'HARGA SATUAN'!$C$7:$C$1492,0),0)) -> 95000 | H50: =IF(OR(D50="MDU",D50="MDU-KD"),(IF($O$3="RAB NON MDU","PLN KD",G50*F50)),0) -> 0 | I50: =IF(D50="HDW",G50*F50,0) -> 95000 | J50: =IF(D50="JASA",G50*F50,0) -> 0 | K50: =SUM(H50:J50) -> 95000
B51: 8 | C51: Cross Arm Steel 2.000 mm ( UNSP 10 ) galvanis | D51: =IF(ISERROR(OFFSET('HARGA SATUAN'!$D$6,MATCH(RAB!C51,'HARGA SATUAN'!$C$7:$C$1492,0),0)),"",OFFSET('HARGA SATUAN'!$D$6,MATCH(RAB!C51,'HARGA SATUAN'!$C$7:$C$1492,0),0)) -> HDW | E51: =IF(B51="+","Unit",IF(ISERROR(OFFSET('HARGA SATUAN'!$E$6,MATCH(RAB!C51,'HARGA SATUAN'!$C$7:$C$1492,0),0)),"",OFFSET('HARGA SATUAN'!$E$6,MATCH(RAB!C51,'HARGA SATUAN'!$C$7:$C$1492,0),0))) -> Bh | F51: 1 | G51: =IF(ISERROR(OFFSET('HARGA SATUAN'!$I$6,MATCH(RAB!C51,'HARGA SATUAN'!$C$7:$C$1492,0),0)),0,OFFSET('HARGA SATUAN'!$I$6,MATCH(RAB!C51,'HARGA SATUAN'!$C$7:$C$1492,0),0)) -> 380500 | H51: =IF(OR(D51="MDU",D51="MDU-KD"),(IF($O$3="RAB NON MDU","PLN KD",G51*F51)),0) -> 0 | I51: =IF(D51="HDW",G51*F51,0) -> 380500 | J51: =IF(D51="JASA",G51*F51,0) -> 0 | K51: =SUM(H51:J51) -> 380500
B52: 9 | C52: Lock Nut ⅝" | D52: =IF(ISERROR(OFFSET('HARGA SATUAN'!$D$6,MATCH(RAB!C52,'HARGA SATUAN'!$C$7:$C$1492,0),0)),"",OFFSET('HARGA SATUAN'!$D$6,MATCH(RAB!C52,'HARGA SATUAN'!$C$7:$C$1492,0),0)) -> HDW | E52: =IF(B52="+","Unit",IF(ISERROR(OFFSET('HARGA SATUAN'!$E$6,MATCH(RAB!C52,'HARGA SATUAN'!$C$7:$C$1492,0),0)),"",OFFSET('HARGA SATUAN'!$E$6,MATCH(RAB!C52,'HARGA SATUAN'!$C$7:$C$1492,0),0))) -> Bh | F52: 4 | G52: =IF(ISERROR(OFFSET('HARGA SATUAN'!$I$6,MATCH(RAB!C52,'HARGA SATUAN'!$C$7:$C$1492,0),0)),0,OFFSET('HARGA SATUAN'!$I$6,MATCH(RAB!C52,'HARGA SATUAN'!$C$7:$C$1492,0),0)) -> 11400 | H52: =IF(OR(D52="MDU",D52="MDU-KD"),(IF($O$3="RAB NON MDU","PLN KD",G52*F52)),0) -> 0 | I52: =IF(D52="HDW",G52*F52,0) -> 45600 | J52: =IF(D52="JASA",G52*F52,0) -> 0 | K52: =SUM(H52:J52) -> 45600
B53: 10 | C53: Pole Band Single Rack 7" atau 7 ½" | D53: =IF(ISERROR(OFFSET('HARGA SATUAN'!$D$6,MATCH(RAB!C53,'HARGA SATUAN'!$C$7:$C$1492,0),0)),"",OFFSET('HARGA SATUAN'!$D$6,MATCH(RAB!C53,'HARGA SATUAN'!$C$7:$C$1492,0),0)) -> HDW | E53: =IF(B53="+","Unit",IF(ISERROR(OFFSET('HARGA SATUAN'!$E$6,MATCH(RAB!C53,'HARGA SATUAN'!$C$7:$C$1492,0),0)),"",OFFSET('HARGA SATUAN'!$E$6,MATCH(RAB!C53,'HARGA SATUAN'!$C$7:$C$1492,0),0))) -> Bh | F53: 1 | G53: =IF(ISERROR(OFFSET('HARGA SATUAN'!$I$6,MATCH(RAB!C53,'HARGA SATUAN'!$C$7:$C$1492,0),0)),0,OFFSET('HARGA SATUAN'!$I$6,MATCH(RAB!C53,'HARGA SATUAN'!$C$7:$C$1492,0),0)) -> 57690 | H53: =IF(OR(D53="MDU",D53="MDU-KD"),(IF($O$3="RAB NON MDU","PLN KD",G53*F53)),0) -> 0 | I53: =IF(D53="HDW",G53*F53,0) -> 57690 | J53: =IF(D53="JASA",G53*F53,0) -> 0 | K53: =SUM(H53:J53) -> 57690
B54: 11 | C54: Spool Insulator ANSI 53 - 2 | D54: =IF(ISERROR(OFFSET('HARGA SATUAN'!$D$6,MATCH(RAB!C54,'HARGA SATUAN'!$C$7:$C$1492,0),0)),"",OFFSET('HARGA SATUAN'!$D$6,MATCH(RAB!C54,'HARGA SATUAN'!$C$7:$C$1492,0),0)) -> HDW | E54: =IF(B54="+","Unit",IF(ISERROR(OFFSET('HARGA SATUAN'!$E$6,MATCH(RAB!C54,'HARGA SATUAN'!$C$7:$C$1492,0),0)),"",OFFSET('HARGA SATUAN'!$E$6,MATCH(RAB!C54,'HARGA SATUAN'!$C$7:$C$1492,0),0))) -> Bh | F54: 1 | G54: =IF(ISERROR(OFFSET('HARGA SATUAN'!$I$6,MATCH(RAB!C54,'HARGA SATUAN'!$C$7:$C$1492,0),0)),0,OFFSET('HARGA SATUAN'!$I$6,MATCH(RAB!C54,'HARGA SATUAN'!$C$7:$C$1492,0),0)) -> 28000 | H54: =IF(OR(D54="MDU",D54="MDU-KD"),(IF($O$3="RAB NON MDU","PLN KD",G54*F54)),0) -> 0 | I54: =IF(D54="HDW",G54*F54,0) -> 28000 | J54: =IF(D54="JASA",G54*F54,0) -> 0 | K54: =SUM(H54:J54) -> 28000
B55: 12 | C55: Tie Wire # 4 / Alluminium bonding wire # 20 | D55: =IF(ISERROR(OFFSET('HARGA SATUAN'!$D$6,MATCH(RAB!C55,'HARGA SATUAN'!$C$7:$C$1492,0),0)),"",OFFSET('HARGA SATUAN'!$D$6,MATCH(RAB!C55,'HARGA SATUAN'!$C$7:$C$1492,0),0)) -> HDW | E55: =IF(B55="+","Unit",IF(ISERROR(OFFSET('HARGA SATUAN'!$E$6,MATCH(RAB!C55,'HARGA SATUAN'!$C$7:$C$1492,0),0)),"",OFFSET('HARGA SATUAN'!$E$6,MATCH(RAB!C55,'HARGA SATUAN'!$C$7:$C$1492,0),0))) -> Mtr | F55: 6.2 | G55: =IF(ISERROR(OFFSET('HARGA SATUAN'!$I$6,MATCH(RAB!C55,'HARGA SATUAN'!$C$7:$C$1492,0),0)),0,OFFSET('HARGA SATUAN'!$I$6,MATCH(RAB!C55,'HARGA SATUAN'!$C$7:$C$1492,0),0)) -> 8550 | H55: =IF(OR(D55="MDU",D55="MDU-KD"),(IF($O$3="RAB NON MDU","PLN KD",G55*F55)),0) -> 0 | I55: =IF(D55="HDW",G55*F55,0) -> 53010 | J55: =IF(D55="JASA",G55*F55,0) -> 0 | K55: =SUM(H55:J55) -> 53010
... B57: 14 | C57: Upah Pasang Konst. JTM 3 Fasa C1-A | D57: =IF(ISERROR(OFFSET('HARGA SATUAN'!$D$6,MATCH(RAB!C57,'HARGA SATUAN'!$C$7:$C$1492,0),0)),"",OFFSET('HARGA SATUAN'!$D$6,MATCH(RAB!C57,'HARGA SATUAN'!$C$7:$C$1492,0),0)) -> JASA | E57: =IF(B57="+","Unit",IF(ISERROR(OFFSET('HARGA SATUAN'!$E$6,MATCH(RAB!C57,'HARGA SATUAN'!$C$7:$C$1492,0),0)),"",OFFSET('HARGA SATUAN'!$E$6,MATCH(RAB!C57,'HARGA SATUAN'!$C$7:$C$1492,0),0))) -> Unit | F57: 1 | G57: =IF(ISERROR(OFFSET('HARGA SATUAN'!$I$6,MATCH(RAB!C57,'HARGA SATUAN'!$C$7:$C$1492,0),0)),0,OFFSET('HARGA SATUAN'!$I$6,MATCH(RAB!C57,'HARGA SATUAN'!$C$7:$C$1492,0),0)) -> 111000 | H57: =IF(OR(D57="MDU",D57="MDU-KD"),(IF($O$3="RAB NON MDU","PLN KD",G57*F57)),0) -> 0 | I57: =IF(D57="HDW",G57*F57,0) -> 0 | J57: =IF(D57="JASA",G57*F57,0) -> 111000 | K57: =SUM(H57:J57) -> 111000
D58: =IF(ISERROR(OFFSET('HARGA SATUAN'!$D$6,MATCH(RAB!C58,'HARGA SATUAN'!$C$7:$C$1492,0),0)),"",OFFSET('HARGA SATUAN'!$D$6,MATCH(RAB!C58,'HARGA SATUAN'!$C$7:$C$1492,0),0)) | E58: =IF(B58="+","Unit",IF(ISERROR(OFFSET('HARGA SATUAN'!$E$6,MATCH(RAB!C58,'HARGA SATUAN'!$C$7:$C$1492,0),0)),"",OFFSET('HARGA SATUAN'!$E$6,MATCH(RAB!C58,'HARGA SATUAN'!$C$7:$C$1492,0),0))) | G58: =IF(ISERROR(OFFSET('HARGA SATUAN'!$I$6,MATCH(RAB!C58,'HARGA SATUAN'!$C$7:$C$1492,0),0)),0,OFFSET('HARGA SATUAN'!$I$6,MATCH(RAB!C58,'HARGA SATUAN'!$C$7:$C$1492,0),0)) -> 0 | H58: =IF(OR(D58="MDU",D58="MDU-KD"),(IF($O$3="RAB NON MDU","PLN KD",G58*F58)),0) -> 0 | I58: =IF(D58="HDW",G58*F58,0) -> 0 | J58: =IF(D58="JASA",G58*F58,0) -> 0 | K58: =SUM(H58:J58) -> 0
B59: + | C59: CM2-12 | D59: =IF(ISERROR(OFFSET('HARGA SATUAN'!$D$6,MATCH(RAB!C59,'HARGA SATUAN'!$C$7:$C$1492,0),0)),"",OFFSET('HARGA SATUAN'!$D$6,MATCH(RAB!C59,'HARGA SATUAN'!$C$7:$C$1492,0),0)) | E59: =IF(B59="+","Unit",IF(ISERROR(OFFSET('HARGA SATUAN'!$E$6,MATCH(RAB!C59,'HARGA SATUAN'!$C$7:$C$1492,0),0)),"",OFFSET('HARGA SATUAN'!$E$6,MATCH(RAB!C59,'HARGA SATUAN'!$C$7:$C$1492,0),0))) -> Unit | F59: 3 | G59: =IF(ISERROR(OFFSET('HARGA SATUAN'!$I$6,MATCH(RAB!C59,'HARGA SATUAN'!$C$7:$C$1492,0),0)),0,OFFSET('HARGA SATUAN'!$I$6,MATCH(RAB!C59,'HARGA SATUAN'!$C$7:$C$1492,0),0)) -> 0 | H59: =IF(OR(D59="MDU",D59="MDU-KD"),(IF($O$3="RAB NON MDU","PLN KD",G59*F59)),0) -> 0 | I59: =IF(D59="HDW",G59*F59,0) -> 0 | J59: =IF(D59="JASA",G59*F59,0) -> 0 | K59: =SUM(H59:J59) -> 0
B60: 1 | C60: Bimetalic Connector 35 - 240 mm² | D60: =IF(ISERROR(OFFSET('HARGA SATUAN'!$D$6,MATCH(RAB!C60,'HARGA SATUAN'!$C$7:$C$1492,0),0)),"",OFFSET('HARGA SATUAN'!$D$6,MATCH(RAB!C60,'HARGA SATUAN'!$C$7:$C$1492,0),0)) -> HDW | E60: =IF(B60="+","Unit",IF(ISERROR(OFFSET('HARGA SATUAN'!$E$6,MATCH(RAB!C60,'HARGA SATUAN'!$C$7:$C$1492,0),0)),"",OFFSET('HARGA SATUAN'!$E$6,MATCH(RAB!C60,'HARGA SATUAN'!$C$7:$C$1492,0),0))) -> Bh | F60: =F59*1 -> 3 | G60: =IF(ISERROR(OFFSET('HARGA SATUAN'!$I$6,MATCH(RAB!C60,'HARGA SATUAN'!$C$7:$C$1492,0),0)),0,OFFSET('HARGA SATUAN'!$I$6,MATCH(RAB!C60,'HARGA SATUAN'!$C$7:$C$1492,0),0)) -> 47459 | H60: =IF(OR(D60="MDU",D60="MDU-KD"),(IF($O$3="RAB NON MDU","PLN KD",G60*F60)),0) -> 0 | I60: =IF(D60="HDW",G60*F60,0) -> 142377 | J60: =IF(D60="JASA",G60*F60,0) -> 0 | K60: =SUM(H60:J60) -> 142377
B61: 2 | C61: Ground wire Cu 16 mm² | D61: =IF(ISERROR(OFFSET('HARGA SATUAN'!$D$6,MATCH(RAB!C61,'HARGA SATUAN'!$C$7:$C$1492,0),0)),"",OFFSET('HARGA SATUAN'!$D$6,MATCH(RAB!C61,'HARGA SATUAN'!$C$7:$C$1492,0),0)) -> HDW | E61: =IF(B61="+","Unit",IF(ISERROR(OFFSET('HARGA SATUAN'!$E$6,MATCH(RAB!C61,'HARGA SATUAN'!$C$7:$C$1492,0),0)),"",OFFSET('HARGA SATUAN'!$E$6,MATCH(RAB!C61,'HARGA SATUAN'!$C$7:$C$1492,0),0))) -> Mtr | F61: =F59*0.8 -> 2.4 | G61: =IF(ISERROR(OFFSET('HARGA SATUAN'!$I$6,MATCH(RAB!C61,'HARGA SATUAN'!$C$7:$C$1492,0),0)),0,OFFSET('HARGA SATUAN'!$I$6,MATCH(RAB!C61,'HARGA SATUAN'!$C$7:$C$1492,0),0)) -> 30000 | H61: =IF(OR(D61="MDU",D61="MDU-KD"),(IF($O$3="RAB NON MDU","PLN KD",G61*F61)),0) -> 0 | I61: =IF(D61="HDW",G61*F61,0) -> 72000 | J61: =IF(D61="JASA",G61*F61,0) -> 0 | K61: =SUM(H61:J61) -> 72000
B62: 3 | C62: Ground rod & Washer | D62: =IF(ISERROR(OFFSET('HARGA SATUAN'!$D$6,MATCH(RAB!C62,'HARGA SATUAN'!$C$7:$C$1492,0),0)),"",OFFSET('HARGA SATUAN'!$D$6,MATCH(RAB!C62,'HARGA SATUAN'!$C$7:$C$1492,0),0)) -> HDW | E62: =IF(B62="+","Unit",IF(ISERROR(OFFSET('HARGA SATUAN'!$E$6,MATCH(RAB!C62,'HARGA SATUAN'!$C$7:$C$1492,0),0)),"",OFFSET('HARGA SATUAN'!$E$6,MATCH(RAB!C62,'HARGA SATUAN'!$C$7:$C$1492,0),0))) -> Bh | F62: =F59*1 -> 3 | G62: =IF(ISERROR(OFFSET('HARGA SATUAN'!$I$6,MATCH(RAB!C62,'HARGA SATUAN'!$C$7:$C$1492,0),0)),0,OFFSET('HARGA SATUAN'!$I$6,MATCH(RAB!C62,'HARGA SATUAN'!$C$7:$C$1492,0),0)) -> 9500 | H62: =IF(OR(D62="MDU",D62="MDU-KD"),(IF($O$3="RAB NON MDU","PLN KD",G62*F62)),0) -> 0 | I62: =IF(D62="HDW",G62*F62,0) -> 28500 | J62: =IF(D62="JASA",G62*F62,0) -> 0 | K62: =SUM(H62:J62) -> 28500
B63: 4 | C63: Upah Pasang Acc.Jar M2-12 | D63: =IF(ISERROR(OFFSET('HARGA SATUAN'!$D$6,MATCH(RAB!C63,'HARGA SATUAN'!$C$7:$C$1492,0),0)),"",OFFSET('HARGA SATUAN'!$D$6,MATCH(RAB!C63,'HARGA SATUAN'!$C$7:$C$1492,0),0)) -> JASA | E63: =IF(B63="+","Unit",IF(ISERROR(OFFSET('HARGA SATUAN'!$E$6,MATCH(RAB!C63,'HARGA SATUAN'!$C$7:$C$1492,0),0)),"",OFFSET('HARGA SATUAN'!$E$6,MATCH(RAB!C63,'HARGA SATUAN'!$C$7:$C$1492,0),0))) -> Unit | F63: =F59*1 -> 3 | G63: =IF(ISERROR(OFFSET('HARGA SATUAN'!$I$6,MATCH(RAB!C63,'HARGA SATUAN'!$C$7:$C$1492,0),0)),0,OFFSET('HARGA SATUAN'!$I$6,MATCH(RAB!C63,'HARGA SATUAN'!$C$7:$C$1492,0),0)) -> 16200 | H63: =IF(OR(D63="MDU",D63="MDU-KD"),(IF($O$3="RAB NON MDU","PLN KD",G63*F63)),0) -> 0 | I63: =IF(D63="HDW",G63*F63,0) -> 0 | J63: =IF(D63="JASA",G63*F63,0) -> 48600 | K63: =SUM(H63:J63) -> 48600
D64: =IF(ISERROR(OFFSET('HARGA SATUAN'!$D$6,MATCH(RAB!C64,'HARGA SATUAN'!$C$7:$C$1492,0),0)),"",OFFSET('HARGA SATUAN'!$D$6,MATCH(RAB!C64,'HARGA SATUAN'!$C$7:$C$1492,0),0)) | E64: =IF(B64="+","Unit",IF(ISERROR(OFFSET('HARGA SATUAN'!$E$6,MATCH(RAB!C64,'HARGA SATUAN'!$C$7:$C$1492,0),0)),"",OFFSET('HARGA SATUAN'!$E$6,MATCH(RAB!C64,'HARGA SATUAN'!$C$7:$C$1492,0),0))) | G64: =IF(ISERROR(OFFSET('HARGA SATUAN'!$I$6,MATCH(RAB!C64,'HARGA SATUAN'!$C$7:$C$1492,0),0)),0,OFFSET('HARGA SATUAN'!$I$6,MATCH(RAB!C64,'HARGA SATUAN'!$C$7:$C$1492,0),0)) -> 0 | H64: =IF(OR(D64="MDU",D64="MDU-KD"),(IF($O$3="RAB NON MDU","PLN KD",G64*F64)),0) -> 0 | I64: =IF(D64="HDW",G64*F64,0) -> 0 | J64: =IF(D64="JASA",G64*F64,0) -> 0 | K64: =SUM(H64:J64) -> 0
C65: CONDUKTOR | D65: =IF(ISERROR(OFFSET('HARGA SATUAN'!$D$6,MATCH(RAB!C65,'HARGA SATUAN'!$C$7:$C$1492,0),0)),"",OFFSET('HARGA SATUAN'!$D$6,MATCH(RAB!C65,'HARGA SATUAN'!$C$7:$C$1492,0),0)) | E65: =IF(B65="+","Unit",IF(ISERROR(OFFSET('HARGA SATUAN'!$E$6,MATCH(RAB!C65,'HARGA SATUAN'!$C$7:$C$1492,0),0)),"",OFFSET('HARGA SATUAN'!$E$6,MATCH(RAB!C65,'HARGA SATUAN'!$C$7:$C$1492,0),0))) | G65: =IF(ISERROR(OFFSET('HARGA SATUAN'!$I$6,MATCH(RAB!C65,'HARGA SATUAN'!$C$7:$C$1492,0),0)),0,OFFSET('HARGA SATUAN'!$I$6,MATCH(RAB!C65,'HARGA SATUAN'!$C$7:$C$1492,0),0)) -> 0 | H65: =IF(OR(D65="MDU",D65="MDU-KD"),(IF($O$3="RAB NON MDU","PLN KD",G65*F65)),0) -> 0 | I65: =IF(D65="HDW",G65*F65,0) -> 0 | J65: =IF(D65="JASA",G65*F65,0) -> 0 | K65: =SUM(H65:J65) -> 0
B66: 1 | C66: AAAC 70 mm² | D66: =IF(ISERROR(OFFSET('HARGA SATUAN'!$D$6,MATCH(RAB!C66,'HARGA SATUAN'!$C$7:$C$1492,0),0)),"",OFFSET('HARGA SATUAN'!$D$6,MATCH(RAB!C66,'HARGA SATUAN'!$C$7:$C$1492,0),0)) -> MDU-KD | E66: =IF(B66="+","Unit",IF(ISERROR(OFFSET('HARGA SATUAN'!$E$6,MATCH(RAB!C66,'HARGA SATUAN'!$C$7:$C$1492,0),0)),"",OFFSET('HARGA SATUAN'!$E$6,MATCH(RAB!C66,'HARGA SATUAN'!$C$7:$C$1492,0),0))) -> Mtr | F66: =55*4 -> 220 | G66: =IF(ISERROR(OFFSET('HARGA SATUAN'!$I$6,MATCH(RAB!C66,'HARGA SATUAN'!$C$7:$C$1492,0),0)),0,OFFSET('HARGA SATUAN'!$I$6,MATCH(RAB!C66,'HARGA SATUAN'!$C$7:$C$1492,0),0)) -> 14200 | H66: =IF(OR(D66="MDU",D66="MDU-KD"),(IF($O$3="RAB NON MDU","PLN KD",G66*F66)),0) -> 3124000 | I66: =IF(D66="HDW",G66*F66,0) -> 0 | J66: =IF(D66="JASA",G66*F66,0) -> 0 | K66: =SUM(H66:J66) -> 3124000
B67: 2 | C67: Upah Pasang Penghantar TM A3C 3x70 + 1x70mm² | D67: =IF(ISERROR(OFFSET('HARGA SATUAN'!$D$6,MATCH(RAB!C67,'HARGA SATUAN'!$C$7:$C$1492,0),0)),"",OFFSET('HARGA SATUAN'!$D$6,MATCH(RAB!C67,'HARGA SATUAN'!$C$7:$C$1492,0),0)) -> JASA | E67: =IF(B67="+","Unit",IF(ISERROR(OFFSET('HARGA SATUAN'!$E$6,MATCH(RAB!C67,'HARGA SATUAN'!$C$7:$C$1492,0),0)),"",OFFSET('HARGA SATUAN'!$E$6,MATCH(RAB!C67,'HARGA SATUAN'!$C$7:$C$1492,0),0))) -> Per 50 m | F67: =F66/200 -> 1.1 | G67: =IF(ISERROR(OFFSET('HARGA SATUAN'!$I$6,MATCH(RAB!C67,'HARGA SATUAN'!$C$7:$C$1492,0),0)),0,OFFSET('HARGA SATUAN'!$I$6,MATCH(RAB!C67,'HARGA SATUAN'!$C$7:$C$1492,0),0)) -> 300100 | H67: =IF(OR(D67="MDU",D67="MDU-KD"),(IF($O$3="RAB NON MDU","PLN KD",G67*F67)),0) -> 0 | I67: =IF(D67="HDW",G67*F67,0) -> 0 | J67: =IF(D67="JASA",G67*F67,0) -> 330110 | K67: =SUM(H67:J67) -> 330110
B68: 3 | C68: Compresion Conector H type 70 mm² / 240 mm² | D68: =IF(ISERROR(OFFSET('HARGA SATUAN'!$D$6,MATCH(RAB!C68,'HARGA SATUAN'!$C$7:$C$1492,0),0)),"",OFFSET('HARGA SATUAN'!$D$6,MATCH(RAB!C68,'HARGA SATUAN'!$C$7:$C$1492,0),0)) -> HDW | E68: =IF(B68="+","Unit",IF(ISERROR(OFFSET('HARGA SATUAN'!$E$6,MATCH(RAB!C68,'HARGA SATUAN'!$C$7:$C$1492,0),0)),"",OFFSET('HARGA SATUAN'!$E$6,MATCH(RAB!C68,'HARGA SATUAN'!$C$7:$C$1492,0),0))) -> Bh | F68: 4 | G68: =IF(ISERROR(OFFSET('HARGA SATUAN'!$I$6,MATCH(RAB!C68,'HARGA SATUAN'!$C$7:$C$1492,0),0)),0,OFFSET('HARGA SATUAN'!$I$6,MATCH(RAB!C68,'HARGA SATUAN'!$C$7:$C$1492,0),0)) -> 36500 | H68: =IF(OR(D68="MDU",D68="MDU-KD"),(IF($O$3="RAB NON MDU","PLN KD",G68*F68)),0) -> 0 | I68: =IF(D68="HDW",G68*F68,0) -> 146000 | J68: =IF(D68="JASA",G68*F68,0) -> 0 | K68: =SUM(H68:J68) -> 146000
B69: 4 | C69: Pengepresan CCO | D69: =IF(ISERROR(OFFSET('HARGA SATUAN'!$D$6,MATCH(RAB!C69,'HARGA SATUAN'!$C$7:$C$1492,0),0)),"",OFFSET('HARGA SATUAN'!$D$6,MATCH(RAB!C69,'HARGA SATUAN'!$C$7:$C$1492,0),0)) -> JASA | E69: =IF(B69="+","Unit",IF(ISERROR(OFFSET('HARGA SATUAN'!$E$6,MATCH(RAB!C69,'HARGA SATUAN'!$C$7:$C$1492,0),0)),"",OFFSET('HARGA SATUAN'!$E$6,MATCH(RAB!C69,'HARGA SATUAN'!$C$7:$C$1492,0),0))) -> Bh | F69: 4 | G69: =IF(ISERROR(OFFSET('HARGA SATUAN'!$I$6,MATCH(RAB!C69,'HARGA SATUAN'!$C$7:$C$1492,0),0)),0,OFFSET('HARGA SATUAN'!$I$6,MATCH(RAB!C69,'HARGA SATUAN'!$C$7:$C$1492,0),0)) -> 13770 | H69: =IF(OR(D69="MDU",D69="MDU-KD"),(IF($O$3="RAB NON MDU","PLN KD",G69*F69)),0) -> 0 | I69: =IF(D69="HDW",G69*F69,0) -> 0 | J69: =IF(D69="JASA",G69*F69,0) -> 55080 | K69: =SUM(H69:J69) -> 55080
D70: =IF(ISERROR(OFFSET('HARGA SATUAN'!$D$6,MATCH(RAB!C70,'HARGA SATUAN'!$C$7:$C$1492,0),0)),"",OFFSET('HARGA SATUAN'!$D$6,MATCH(RAB!C70,'HARGA SATUAN'!$C$7:$C$1492,0),0)) | E70: =IF(B70="+","Unit",IF(ISERROR(OFFSET('HARGA SATUAN'!$E$6,MATCH(RAB!C70,'HARGA SATUAN'!$C$7:$C$1492,0),0)),"",OFFSET('HARGA SATUAN'!$E$6,MATCH(RAB!C70,'HARGA SATUAN'!$C$7:$C$1492,0),0))) | G70: =IF(ISERROR(OFFSET('HARGA SATUAN'!$I$6,MATCH(RAB!C70,'HARGA SATUAN'!$C$7:$C$1492,0),0)),0,OFFSET('HARGA SATUAN'!$I$6,MATCH(RAB!C70,'HARGA SATUAN'!$C$7:$C$1492,0),0)) -> 0 | H70: =IF(OR(D70="MDU",D70="MDU-KD"),(IF($O$3="RAB NON MDU","PLN KD",G70*F70)),0) -> 0 | I70: =IF(D70="HDW",G70*F70,0) -> 0 | J70: =IF(D70="JASA",G70*F70,0) -> 0 | K70: =SUM(H70:J70) -> 0
C71: SCHOOR | D71: =IF(ISERROR(OFFSET('HARGA SATUAN'!$D$6,MATCH(RAB!C71,'HARGA SATUAN'!$C$7:$C$1492,0),0)),"",OFFSET('HARGA SATUAN'!$D$6,MATCH(RAB!C71,'HARGA SATUAN'!$C$7:$C$1492,0),0)) | E71: =IF(B71="+","Unit",IF(ISERROR(OFFSET('HARGA SATUAN'!$E$6,MATCH(RAB!C71,'HARGA SATUAN'!$C$7:$C$1492,0),0)),"",OFFSET('HARGA SATUAN'!$E$6,MATCH(RAB!C71,'HARGA SATUAN'!$C$7:$C$1492,0),0))) | G71: =IF(ISERROR(OFFSET('HARGA SATUAN'!$I$6,MATCH(RAB!C71,'HARGA SATUAN'!$C$7:$C$1492,0),0)),0,OFFSET('HARGA SATUAN'!$I$6,MATCH(RAB!C71,'HARGA SATUAN'!$C$7:$C$1492,0),0)) -> 0 | H71: =IF(OR(D71="MDU",D71="MDU-KD"),(IF($O$3="RAB NON MDU","PLN KD",G71*F71)),0) -> 0 | I71: =IF(D71="HDW",G71*F71,0) -> 0 | J71: =IF(D71="JASA",G71*F71,0) -> 0 | K71: =SUM(H71:J71) -> 0
D72: =IF(ISERROR(OFFSET('HARGA SATUAN'!$D$6,MATCH(RAB!C72,'HARGA SATUAN'!$C$7:$C$1492,0),0)),"",OFFSET('HARGA SATUAN'!$D$6,MATCH(RAB!C72,'HARGA SATUAN'!$C$7:$C$1492,0),0)) | E72: =IF(B72="+","Unit",IF(ISERROR(OFFSET('HARGA SATUAN'!$E$6,MATCH(RAB!C72,'HARGA SATUAN'!$C$7:$C$1492,0),0)),"",OFFSET('HARGA SATUAN'!$E$6,MATCH(RAB!C72,'HARGA SATUAN'!$C$7:$C$1492,0),0))) | G72: =IF(ISERROR(OFFSET('HARGA SATUAN'!$I$6,MATCH(RAB!C72,'HARGA SATUAN'!$C$7:$C$1492,0),0)),0,OFFSET('HARGA SATUAN'!$I$6,MATCH(RAB!C72,'HARGA SATUAN'!$C$7:$C$1492,0),0)) -> 0 | H72: =IF(OR(D72="MDU",D72="MDU-KD"),(IF($O$3="RAB NON MDU","PLN KD",G72*F72)),0) -> 0 | I72: =IF(D72="HDW",G72*F72,0) -> 0 | J72: =IF(D72="JASA",G72*F72,0) -> 0 | K72: =SUM(H72:J72) -> 0
B73: + | C73: CE1-3 | D73: =IF(ISERROR(OFFSET('HARGA SATUAN'!$D$6,MATCH(RAB!C73,'HARGA SATUAN'!$C$7:$C$1492,0),0)),"",OFFSET('HARGA SATUAN'!$D$6,MATCH(RAB!C73,'HARGA SATUAN'!$C$7:$C$1492,0),0)) | E73: =IF(B73="+","Unit",IF(ISERROR(OFFSET('HARGA SATUAN'!$E$6,MATCH(RAB!C73,'HARGA SATUAN'!$C$7:$C$1492,0),0)),"",OFFSET('HARGA SATUAN'!$E$6,MATCH(RAB!C73,'HARGA SATUAN'!$C$7:$C$1492,0),0))) -> Unit | F73: 1 | G73: =IF(ISERROR(OFFSET('HARGA SATUAN'!$I$6,MATCH(RAB!C73,'HARGA SATUAN'!$C$7:$C$1492,0),0)),0,OFFSET('HARGA SATUAN'!$I$6,MATCH(RAB!C73,'HARGA SATUAN'!$C$7:$C$1492,0),0)) -> 0 | H73: =IF(OR(D73="MDU",D73="MDU-KD"),(IF($O$3="RAB NON MDU","PLN KD",G73*F73)),0) -> 0 | I73: =IF(D73="HDW",G73*F73,0) -> 0 | J73: =IF(D73="JASA",G73*F73,0) -> 0 | K73: =SUM(H73:J73) -> 0
B74: 1 | C74: Bolt Machine ⅝" x 10" | D74: =IF(ISERROR(OFFSET('HARGA SATUAN'!$D$6,MATCH(RAB!C74,'HARGA SATUAN'!$C$7:$C$1492,0),0)),"",OFFSET('HARGA SATUAN'!$D$6,MATCH(RAB!C74,'HARGA SATUAN'!$C$7:$C$1492,0),0)) -> HDW | E74: =IF(B74="+","Unit",IF(ISERROR(OFFSET('HARGA SATUAN'!$E$6,MATCH(RAB!C74,'HARGA SATUAN'!$C$7:$C$1492,0),0)),"",OFFSET('HARGA SATUAN'!$E$6,MATCH(RAB!C74,'HARGA SATUAN'!$C$7:$C$1492,0),0))) -> Bh | F74: =F73*1 -> 1 | G74: =IF(ISERROR(OFFSET('HARGA SATUAN'!$I$6,MATCH(RAB!C74,'HARGA SATUAN'!$C$7:$C$1492,0),0)),0,OFFSET('HARGA SATUAN'!$I$6,MATCH(RAB!C74,'HARGA SATUAN'!$C$7:$C$1492,0),0)) -> 26500 | H74: =IF(OR(D74="MDU",D74="MDU-KD"),(IF($O$3="RAB NON MDU","PLN KD",G74*F74)),0) -> 0 | I74: =IF(D74="HDW",G74*F74,0) -> 26500 | J74: =IF(D74="JASA",G74*F74,0) -> 0 | K74: =SUM(H74:J74) -> 26500
B75: 2 | C75: Guy Attachment / Guy hok | D75: =IF(ISERROR(OFFSET('HARGA SATUAN'!$D$6,MATCH(RAB!C75,'HARGA SATUAN'!$C$7:$C$1492,0),0)),"",OFFSET('HARGA SATUAN'!$D$6,MATCH(RAB!C75,'HARGA SATUAN'!$C$7:$C$1492,0),0)) -> HDW | E75: =IF(B75="+","Unit",IF(ISERROR(OFFSET('HARGA SATUAN'!$E$6,MATCH(RAB!C75,'HARGA SATUAN'!$C$7:$C$1492,0),0)),"",OFFSET('HARGA SATUAN'!$E$6,MATCH(RAB!C75,'HARGA SATUAN'!$C$7:$C$1492,0),0))) -> Bh | F75: =F73*1 -> 1 | G75: =IF(ISERROR(OFFSET('HARGA SATUAN'!$I$6,MATCH(RAB!C75,'HARGA SATUAN'!$C$7:$C$1492,0),0)),0,OFFSET('HARGA SATUAN'!$I$6,MATCH(RAB!C75,'HARGA SATUAN'!$C$7:$C$1492,0),0)) -> 12500 | H75: =IF(OR(D75="MDU",D75="MDU-KD"),(IF($O$3="RAB NON MDU","PLN KD",G75*F75)),0) -> 0 | I75: =IF(D75="HDW",G75*F75,0) -> 12500 | J75: =IF(D75="JASA",G75*F75,0) -> 0 | K75: =SUM(H75:J75) -> 12500
B76: 3 | C76: Guy Wire 70 mm² | D76: =IF(ISERROR(OFFSET('HARGA SATUAN'!$D$6,MATCH(RAB!C76,'HARGA SATUAN'!$C$7:$C$1492,0),0)),"",OFFSET('HARGA SATUAN'!$D$6,MATCH(RAB!C76,'HARGA SATUAN'!$C$7:$C$1492,0),0)) -> HDW | E76: =IF(B76="+","Unit",IF(ISERROR(OFFSET('HARGA SATUAN'!$E$6,MATCH(RAB!C76,'HARGA SATUAN'!$C$7:$C$1492,0),0)),"",OFFSET('HARGA SATUAN'!$E$6,MATCH(RAB!C76,'HARGA SATUAN'!$C$7:$C$1492,0),0))) -> Mtr | F76: =F73*12 -> 12 | G76: =IF(ISERROR(OFFSET('HARGA SATUAN'!$I$6,MATCH(RAB!C76,'HARGA SATUAN'!$C$7:$C$1492,0),0)),0,OFFSET('HARGA SATUAN'!$I$6,MATCH(RAB!C76,'HARGA SATUAN'!$C$7:$C$1492,0),0)) -> 39204 | H76: =IF(OR(D76="MDU",D76="MDU-KD"),(IF($O$3="RAB NON MDU","PLN KD",G76*F76)),0) -> 0 | I76: =IF(D76="HDW",G76*F76,0) -> 470448 | J76: =IF(D76="JASA",G76*F76,0) -> 0 | K76: =SUM(H76:J76) -> 470448
B77: 4 | C77: Three Bolt Clamp | D77: =IF(ISERROR(OFFSET('HARGA SATUAN'!$D$6,MATCH(RAB!C77,'HARGA SATUAN'!$C$7:$C$1492,0),0)),"",OFFSET('HARGA SATUAN'!$D$6,MATCH(RAB!C77,'HARGA SATUAN'!$C$7:$C$1492,0),0)) -> HDW | E77: =IF(B77="+","Unit",IF(ISERROR(OFFSET('HARGA SATUAN'!$E$6,MATCH(RAB!C77,'HARGA SATUAN'!$C$7:$C$1492,0),0)),"",OFFSET('HARGA SATUAN'!$E$6,MATCH(RAB!C77,'HARGA SATUAN'!$C$7:$C$1492,0),0))) -> Bh | F77: =F73*2 -> 2 | G77: =IF(ISERROR(OFFSET('HARGA SATUAN'!$I$6,MATCH(RAB!C77,'HARGA SATUAN'!$C$7:$C$1492,0),0)),0,OFFSET('HARGA SATUAN'!$I$6,MATCH(RAB!C77,'HARGA SATUAN'!$C$7:$C$1492,0),0)) -> 40000 | H77: =IF(OR(D77="MDU",D77="MDU-KD"),(IF($O$3="RAB NON MDU","PLN KD",G77*F77)),0) -> 0 | I77: =IF(D77="HDW",G77*F77,0) -> 80000 | J77: =IF(D77="JASA",G77*F77,0) -> 0 | K77: =SUM(H77:J77) -> 80000
B78: 5 | C78: Washer Square 2 ¼" | D78: =IF(ISERROR(OFFSET('HARGA SATUAN'!$D$6,MATCH(RAB!C78,'HARGA SATUAN'!$C$7:$C$1492,0),0)),"",OFFSET('HARGA SATUAN'!$D$6,MATCH(RAB!C78,'HARGA SATUAN'!$C$7:$C$1492,0),0)) -> HDW | E78: =IF(B78="+","Unit",IF(ISERROR(OFFSET('HARGA SATUAN'!$E$6,MATCH(RAB!C78,'HARGA SATUAN'!$C$7:$C$1492,0),0)),"",OFFSET('HARGA SATUAN'!$E$6,MATCH(RAB!C78,'HARGA SATUAN'!$C$7:$C$1492,0),0))) -> Bh | F78: =F73*1 -> 1 | G78: =IF(ISERROR(OFFSET('HARGA SATUAN'!$I$6,MATCH(RAB!C78,'HARGA SATUAN'!$C$7:$C$1492,0),0)),0,OFFSET('HARGA SATUAN'!$I$6,MATCH(RAB!C78,'HARGA SATUAN'!$C$7:$C$1492,0),0)) -> 2500 | H78: =IF(OR(D78="MDU",D78="MDU-KD"),(IF($O$3="RAB NON MDU","PLN KD",G78*F78)),0) -> 0 | I78: =IF(D78="HDW",G78*F78,0) -> 2500 | J78: =IF(D78="JASA",G78*F78,0) -> 0 | K78: =SUM(H78:J78) -> 2500
B79: 6 | C79: Upah Pasang Acc.Jar E1-3 | D79: =IF(ISERROR(OFFSET('HARGA SATUAN'!$D$6,MATCH(RAB!C79,'HARGA SATUAN'!$C$7:$C$1492,0),0)),"",OFFSET('HARGA SATUAN'!$D$6,MATCH(RAB!C79,'HARGA SATUAN'!$C$7:$C$1492,0),0)) -> JASA | E79: =IF(B79="+","Unit",IF(ISERROR(OFFSET('HARGA SATUAN'!$E$6,MATCH(RAB!C79,'HARGA SATUAN'!$C$7:$C$1492,0),0)),"",OFFSET('HARGA SATUAN'!$E$6,MATCH(RAB!C79,'HARGA SATUAN'!$C$7:$C$1492,0),0))) -> Unit | F79: =F73*1 -> 1 | G79: =IF(ISERROR(OFFSET('HARGA SATUAN'!$I$6,MATCH(RAB!C79,'HARGA SATUAN'!$C$7:$C$1492,0),0)),0,OFFSET('HARGA SATUAN'!$I$6,MATCH(RAB!C79,'HARGA SATUAN'!$C$7:$C$1492,0),0)) -> 36600 | H79: =IF(OR(D79="MDU",D79="MDU-KD"),(IF($O$3="RAB NON MDU","PLN KD",G79*F79)),0) -> 0 | I79: =IF(D79="HDW",G79*F79,0) -> 0 | J79: =IF(D79="JASA",G79*F79,0) -> 36600 | K79: =SUM(H79:J79) -> 36600
D80: =IF(ISERROR(OFFSET('HARGA SATUAN'!$D$6,MATCH(RAB!C80,'HARGA SATUAN'!$C$7:$C$1492,0),0)),"",OFFSET('HARGA SATUAN'!$D$6,MATCH(RAB!C80,'HARGA SATUAN'!$C$7:$C$1492,0),0)) | E80: =IF(B80="+","Unit",IF(ISERROR(OFFSET('HARGA SATUAN'!$E$6,MATCH(RAB!C80,'HARGA SATUAN'!$C$7:$C$1492,0),0)),"",OFFSET('HARGA SATUAN'!$E$6,MATCH(RAB!C80,'HARGA SATUAN'!$C$7:$C$1492,0),0))) | G80: =IF(ISERROR(OFFSET('HARGA SATUAN'!$I$6,MATCH(RAB!C80,'HARGA SATUAN'!$C$7:$C$1492,0),0)),0,OFFSET('HARGA SATUAN'!$I$6,MATCH(RAB!C80,'HARGA SATUAN'!$C$7:$C$1492,0),0)) -> 0 | H80: =IF(OR(D80="MDU",D80="MDU-KD"),(IF($O$3="RAB NON MDU","PLN KD",G80*F80)),0) -> 0 | I80: =IF(D80="HDW",G80*F80,0) -> 0 | J80: =IF(D80="JASA",G80*F80,0) -> 0 | K80: =SUM(H80:J80) -> 0
B81: + | C81: F1-3 | D81: =IF(ISERROR(OFFSET('HARGA SATUAN'!$D$6,MATCH(RAB!C81,'HARGA SATUAN'!$C$7:$C$1492,0),0)),"",OFFSET('HARGA SATUAN'!$D$6,MATCH(RAB!C81,'HARGA SATUAN'!$C$7:$C$1492,0),0)) | E81: =IF(B81="+","Unit",IF(ISERROR(OFFSET('HARGA SATUAN'!$E$6,MATCH(RAB!C81,'HARGA SATUAN'!$C$7:$C$1492,0),0)),"",OFFSET('HARGA SATUAN'!$E$6,MATCH(RAB!C81,'HARGA SATUAN'!$C$7:$C$1492,0),0))) -> Unit | F81: =F73 -> 1 | G81: =IF(ISERROR(OFFSET('HARGA SATUAN'!$I$6,MATCH(RAB!C81,'HARGA SATUAN'!$C$7:$C$1492,0),0)),0,OFFSET('HARGA SATUAN'!$I$6,MATCH(RAB!C81,'HARGA SATUAN'!$C$7:$C$1492,0),0)) -> 0 | H81: =IF(OR(D81="MDU",D81="MDU-KD"),(IF($O$3="RAB NON MDU","PLN KD",G81*F81)),0) -> 0 | I81: =IF(D81="HDW",G81*F81,0) -> 0 | J81: =IF(D81="JASA",G81*F81,0) -> 0 | K81: =SUM(H81:J81) -> 0
B82: 1 | C82: Expanding Anchor 10.000 lbs | D82: =IF(ISERROR(OFFSET('HARGA SATUAN'!$D$6,MATCH(RAB!C82,'HARGA SATUAN'!$C$7:$C$1492,0),0)),"",OFFSET('HARGA SATUAN'!$D$6,MATCH(RAB!C82,'HARGA SATUAN'!$C$7:$C$1492,0),0)) -> HDW | E82: =IF(B82="+","Unit",IF(ISERROR(OFFSET('HARGA SATUAN'!$E$6,MATCH(RAB!C82,'HARGA SATUAN'!$C$7:$C$1492,0),0)),"",OFFSET('HARGA SATUAN'!$E$6,MATCH(RAB!C82,'HARGA SATUAN'!$C$7:$C$1492,0),0))) -> Bh | F82: =F81*1 -> 1 | G82: =IF(ISERROR(OFFSET('HARGA SATUAN'!$I$6,MATCH(RAB!C82,'HARGA SATUAN'!$C$7:$C$1492,0),0)),0,OFFSET('HARGA SATUAN'!$I$6,MATCH(RAB!C82,'HARGA SATUAN'!$C$7:$C$1492,0),0)) -> 120900 | H82: =IF(OR(D82="MDU",D82="MDU-KD"),(IF($O$3="RAB NON MDU","PLN KD",G82*F82)),0) -> 0 | I82: =IF(D82="HDW",G82*F82,0) -> 120900 | J82: =IF(D82="JASA",G82*F82,0) -> 0 | K82: =SUM(H82:J82) -> 120900
B83: 2 | C83: Rod Anchor ¾" x 8' | D83: =IF(ISERROR(OFFSET('HARGA SATUAN'!$D$6,MATCH(RAB!C83,'HARGA SATUAN'!$C$7:$C$1492,0),0)),"",OFFSET('HARGA SATUAN'!$D$6,MATCH(RAB!C83,'HARGA SATUAN'!$C$7:$C$1492,0),0)) -> HDW | E83: =IF(B83="+","Unit",IF(ISERROR(OFFSET('HARGA SATUAN'!$E$6,MATCH(RAB!C83,'HARGA SATUAN'!$C$7:$C$1492,0),0)),"",OFFSET('HARGA SATUAN'!$E$6,MATCH(RAB!C83,'HARGA SATUAN'!$C$7:$C$1492,0),0))) -> Bh | F83: =F81*1 -> 1 | G83: =IF(ISERROR(OFFSET('HARGA SATUAN'!$I$6,MATCH(RAB!C83,'HARGA SATUAN'!$C$7:$C$1492,0),0)),0,OFFSET('HARGA SATUAN'!$I$6,MATCH(RAB!C83,'HARGA SATUAN'!$C$7:$C$1492,0),0)) -> 135800 | H83: =IF(OR(D83="MDU",D83="MDU-KD"),(IF($O$3="RAB NON MDU","PLN KD",G83*F83)),0) -> 0 | I83: =IF(D83="HDW",G83*F83,0) -> 135800 | J83: =IF(D83="JASA",G83*F83,0) -> 0 | K83: =SUM(H83:J83) -> 135800
B84: 3 | C84: Kousen | D84: =IF(ISERROR(OFFSET('HARGA SATUAN'!$D$6,MATCH(RAB!C84,'HARGA SATUAN'!$C$7:$C$1492,0),0)),"",OFFSET('HARGA SATUAN'!$D$6,MATCH(RAB!C84,'HARGA SATUAN'!$C$7:$C$1492,0),0)) -> HDW | E84: =IF(B84="+","Unit",IF(ISERROR(OFFSET('HARGA SATUAN'!$E$6,MATCH(RAB!C84,'HARGA SATUAN'!$C$7:$C$1492,0),0)),"",OFFSET('HARGA SATUAN'!$E$6,MATCH(RAB!C84,'HARGA SATUAN'!$C$7:$C$1492,0),0))) -> Bh | F84: =F81*1 -> 1 | G84: =IF(ISERROR(OFFSET('HARGA SATUAN'!$I$6,MATCH(RAB!C84,'HARGA SATUAN'!$C$7:$C$1492,0),0)),0,OFFSET('HARGA SATUAN'!$I$6,MATCH(RAB!C84,'HARGA SATUAN'!$C$7:$C$1492,0),0)) -> 4500 | H84: =IF(OR(D84="MDU",D84="MDU-KD"),(IF($O$3="RAB NON MDU","PLN KD",G84*F84)),0) -> 0 | I84: =IF(D84="HDW",G84*F84,0) -> 4500 | J84: =IF(D84="JASA",G84*F84,0) -> 0 | K84: =SUM(H84:J84) -> 4500
B85: 4 | C85: Upah Pasang Acc.Jar F1-3 | D85: =IF(ISERROR(OFFSET('HARGA SATUAN'!$D$6,MATCH(RAB!C85,'HARGA SATUAN'!$C$7:$C$1492,0),0)),"",OFFSET('HARGA SATUAN'!$D$6,MATCH(RAB!C85,'HARGA SATUAN'!$C$7:$C$1492,0),0)) -> JASA | E85: =IF(B85="+","Unit",IF(ISERROR(OFFSET('HARGA SATUAN'!$E$6,MATCH(RAB!C85,'HARGA SATUAN'!$C$7:$C$1492,0),0)),"",OFFSET('HARGA SATUAN'!$E$6,MATCH(RAB!C85,'HARGA SATUAN'!$C$7:$C$1492,0),0))) -> Unit | F85: =F81*1 -> 1 | G85: =IF(ISERROR(OFFSET('HARGA SATUAN'!$I$6,MATCH(RAB!C85,'HARGA SATUAN'!$C$7:$C$1492,0),0)),0,OFFSET('HARGA SATUAN'!$I$6,MATCH(RAB!C85,'HARGA SATUAN'!$C$7:$C$1492,0),0)) -> 55500 | H85: =IF(OR(D85="MDU",D85="MDU-KD"),(IF($O$3="RAB NON MDU","PLN KD",G85*F85)),0) -> 0 | I85: =IF(D85="HDW",G85*F85,0) -> 0 | J85: =IF(D85="JASA",G85*F85,0) -> 55500 | K85: =SUM(H85:J85) -> 55500
B87: + | C87: CM2-12A | D87: =IF(ISERROR(OFFSET('HARGA SATUAN'!$D$6,MATCH(RAB!C87,'HARGA SATUAN'!$C$7:$C$1492,0),0)),"",OFFSET('HARGA SATUAN'!$D$6,MATCH(RAB!C87,'HARGA SATUAN'!$C$7:$C$1492,0),0)) | E87: =IF(B87="+","Unit",IF(ISERROR(OFFSET('HARGA SATUAN'!$E$6,MATCH(RAB!C87,'HARGA SATUAN'!$C$7:$C$1492,0),0)),"",OFFSET('HARGA SATUAN'!$E$6,MATCH(RAB!C87,'HARGA SATUAN'!$C$7:$C$1492,0),0))) -> Unit | F87: =F73 -> 1 | G87: =IF(ISERROR(OFFSET('HARGA SATUAN'!$I$6,MATCH(RAB!C87,'HARGA SATUAN'!$C$7:$C$1492,0),0)),0,OFFSET('HARGA SATUAN'!$I$6,MATCH(RAB!C87,'HARGA SATUAN'!$C$7:$C$1492,0),0)) -> 0 | H87: =IF(OR(D87="MDU",D87="MDU-KD"),(IF($O$3="RAB NON MDU","PLN KD",G87*F87)),0) -> 0 | I87: =IF(D87="HDW",G87*F87,0) -> 0 | J87: =IF(D87="JASA",G87*F87,0) -> 0 | K87: =SUM(H87:J87) -> 0
B88: 1 | C88: Bimetalic Connector 35 - 240 mm² | D88: =IF(ISERROR(OFFSET('HARGA SATUAN'!$D$6,MATCH(RAB!C88,'HARGA SATUAN'!$C$7:$C$1492,0),0)),"",OFFSET('HARGA SATUAN'!$D$6,MATCH(RAB!C88,'HARGA SATUAN'!$C$7:$C$1492,0),0)) -> HDW | E88: =IF(B88="+","Unit",IF(ISERROR(OFFSET('HARGA SATUAN'!$E$6,MATCH(RAB!C88,'HARGA SATUAN'!$C$7:$C$1492,0),0)),"",OFFSET('HARGA SATUAN'!$E$6,MATCH(RAB!C88,'HARGA SATUAN'!$C$7:$C$1492,0),0))) -> Bh | F88: =F87*1 -> 1 | G88: =IF(ISERROR(OFFSET('HARGA SATUAN'!$I$6,MATCH(RAB!C88,'HARGA SATUAN'!$C$7:$C$1492,0),0)),0,OFFSET('HARGA SATUAN'!$I$6,MATCH(RAB!C88,'HARGA SATUAN'!$C$7:$C$1492,0),0)) -> 47459 | H88: =IF(OR(D88="MDU",D88="MDU-KD"),(IF($O$3="RAB NON MDU","PLN KD",G88*F88)),0) -> 0 | I88: =IF(D88="HDW",G88*F88,0) -> 47459 | J88: =IF(D88="JASA",G88*F88,0) -> 0 | K88: =SUM(H88:J88) -> 47459
B89: 2 | C89: Ground wire Cu 16 mm² | D89: =IF(ISERROR(OFFSET('HARGA SATUAN'!$D$6,MATCH(RAB!C89,'HARGA SATUAN'!$C$7:$C$1492,0),0)),"",OFFSET('HARGA SATUAN'!$D$6,MATCH(RAB!C89,'HARGA SATUAN'!$C$7:$C$1492,0),0)) -> HDW | E89: =IF(B89="+","Unit",IF(ISERROR(OFFSET('HARGA SATUAN'!$E$6,MATCH(RAB!C89,'HARGA SATUAN'!$C$7:$C$1492,0),0)),"",OFFSET('HARGA SATUAN'!$E$6,MATCH(RAB!C89,'HARGA SATUAN'!$C$7:$C$1492,0),0))) -> Mtr | F89: =F87*1 -> 1 | G89: =IF(ISERROR(OFFSET('HARGA SATUAN'!$I$6,MATCH(RAB!C89,'HARGA SATUAN'!$C$7:$C$1492,0),0)),0,OFFSET('HARGA SATUAN'!$I$6,MATCH(RAB!C89,'HARGA SATUAN'!$C$7:$C$1492,0),0)) -> 30000 | H89: =IF(OR(D89="MDU",D89="MDU-KD"),(IF($O$3="RAB NON MDU","PLN KD",G89*F89)),0) -> 0 | I89: =IF(D89="HDW",G89*F89,0) -> 30000 | J89: =IF(D89="JASA",G89*F89,0) -> 0 | K89: =SUM(H89:J89) -> 30000
B90: 3 | C90: Ground rod & Washer | D90: =IF(ISERROR(OFFSET('HARGA SATUAN'!$D$6,MATCH(RAB!C90,'HARGA SATUAN'!$C$7:$C$1492,0),0)),"",OFFSET('HARGA SATUAN'!$D$6,MATCH(RAB!C90,'HARGA SATUAN'!$C$7:$C$1492,0),0)) -> HDW | E90: =IF(B90="+","Unit",IF(ISERROR(OFFSET('HARGA SATUAN'!$E$6,MATCH(RAB!C90,'HARGA SATUAN'!$C$7:$C$1492,0),0)),"",OFFSET('HARGA SATUAN'!$E$6,MATCH(RAB!C90,'HARGA SATUAN'!$C$7:$C$1492,0),0))) -> Bh | F90: =F87*1 -> 1 | G90: =IF(ISERROR(OFFSET('HARGA SATUAN'!$I$6,MATCH(RAB!C90,'HARGA SATUAN'!$C$7:$C$1492,0),0)),0,OFFSET('HARGA SATUAN'!$I$6,MATCH(RAB!C90,'HARGA SATUAN'!$C$7:$C$1492,0),0)) -> 9500 | H90: =IF(OR(D90="MDU",D90="MDU-KD"),(IF($O$3="RAB NON MDU","PLN KD",G90*F90)),0) -> 0 | I90: =IF(D90="HDW",G90*F90,0) -> 9500 | J90: =IF(D90="JASA",G90*F90,0) -> 0 | K90: =SUM(H90:J90) -> 9500
B91: 4 | C91: Upah Pasang Acc.Jar M2-12A | D91: =IF(ISERROR(OFFSET('HARGA SATUAN'!$D$6,MATCH(RAB!C91,'HARGA SATUAN'!$C$7:$C$1492,0),0)),"",OFFSET('HARGA SATUAN'!$D$6,MATCH(RAB!C91,'HARGA SATUAN'!$C$7:$C$1492,0),0)) -> JASA | E91: =IF(B91="+","Unit",IF(ISERROR(OFFSET('HARGA SATUAN'!$E$6,MATCH(RAB!C91,'HARGA SATUAN'!$C$7:$C$1492,0),0)),"",OFFSET('HARGA SATUAN'!$E$6,MATCH(RAB!C91,'HARGA SATUAN'!$C$7:$C$1492,0),0))) -> Unit | F91: =F87*1 -> 1 | G91: =IF(ISERROR(OFFSET('HARGA SATUAN'!$I$6,MATCH(RAB!C91,'HARGA SATUAN'!$C$7:$C$1492,0),0)),0,OFFSET('HARGA SATUAN'!$I$6,MATCH(RAB!C91,'HARGA SATUAN'!$C$7:$C$1492,0),0)) -> 21200 | H91: =IF(OR(D91="MDU",D91="MDU-KD"),(IF($O$3="RAB NON MDU","PLN KD",G91*F91)),0) -> 0 | I91: =IF(D91="HDW",G91*F91,0) -> 0 | J91: =IF(D91="JASA",G91*F91,0) -> 21200 | K91: =SUM(H91:J91) -> 21200
B93: III | C93: PEMASANGAN TRAFO | D93: =IF(ISERROR(OFFSET('HARGA SATUAN'!$D$6,MATCH(RAB!C93,'HARGA SATUAN'!$C$7:$C$1492,0),0)),"",OFFSET('HARGA SATUAN'!$D$6,MATCH(RAB!C93,'HARGA SATUAN'!$C$7:$C$1492,0),0)) | E93: =IF(B93="+","Unit",IF(ISERROR(OFFSET('HARGA SATUAN'!$E$6,MATCH(RAB!C93,'HARGA SATUAN'!$C$7:$C$1492,0),0)),"",OFFSET('HARGA SATUAN'!$E$6,MATCH(RAB!C93,'HARGA SATUAN'!$C$7:$C$1492,0),0))) | G93: =IF(ISERROR(OFFSET('HARGA SATUAN'!$I$6,MATCH(RAB!C93,'HARGA SATUAN'!$C$7:$C$1492,0),0)),0,OFFSET('HARGA SATUAN'!$I$6,MATCH(RAB!C93,'HARGA SATUAN'!$C$7:$C$1492,0),0)) -> 0 | H93: =IF(OR(D93="MDU",D93="MDU-KD"),(IF($O$3="RAB NON MDU","PLN KD",G93*F93)),0) -> 0 | I93: =IF(D93="HDW",G93*F93,0) -> 0 | J93: =IF(D93="JASA",G93*F93,0) -> 0 | K93: =SUM(H93:J93) -> 0
D94: =IF(ISERROR(OFFSET('HARGA SATUAN'!$D$6,MATCH(RAB!C94,'HARGA SATUAN'!$C$7:$C$1492,0),0)),"",OFFSET('HARGA SATUAN'!$D$6,MATCH(RAB!C94,'HARGA SATUAN'!$C$7:$C$1492,0),0)) | E94: =IF(B94="+","Unit",IF(ISERROR(OFFSET('HARGA SATUAN'!$E$6,MATCH(RAB!C94,'HARGA SATUAN'!$C$7:$C$1492,0),0)),"",OFFSET('HARGA SATUAN'!$E$6,MATCH(RAB!C94,'HARGA SATUAN'!$C$7:$C$1492,0),0))) | G94: =IF(ISERROR(OFFSET('HARGA SATUAN'!$I$6,MATCH(RAB!C94,'HARGA SATUAN'!$C$7:$C$1492,0),0)),0,OFFSET('HARGA SATUAN'!$I$6,MATCH(RAB!C94,'HARGA SATUAN'!$C$7:$C$1492,0),0)) -> 0 | H94: =IF(OR(D94="MDU",D94="MDU-KD"),(IF($O$3="RAB NON MDU","PLN KD",G94*F94)),0) -> 0 | I94: =IF(D94="HDW",G94*F94,0) -> 0 | J94: =IF(D94="JASA",G94*F94,0) -> 0 | K94: =SUM(H94:J94) -> 0
B95: + | C95: Trafo 3 Fasa 100 KVA 2 Tiang (G313) | D95: =IF(ISERROR(OFFSET('HARGA SATUAN'!$D$6,MATCH(RAB!C95,'HARGA SATUAN'!$C$7:$C$1492,0),0)),"",OFFSET('HARGA SATUAN'!$D$6,MATCH(RAB!C95,'HARGA SATUAN'!$C$7:$C$1492,0),0)) | E95: =IF(B95="+","Unit",IF(ISERROR(OFFSET('HARGA SATUAN'!$E$6,MATCH(RAB!C95,'HARGA SATUAN'!$C$7:$C$1492,0),0)),"",OFFSET('HARGA SATUAN'!$E$6,MATCH(RAB!C95,'HARGA SATUAN'!$C$7:$C$1492,0),0))) -> Unit | F95: 1 | G95: =IF(ISERROR(OFFSET('HARGA SATUAN'!$I$6,MATCH(RAB!C95,'HARGA SATUAN'!$C$7:$C$1492,0),0)),0,OFFSET('HARGA SATUAN'!$I$6,MATCH(RAB!C95,'HARGA SATUAN'!$C$7:$C$1492,0),0)) -> 0 | H95: =IF(OR(D95="MDU",D95="MDU-KD"),(IF($O$3="RAB NON MDU","PLN KD",G95*F95)),0) -> 0 | I95: =IF(D95="HDW",G95*F95,0) -> 0 | J95: =IF(D95="JASA",G95*F95,0) -> 0 | K95: =SUM(H95:J95) -> 0
B96: 1 | C96: Trafo 3 phasa 100 kVA YNyn0 | D96: =IF(ISERROR(OFFSET('HARGA SATUAN'!$D$6,MATCH(RAB!C96,'HARGA SATUAN'!$C$7:$C$1492,0),0)),"",OFFSET('HARGA SATUAN'!$D$6,MATCH(RAB!C96,'HARGA SATUAN'!$C$7:$C$1492,0),0)) -> MDU-KD | E96: =IF(B96="+","Unit",IF(ISERROR(OFFSET('HARGA SATUAN'!$E$6,MATCH(RAB!C96,'HARGA SATUAN'!$C$7:$C$1492,0),0)),"",OFFSET('HARGA SATUAN'!$E$6,MATCH(RAB!C96,'HARGA SATUAN'!$C$7:$C$1492,0),0))) -> Bh | F96: 1 | G96: =IF(ISERROR(OFFSET('HARGA SATUAN'!$I$6,MATCH(RAB!C96,'HARGA SATUAN'!$C$7:$C$1492,0),0)),0,OFFSET('HARGA SATUAN'!$I$6,MATCH(RAB!C96,'HARGA SATUAN'!$C$7:$C$1492,0),0)) -> 56838600 | H96: =IF(OR(D96="MDU",D96="MDU-KD"),(IF($O$3="RAB NON MDU","PLN KD",G96*F96)),0) -> 56838600 | I96: =IF(D96="HDW",G96*F96,0) -> 0 | J96: =IF(D96="JASA",G96*F96,0) -> 0 | K96: =SUM(H96:J96) -> 56838600
B97: 2 | C97: Jumper Wire : | D97: =IF(ISERROR(OFFSET('HARGA SATUAN'!$D$6,MATCH(RAB!C97,'HARGA SATUAN'!$C$7:$C$1492,0),0)),"",OFFSET('HARGA SATUAN'!$D$6,MATCH(RAB!C97,'HARGA SATUAN'!$C$7:$C$1492,0),0)) | E97: =IF(B97="+","Unit",IF(ISERROR(OFFSET('HARGA SATUAN'!$E$6,MATCH(RAB!C97,'HARGA SATUAN'!$C$7:$C$1492,0),0)),"",OFFSET('HARGA SATUAN'!$E$6,MATCH(RAB!C97,'HARGA SATUAN'!$C$7:$C$1492,0),0))) | G97: =IF(ISERROR(OFFSET('HARGA SATUAN'!$I$6,MATCH(RAB!C97,'HARGA SATUAN'!$C$7:$C$1492,0),0)),0,OFFSET('HARGA SATUAN'!$I$6,MATCH(RAB!C97,'HARGA SATUAN'!$C$7:$C$1492,0),0)) -> 0 | H97: =IF(OR(D97="MDU",D97="MDU-KD"),(IF($O$3="RAB NON MDU","PLN KD",G97*F97)),0) -> 0 | I97: =IF(D97="HDW",G97*F97,0) -> 0 | J97: =IF(D97="JASA",G97*F97,0) -> 0 | K97: =SUM(H97:J97) -> 0
C98: AAAC 70 mm² | D98: =IF(ISERROR(OFFSET('HARGA SATUAN'!$D$6,MATCH(RAB!C98,'HARGA SATUAN'!$C$7:$C$1492,0),0)),"",OFFSET('HARGA SATUAN'!$D$6,MATCH(RAB!C98,'HARGA SATUAN'!$C$7:$C$1492,0),0)) -> MDU-KD | E98: =IF(B98="+","Unit",IF(ISERROR(OFFSET('HARGA SATUAN'!$E$6,MATCH(RAB!C98,'HARGA SATUAN'!$C$7:$C$1492,0),0)),"",OFFSET('HARGA SATUAN'!$E$6,MATCH(RAB!C98,'HARGA SATUAN'!$C$7:$C$1492,0),0))) -> Mtr | F98: 9 | G98: =IF(ISERROR(OFFSET('HARGA SATUAN'!$I$6,MATCH(RAB!C98,'HARGA SATUAN'!$C$7:$C$1492,0),0)),0,OFFSET('HARGA SATUAN'!$I$6,MATCH(RAB!C98,'HARGA SATUAN'!$C$7:$C$1492,0),0)) -> 14200 | H98: =IF(OR(D98="MDU",D98="MDU-KD"),(IF($O$3="RAB NON MDU","PLN KD",G98*F98)),0) -> 127800 | I98: =IF(D98="HDW",G98*F98,0) -> 0 | J98: =IF(D98="JASA",G98*F98,0) -> 0 | K98: =SUM(H98:J98) -> 127800
C99: NFA2X-T 3 x 70 + N 50 mm² | D99: =IF(ISERROR(OFFSET('HARGA SATUAN'!$D$6,MATCH(RAB!C99,'HARGA SATUAN'!$C$7:$C$1492,0),0)),"",OFFSET('HARGA SATUAN'!$D$6,MATCH(RAB!C99,'HARGA SATUAN'!$C$7:$C$1492,0),0)) | E99: =IF(B99="+","Unit",IF(ISERROR(OFFSET('HARGA SATUAN'!$E$6,MATCH(RAB!C99,'HARGA SATUAN'!$C$7:$C$1492,0),0)),"",OFFSET('HARGA SATUAN'!$E$6,MATCH(RAB!C99,'HARGA SATUAN'!$C$7:$C$1492,0),0))) | F99: 3 | G99: =IF(ISERROR(OFFSET('HARGA SATUAN'!$I$6,MATCH(RAB!C99,'HARGA SATUAN'!$C$7:$C$1492,0),0)),0,OFFSET('HARGA SATUAN'!$I$6,MATCH(RAB!C99,'HARGA SATUAN'!$C$7:$C$1492,0),0)) -> 0 | H99: =IF(OR(D99="MDU",D99="MDU-KD"),(IF($O$3="RAB NON MDU","PLN KD",G99*F99)),0) -> 0 | I99: =IF(D99="HDW",G99*F99,0) -> 0 | J99: =IF(D99="JASA",G99*F99,0) -> 0 | K99: =SUM(H99:J99) -> 0 | L99: =PROPER([94]!terbilang(K166)) -> #NAME?
B100: 3 | C100: Lightning Arester (Polymer) 21 KV, 10 KA | D100: =IF(ISERROR(OFFSET('HARGA SATUAN'!$D$6,MATCH(RAB!C100,'HARGA SATUAN'!$C$7:$C$1492,0),0)),"",OFFSET('HARGA SATUAN'!$D$6,MATCH(RAB!C100,'HARGA SATUAN'!$C$7:$C$1492,0),0)) -> MDU-KD | E100: =IF(B100="+","Unit",IF(ISERROR(OFFSET('HARGA SATUAN'!$E$6,MATCH(RAB!C100,'HARGA SATUAN'!$C$7:$C$1492,0),0)),"",OFFSET('HARGA SATUAN'!$E$6,MATCH(RAB!C100,'HARGA SATUAN'!$C$7:$C$1492,0),0))) -> Bh | F100: 3 | G100: =IF(ISERROR(OFFSET('HARGA SATUAN'!$I$6,MATCH(RAB!C100,'HARGA SATUAN'!$C$7:$C$1492,0),0)),0,OFFSET('HARGA SATUAN'!$I$6,MATCH(RAB!C100,'HARGA SATUAN'!$C$7:$C$1492,0),0)) -> 725900 | H100: =IF(OR(D100="MDU",D100="MDU-KD"),(IF($O$3="RAB NON MDU","PLN KD",G100*F100)),0) -> 2177700 | I100: =IF(D100="HDW",G100*F100,0) -> 0 | J100: =IF(D100="JASA",G100*F100,0) -> 0 | K100: =SUM(H100:J100) -> 2177700
B101: 4 | C101: FCO Polymer | D101: =IF(ISERROR(OFFSET('HARGA SATUAN'!$D$6,MATCH(RAB!C101,'HARGA SATUAN'!$C$7:$C$1492,0),0)),"",OFFSET('HARGA SATUAN'!$D$6,MATCH(RAB!C101,'HARGA SATUAN'!$C$7:$C$1492,0),0)) -> MDU-KD | E101: =IF(B101="+","Unit",IF(ISERROR(OFFSET('HARGA SATUAN'!$E$6,MATCH(RAB!C101,'HARGA SATUAN'!$C$7:$C$1492,0),0)),"",OFFSET('HARGA SATUAN'!$E$6,MATCH(RAB!C101,'HARGA SATUAN'!$C$7:$C$1492,0),0))) -> Bh | F101: 3 | G101: =IF(ISERROR(OFFSET('HARGA SATUAN'!$I$6,MATCH(RAB!C101,'HARGA SATUAN'!$C$7:$C$1492,0),0)),0,OFFSET('HARGA SATUAN'!$I$6,MATCH(RAB!C101,'HARGA SATUAN'!$C$7:$C$1492,0),0)) -> 848250 | H101: =IF(OR(D101="MDU",D101="MDU-KD"),(IF($O$3="RAB NON MDU","PLN KD",G101*F101)),0) -> 2544750 | I101: =IF(D101="HDW",G101*F101,0) -> 0 | J101: =IF(D101="JASA",G101*F101,0) -> 0 | K101: =SUM(H101:J101) -> 2544750
B102: 5 | C102: Fuse Link 6 A | D102: =IF(ISERROR(OFFSET('HARGA SATUAN'!$D$6,MATCH(RAB!C102,'HARGA SATUAN'!$C$7:$C$1492,0),0)),"",OFFSET('HARGA SATUAN'!$D$6,MATCH(RAB!C102,'HARGA SATUAN'!$C$7:$C$1492,0),0)) -> HDW | E102: =IF(B102="+","Unit",IF(ISERROR(OFFSET('HARGA SATUAN'!$E$6,MATCH(RAB!C102,'HARGA SATUAN'!$C$7:$C$1492,0),0)),"",OFFSET('HARGA SATUAN'!$E$6,MATCH(RAB!C102,'HARGA SATUAN'!$C$7:$C$1492,0),0))) -> Bh | F102: 3 | G102: =IF(ISERROR(OFFSET('HARGA SATUAN'!$I$6,MATCH(RAB!C102,'HARGA SATUAN'!$C$7:$C$1492,0),0)),0,OFFSET('HARGA SATUAN'!$I$6,MATCH(RAB!C102,'HARGA SATUAN'!$C$7:$C$1492,0),0)) -> 18000 | H102: =IF(OR(D102="MDU",D102="MDU-KD"),(IF($O$3="RAB NON MDU","PLN KD",G102*F102)),0) -> 0 | I102: =IF(D102="HDW",G102*F102,0) -> 54000 | J102: =IF(D102="JASA",G102*F102,0) -> 0 | K102: =SUM(H102:J102) -> 54000
B103: 6 | C103: Sepatu Kabel AL/CU Ring-70 mm² | D103: =IF(ISERROR(OFFSET('HARGA SATUAN'!$D$6,MATCH(RAB!C103,'HARGA SATUAN'!$C$7:$C$1492,0),0)),"",OFFSET('HARGA SATUAN'!$D$6,MATCH(RAB!C103,'HARGA SATUAN'!$C$7:$C$1492,0),0)) | E103: =IF(B103="+","Unit",IF(ISERROR(OFFSET('HARGA SATUAN'!$E$6,MATCH(RAB!C103,'HARGA SATUAN'!$C$7:$C$1492,0),0)),"",OFFSET('HARGA SATUAN'!$E$6,MATCH(RAB!C103,'HARGA SATUAN'!$C$7:$C$1492,0),0))) | F103: 13 | G103: =IF(ISERROR(OFFSET('HARGA SATUAN'!$I$6,MATCH(RAB!C103,'HARGA SATUAN'!$C$7:$C$1492,0),0)),0,OFFSET('HARGA SATUAN'!$I$6,MATCH(RAB!C103,'HARGA SATUAN'!$C$7:$C$1492,0),0)) -> 0 | H103: =IF(OR(D103="MDU",D103="MDU-KD"),(IF($O$3="RAB NON MDU","PLN KD",G103*F103)),0) -> 0 | I103: =IF(D103="HDW",G103*F103,0) -> 0 | J103: =IF(D103="JASA",G103*F103,0) -> 0 | K103: =SUM(H103:J103) -> 0
B104: 7 | C104: Bolt Machine / Bolt cariage ½" x ¾" | D104: =IF(ISERROR(OFFSET('HARGA SATUAN'!$D$6,MATCH(RAB!C104,'HARGA SATUAN'!$C$7:$C$1492,0),0)),"",OFFSET('HARGA SATUAN'!$D$6,MATCH(RAB!C104,'HARGA SATUAN'!$C$7:$C$1492,0),0)) -> HDW | E104: =IF(B104="+","Unit",IF(ISERROR(OFFSET('HARGA SATUAN'!$E$6,MATCH(RAB!C104,'HARGA SATUAN'!$C$7:$C$1492,0),0)),"",OFFSET('HARGA SATUAN'!$E$6,MATCH(RAB!C104,'HARGA SATUAN'!$C$7:$C$1492,0),0))) -> Bh | F104: 28 | G104: =IF(ISERROR(OFFSET('HARGA SATUAN'!$I$6,MATCH(RAB!C104,'HARGA SATUAN'!$C$7:$C$1492,0),0)),0,OFFSET('HARGA SATUAN'!$I$6,MATCH(RAB!C104,'HARGA SATUAN'!$C$7:$C$1492,0),0)) -> 7938 | H104: =IF(OR(D104="MDU",D104="MDU-KD"),(IF($O$3="RAB NON MDU","PLN KD",G104*F104)),0) -> 0 | I104: =IF(D104="HDW",G104*F104,0) -> 222264 | J104: =IF(D104="JASA",G104*F104,0) -> 0 | K104: =SUM(H104:J104) -> 222264
B105: 8 | C105: Bracket band segment,vertikal plat ( Hot dip galvanis ) | D105: =IF(ISERROR(OFFSET('HARGA SATUAN'!$D$6,MATCH(RAB!C105,'HARGA SATUAN'!$C$7:$C$1492,0),0)),"",OFFSET('HARGA SATUAN'!$D$6,MATCH(RAB!C105,'HARGA SATUAN'!$C$7:$C$1492,0),0)) -> HDW | E105: =IF(B105="+","Unit",IF(ISERROR(OFFSET('HARGA SATUAN'!$E$6,MATCH(RAB!C105,'HARGA SATUAN'!$C$7:$C$1492,0),0)),"",OFFSET('HARGA SATUAN'!$E$6,MATCH(RAB!C105,'HARGA SATUAN'!$C$7:$C$1492,0),0))) -> Bh | F105: 2 | G105: =IF(ISERROR(OFFSET('HARGA SATUAN'!$I$6,MATCH(RAB!C105,'HARGA SATUAN'!$C$7:$C$1492,0),0)),0,OFFSET('HARGA SATUAN'!$I$6,MATCH(RAB!C105,'HARGA SATUAN'!$C$7:$C$1492,0),0)) -> 404600 | H105: =IF(OR(D105="MDU",D105="MDU-KD"),(IF($O$3="RAB NON MDU","PLN KD",G105*F105)),0) -> 0 | I105: =IF(D105="HDW",G105*F105,0) -> 809200 | J105: =IF(D105="JASA",G105*F105,0) -> 0 | K105: =SUM(H105:J105) -> 809200
B106: 9 | C106: Compresion Conector H type 70 mm² / 70 mm² | D106: =IF(ISERROR(OFFSET('HARGA SATUAN'!$D$6,MATCH(RAB!C106,'HARGA SATUAN'!$C$7:$C$1492,0),0)),"",OFFSET('HARGA SATUAN'!$D$6,MATCH(RAB!C106,'HARGA SATUAN'!$C$7:$C$1492,0),0)) -> HDW | E106: =IF(B106="+","Unit",IF(ISERROR(OFFSET('HARGA SATUAN'!$E$6,MATCH(RAB!C106,'HARGA SATUAN'!$C$7:$C$1492,0),0)),"",OFFSET('HARGA SATUAN'!$E$6,MATCH(RAB!C106,'HARGA SATUAN'!$C$7:$C$1492,0),0))) -> Bh | F106: 3 | G106: =IF(ISERROR(OFFSET('HARGA SATUAN'!$I$6,MATCH(RAB!C106,'HARGA SATUAN'!$C$7:$C$1492,0),0)),0,OFFSET('HARGA SATUAN'!$I$6,MATCH(RAB!C106,'HARGA SATUAN'!$C$7:$C$1492,0),0)) -> 15900 | H106: =IF(OR(D106="MDU",D106="MDU-KD"),(IF($O$3="RAB NON MDU","PLN KD",G106*F106)),0) -> 0 | I106: =IF(D106="HDW",G106*F106,0) -> 47700 | J106: =IF(D106="JASA",G106*F106,0) -> 0 | K106: =SUM(H106:J106) -> 47700
...

Sheet GAMBAR
W2: PT. PLN (PERSERO) UP3 DEMAK
W4: Keterangan Gambar :
W5: No | X5: Nama Material | AA5: Baru | AC5: Eksisting
W6: 1 | X6: Tiang Beton
E7: KOORDINAT : -6.923885, 110.633238 | W7: 2 | X7: Tiang Besi
W8: 3 | X8: JTM 3 Fasa
W9: 4 | X9: JTM 1 Fasa
W10: 5 | X10: JTR 1 Fasa Only / UB
W11: 6 | X11: JTR 3 Fasa Only / UB
W12: 7 | X12: Trafo 1 Fasa
W13: 8 | X13: Trafo 3 Fasa
W14: 9 | X14: Fuse Cut Out
W15: 10 | X15: ABSW
W16: 11 | X16: Vang Net
W17: 12 | X17: Schoor
W18: 13
W20: Bongkar Pasang Konstruksi :
W21: Pasang | AA21: Bongkar
W22: CJ5-T | Y22: 3 | Z22: U
W23: CJ6-T | Y23: 4 | Z23: U
W24: MJ6-T | Y24: 1 | Z24: U
W42: Keterangan Tambahan :
W44: Golongan
W45: No. Gambar | Y45: 1 | AB45: Lembar | AD45: dr
W46: Gambar dari | AB46: Skala
W47: Perihal:
W48: =RAB!G6 -> AGR UD NURA JAYA
W52: Digambar | Y52: Staff Teknik
W53: Diperiksa | Y53: TL. Teknik
W54: Diketahui | Y54: MULP
W55: Disetujui

Sheet SLD
D4: SINGLE LINE DIAGRAM LOKASI PELANGGAN

Sheet PETA
C3: PETA LOKASI PELANGGAN

Sheet PDL
A1: 1
A2: 3
C4: 1
C5: 3
E7: 1
E8: 3
G10: 3
G11: 1
I13: 3
I14: 1
K16: 3
K17: 1
M19: 3
M20: 1
O22: 3
O23: 1
Q25: 3
Q26: 1
S28: 3
S29: 1
U31: 3
U32: 1
